Workbook
Name Выбранный_год: 'Финансовый отчет'!$K$2
Name Последние_метрики: OFFSET('Anglo American Platinum'!$B$6:$B$23,0,0,COUNTA('Anglo American Platinum'!$B$6:$B$23))
Name Последние_метрики: OFFSET('Impala Platinum'!$B$6:$B$21,0,0,COUNTA('Impala Platinum'!$B$6:$B$21))
Name Последние_метрики: OFFSET(Vale!$B$6:$B$21,0,0,COUNTA(Vale!$B$6:$B$21))
Name Последние_метрики: OFFSET(Норникель!$B$6:$B$24,0,0,COUNTA(Норникель!$B$6:$B$24))
Name Прошедшие_годы: OFFSET('Anglo American Platinum'!$B$3:$G$3,0,1,1,COUNTA('Anglo American Platinum'!$B$3:$G$3)-1)
Name Прошедшие_годы: OFFSET('Impala Platinum'!$B$3:$F$3,0,1,1,COUNTA('Impala Platinum'!$B$3:$F$3)-1)
Name Прошедшие_годы: OFFSET(Vale!$B$3:$F$3,0,1,1,COUNTA(Vale!$B$3:$F$3)-1)
Name Прошедшие_годы: OFFSET(Норникель!$B$3:$G$3,0,1,1,COUNTA(Норникель!$B$3:$G$3)-1)

Sheet Финансовый отчет
B2: ОТЧЁТ О ПРИБЫЛЯХ И УБЫТКАХ | K2: 2024
B3: Горно-металлургическая компания "Норильский никель"
B5: КЛЮЧЕВЫЕ МЕТРИКИ
B7: =Расчеты!B8 -> Итого выручка | D7: =Расчеты!B9 -> Валовая прибыль | F7: =Расчеты!B10 -> Прибыль от операционной деятельности | H7: =Расчеты!B11 -> Прибыль до налогообложения | J7: =Расчеты!B12 -> Прибыль за год
B8: =IFERROR(Расчеты!G8,"") | D8: =IFERROR(Расчеты!G9,"") | F8: =IFERROR(Расчеты!G10,"") | H8: =IFERROR(Расчеты!G11,"") | J8: =IFERROR(Расчеты!G12,"")
B9: =Расчеты!H8 | D9: =Расчеты!H9 | F9: =Расчеты!H10 | H9: =Расчеты!H11 | J9: =Расчеты!H12
B13: ВСЕ МЕТРИКИ
B15: МЕТРИКА | D15: ="ТЕКУЩИЙ ГОД ("&Выбранный_год&")" -> ТЕКУЩИЙ ГОД (2024) | F15: ="ПРОШЕДШИЙ ГОД ("&Выбранный_год-1&")" -> ПРОШЕДШИЙ ГОД (2023) | H15: ИЗМЕНЕНИЕ В % | I15: ТЕНДЕНЦИЯ ЗА 4 года
B16: Выручка: | H16: =IFERROR(D16/F16-1,"")
B17: =Расчеты!B16 -> Выручка от реализации металлов | D17: =IF($B17="","",Расчеты!G16) -> #N/A | F17: =IF($B17="","",Расчеты!F16) -> #N/A | H17: =IFERROR(D17/F17-1,"")
B18: =Расчеты!B17 -> Выручка от прочей реализации | D18: =IF($B18="","",Расчеты!G17) -> #N/A | F18: =IF($B18="","",Расчеты!F17) -> #N/A | H18: =IFERROR(D18/F18-1,"")
B19: =Расчеты!B18 -> Итого выручка | D19: =IF($B19="","",Расчеты!G18) -> #N/A | F19: =IF($B19="","",Расчеты!F18) -> #N/A | H19: =IFERROR(D19/F19-1,"")
B20: =Расчеты!B19 -> Себестоимость реализованных металлов | D20: =IF($B20="","",Расчеты!G19) -> #N/A | F20: =IF($B20="","",Расчеты!F19) -> #N/A | H20: =IFERROR(D20/F20-1,"")
B21: =Расчеты!B20 -> Себестоимость прочей реализации | D21: =IF($B21="","",Расчеты!G20) -> #N/A | F21: =IF($B21="","",Расчеты!F20) -> #N/A | H21: =IFERROR(D21/F21-1,"")
B22: =Расчеты!B21 -> Валовая прибыль | D22: =IF($B22="","",Расчеты!G21) -> #N/A | F22: =IF($B22="","",Расчеты!F21) -> #N/A | H22: =IFERROR(D22/F22-1,"")
B23: =Расчеты!B22 -> Административные расходы | D23: =IF($B23="","",Расчеты!G22) -> #N/A | F23: =IF($B23="","",Расчеты!F22) -> #N/A | H23: =IFERROR(D23/F23-1,"")
B24: =Расчеты!B23 -> Коммерческие расходы | D24: =IF($B24="","",Расчеты!G23) -> #N/A | F24: =IF($B24="","",Расчеты!F23) -> #N/A | H24: =IFERROR(D24/F24-1,"")
B25: =Расчеты!B24 -> Убыток от обесценения нефинансовых активов, нетто | D25: =IF($B25="","",Расчеты!G24) -> #N/A | F25: =IF($B25="","",Расчеты!F24) -> #N/A | H25: =IFERROR(D25/F25-1,"")
B26: =Расчеты!B26 -> Прочие операционные расходы, нетто | D26: =IF($B26="","",Расчеты!G26) -> #N/A | F26: =IF($B26="","",Расчеты!F26) -> #N/A | H26: =IFERROR(D26/F26-1,"")
B27: =Расчеты!B27 -> Прибыль от операционной деятельности | D27: =IF($B27="","",Расчеты!G27) -> #N/A | F27: =IF($B27="","",Расчеты!F27) -> #N/A | H27: =IFERROR(D27/F27-1,"")
B28: =Расчеты!B28 -> (Отрицательные)/положительные курсовые разницы, нетто | D28: =IF($B28="","",Расчеты!G28) -> #N/A | F28: =IF($B28="","",Расчеты!F28) -> #N/A | H28: =IFERROR(D28/F28-1,"")
B29: =Расчеты!B30 -> Финансовые расходы, нетто | D29: =IF($B29="","",Расчеты!G30) -> #N/A | F29: =IF($B29="","",Расчеты!F30) -> #N/A | H29: =IFERROR(D29/F29-1,"")
B30: =Расчеты!B31 -> Прибыль/(убыток) от выбытия дочерних организаций и зарубежных совместных операций | D30: =IF($B30="","",Расчеты!G31) -> #N/A | F30: =IF($B30="","",Расчеты!F31) -> #N/A | H30: =IFERROR(D30/F30-1,"")
B31: =Расчеты!B33 -> Прибыль от инвестиционной деятельности, нетто | D31: =IF($B31="","",Расчеты!G33) -> #N/A | F31: =IF($B31="","",Расчеты!F33) -> #N/A | H31: =IFERROR(D31/F31-1,"")
B32: =Расчеты!B34 -> Прибыль до налогообложения | D32: =IF($B32="","",Расчеты!G34) -> #N/A | F32: =IF($B32="","",Расчеты!F34) -> #N/A | H32: =IFERROR(D32/F32-1,"")
B33: =Расчеты!B35 -> Расходы по налогу на прибыль | D33: =IF($B33="","",Расчеты!G35) -> #N/A | F33: =IF($B33="","",Расчеты!F35) -> #N/A | H33: =IFERROR(D33/F33-1,"")
B34: =Расчеты!B36 -> Прибыль за год | D34: =IF($B34="","",Расчеты!G36) -> #N/A | F34: =IF($B34="","",Расчеты!F36) -> #N/A | H34: =IFERROR(D34/F34-1,"")

Sheet Коэффициенты
B2: КОЭФФИЦИЕНТЫ | C2: Норникель | G2: #VALUE! | H2: Vale | L2: #VALUE! | M2: Anglo American Platinum | Q2: #VALUE! | R2: Impala Platinum | V2: #VALUE! | W2: Комментарии
C3: 2021 | D3: 2022 | E3: 2023 | F3: 2024 | H3: 2021 | I3: 2022 | J3: 2023 | K3: 2024 | M3: 2021 | N3: 2022 | O3: 2023 | P3: 2024 | R3: 2021 | S3: 2022 | T3: 2023 | U3: 2024
B5: Коэффициенты ликвидности
B6: Оборотные активы | C6: =Норникель!C62 -> 9870 | D6: =Норникель!D62 -> 8403 | E6: =Норникель!E62 -> 7342 | F6: =Норникель!F62 -> 6845 | H6: =Vale!C56 -> 21384 | I6: =Vale!D56 -> 15526 | J6: =Vale!E56 -> 14767 | K6: =Vale!F56 -> 13481 | M6: ='Anglo American Platinum'!I62 -> 7169.5531 | N6: ='Anglo American Platinum'!J62 -> 5513.8291 | O6: ='Anglo American Platinum'!K62 -> 3691.4058 | P6: ='Anglo American Platinum'!L62 -> 3211.105 | R6: ='Impala Platinum'!I62 -> 3957.5419 | S6: ='Impala Platinum'!J62 -> 3698.8322 | T6: ='Impala Platinum'!K62 -> 3594.8011 | U6: ='Impala Platinum'!L62 -> 2781.0335
B7: Краткосрочные обязательства | C7: =Норникель!C98 -> 8083 | D7: =Норникель!D98 -> 7689 | E7: =Норникель!E98 -> 8831 | F7: =Норникель!F98 -> 5919 | H7: =Vale!C87 -> 14843 | I7: =Vale!D87 -> 13891 | J7: =Vale!E87 -> 14094 | K7: =Vale!F87 -> 13090 | M7: ='Anglo American Platinum'!I81 -> 3943.2961 | N7: ='Anglo American Platinum'!J81 -> 3568.3467 | O7: ='Anglo American Platinum'!K81 -> 2490.1326 | P7: ='Anglo American Platinum'!L81 -> 2479.4393 | R7: ='Impala Platinum'!I90 -> 1242.5279 | S7: ='Impala Platinum'!J90 -> 1019.4837 | T7: ='Impala Platinum'!K90 -> 937.50663 | U7: ='Impala Platinum'!L90 -> 926.0033
B8: Оборотный капитал | C8: =C6-C7 -> 1787 | D8: =D6-D7 -> 714 | E8: =E6-E7 -> -1489 | F8: =F6-F7 -> 926 | H8: =H6-H7 -> 6541 | I8: =I6-I7 -> 1635 | J8: =J6-J7 -> 673 | K8: =K6-K7 -> 391 | M8: =M6-M7 -> 3226.257 | N8: =N6-N7 -> 1945.4825 | O8: =O6-O7 -> 1201.2732 | P8: =P6-P7 -> 731.66575 | R8: =R6-R7 -> 2715.014 | S8: =S6-S7 -> 2679.3485 | T8: =T6-T7 -> 2657.2944 | U8: =U6-U7 -> 1855.0302
B9: Оборотные активы | C9: =Норникель!C62 -> 9870 | D9: =Норникель!D62 -> 8403 | E9: =Норникель!E62 -> 7342 | F9: =Норникель!F62 -> 6845 | H9: =Vale!C56 -> 21384 | I9: =Vale!D56 -> 15526 | J9: =Vale!E56 -> 14767 | K9: =Vale!F56 -> 13481 | M9: ='Anglo American Platinum'!I62 -> 7169.5531 | N9: ='Anglo American Platinum'!J62 -> 5513.8291 | O9: ='Anglo American Platinum'!K62 -> 3691.4058 | P9: ='Anglo American Platinum'!L62 -> 3211.105 | R9: ='Impala Platinum'!I62 -> 3957.5419 | S9: ='Impala Platinum'!J62 -> 3698.8322 | T9: ='Impala Platinum'!K62 -> 3594.8011 | U9: ='Impala Platinum'!L62 -> 2781.0335
B10: Авансы выданные | C10: =Норникель!C56 -> 111 | D10: =Норникель!D56 -> 192 | E10: =Норникель!E56 -> 173 | F10: =Норникель!F56 -> 135 | H10: =Vale!C50 -> 3914 | I10: =Vale!D50 -> 4319 | J10: =Vale!E50 -> 4197 | K10: =Vale!F50 -> 2358 | M10: ='Anglo American Platinum'!I58 -> 542.31844 | N10: ='Anglo American Platinum'!J58 -> 243.02397 | O10: ='Anglo American Platinum'!K58 -> 202.81167 | P10: ='Anglo American Platinum'!L58 -> 203.29852 | R10: ='Impala Platinum'!I60 -> 77.444134 | S10: ='Impala Platinum'!J60 -> 121.75784 | T10: ='Impala Platinum'!K60 -> 224.40318 | U10: ='Impala Platinum'!L60 -> 95.052226
B11: =Норникель!B58 -> Авансовые платежи по налогу на прибыль | C11: =Норникель!C58 -> 203 | D11: =Норникель!D58 -> 17 | E11: =Норникель!E58 -> 101 | F11: =Норникель!F58 -> 38 | H11: =Vale!C53 -> 862 | I11: =Vale!D53 -> 1272 | J11: =Vale!E53 -> 900 | K11: =Vale!F53 -> 1100 | M11: ='Anglo American Platinum'!I60 -> 169.76257 | N11: ='Anglo American Platinum'!J60 -> 196.68101 | O11: ='Anglo American Platinum'!K60 -> 122.33422 | P11: ='Anglo American Platinum'!L60 -> 90.324354 | R11: ='Impala Platinum'!I58 -> 74.301676 | S11: ='Impala Platinum'!J58 -> 32.575292 | T11: ='Impala Platinum'!K58 -> 56.180371 | U11: ='Impala Platinum'!L58 -> 43.485432
B12: Скорректированные оборотные активы | C12: =C9-C10-C11 -> 9556 | D12: =D9-D10-D11 -> 8194 | E12: =E9-E10-E11 -> 7068 | F12: =F9-F10-F11 -> 6672 | H12: =H9-H10-H11 -> 16608 | I12: =I9-I10-I11 -> 9935 | J12: =J9-J10-J11 -> 9670 | K12: =K9-K10-K11 -> 10023 | M12: =M9-M10-M11 -> 6457.4721 | N12: =N9-N10-N11 -> 5074.1242 | O12: =O9-O10-O11 -> 3366.2599 | P12: =P9-P10-P11 -> 2917.4821 | R12: =R9-R10-R11 -> 3805.7961 | S12: =S9-S10-S11 -> 3544.4991 | T12: =T9-T10-T11 -> 3314.2175 | U12: =U9-U10-U11 -> 2642.4959
B13: Краткосрочные обязательства | C13: =Норникель!C98 -> 8083 | D13: =Норникель!D98 -> 7689 | E13: =Норникель!E98 -> 8831 | F13: =Норникель!F98 -> 5919 | H13: =Vale!C87 -> 14843 | I13: =Vale!D87 -> 13891 | J13: =Vale!E87 -> 14094 | K13: =Vale!F87 -> 13090 | M13: ='Anglo American Platinum'!I81 -> 3943.2961 | N13: ='Anglo American Platinum'!J81 -> 3568.3467 | O13: ='Anglo American Platinum'!K81 -> 2490.1326 | P13: ='Anglo American Platinum'!L81 -> 2479.4393 | R13: ='Impala Platinum'!I90 -> 1242.5279 | S13: ='Impala Platinum'!J90 -> 1019.4837 | T13: ='Impala Platinum'!K90 -> 937.50663 | U13: ='Impala Platinum'!L90 -> 926.0033
B14: Коэффициент текущей ликвидности (CR) | C14: =C12/C13 -> 1.1822343 | D14: =D12/D13 -> 1.0656782 | E14: =E12/E13 -> 0.80036236 | F14: =F12/F13 -> 1.1272174 | H14: =H12/H13 -> 1.1189113 | I14: =I12/I13 -> 0.71521129 | J14: =J12/J13 -> 0.68610756 | K14: =K12/K13 -> 0.76569901 | M14: =M12/M13 -> 1.6375823 | N14: =N12/N13 -> 1.4219818 | O14: =O12/O13 -> 1.3518396 | P14: =P12/P13 -> 1.1766701 | R14: =R12/R13 -> 3.0629461 | S14: =S12/S13 -> 3.4767589 | T14: =T12/T13 -> 3.5351403 | U14: =U12/U13 -> 2.8536571
B15: Оборотные активы | C15: =Норникель!C62 -> 9870 | D15: =Норникель!D62 -> 8403 | E15: =Норникель!E62 -> 7342 | F15: =Норникель!F62 -> 6845 | H15: =Vale!C56 -> 21384 | I15: =Vale!D56 -> 15526 | J15: =Vale!E56 -> 14767 | K15: =Vale!F56 -> 13481 | M15: ='Anglo American Platinum'!I62 -> 7169.5531 | N15: ='Anglo American Platinum'!J62 -> 5513.8291 | O15: ='Anglo American Platinum'!K62 -> 3691.4058 | P15: ='Anglo American Platinum'!L62 -> 3211.105 | R15: ='Impala Platinum'!I62 -> 3957.5419 | S15: ='Impala Platinum'!J62 -> 3698.8322 | T15: ='Impala Platinum'!K62 -> 3594.8011 | U15: ='Impala Platinum'!L62 -> 2781.0335
B16: =Норникель!B54 -> Запасы | C16: =Норникель!C54 -> 3026 | D16: =Норникель!D54 -> 4945 | E16: =Норникель!E54 -> 3817 | F16: =Норникель!F54 -> 3114 | H16: =Vale!C52 -> 4377 | I16: =Vale!D52 -> 4482 | J16: =Vale!E52 -> 4684 | K16: =Vale!F52 -> 4605 | M16: ='Anglo American Platinum'!I57 -> 3595.1816 | N16: ='Anglo American Platinum'!J57 -> 1818.8691 | O16: ='Anglo American Platinum'!K57 -> 1291.9363 | P16: ='Anglo American Platinum'!L57 -> 1361.1325 | R16: ='Impala Platinum'!I56 -> 1585.9637 | S16: ='Impala Platinum'!J56 -> 1468.8998 | T16: ='Impala Platinum'!K56 -> 1290.1857 | U16: ='Impala Platinum'!L56 -> 1461.1325
B17: Краткосрочные обязательства | C17: =Норникель!C98 -> 8083 | D17: =Норникель!D98 -> 7689 | E17: =Норникель!E98 -> 8831 | F17: =Норникель!F98 -> 5919 | H17: =Vale!C87 -> 14843 | I17: =Vale!D87 -> 13891 | J17: =Vale!E87 -> 14094 | K17: =Vale!F87 -> 13090 | M17: ='Anglo American Platinum'!I81 -> 3943.2961 | N17: ='Anglo American Platinum'!J81 -> 3568.3467 | O17: ='Anglo American Platinum'!K81 -> 2490.1326 | P17: ='Anglo American Platinum'!L81 -> 2479.4393 | R17: ='Impala Platinum'!I90 -> 1242.5279 | S17: ='Impala Platinum'!J90 -> 1019.4837 | T17: ='Impala Platinum'!K90 -> 937.50663 | U17: ='Impala Platinum'!L90 -> 926.0033
B18: Коэффициент срочной ливидности (QR) | C18: =(C15-C16)/C17 -> 0.84671533 | D18: =(D15-D16)/D17 -> 0.44973339 | E18: =(E15-E16)/E17 -> 0.39916204 | F18: =(F15-F16)/F17 -> 0.63034296 | H18: =(H15-H16)/H17 -> 1.1457926 | I18: =(I15-I16)/I17 -> 0.79504715 | J18: =(J15-J16)/J17 -> 0.71541081 | K18: =(K15-K16)/K17 -> 0.67807487 | M18: =(M15-M16)/M17 -> 0.90644259 | N18: =(N15-N16)/N17 -> 1.0354824 | O18: =(O15-O16)/O17 -> 0.96359104 | P18: =(P15-P16)/P17 -> 0.74612536 | R18: =(R15-R16)/R17 -> 1.9086719 | S18: =(S15-S16)/S17 -> 2.1873154 | T18: =(T15-T16)/T17 -> 2.458239 | U18: =(U15-U16)/U17 -> 1.425374 | W18: слишком маленькие значения (не 1-2)
B20: Коэффициенты оборачиваемости
B21: Дебиторская задолженность | C21: =Норникель!C55 -> 468 | D21: =Норникель!D55 -> 846 | E21: =Норникель!E55 -> 764 | F21: =Норникель!F55 -> 1374 | H21: =Vale!C50 -> 3914 | I21: =Vale!D50 -> 4319 | J21: =Vale!E50 -> 4197 | K21: =Vale!F50 -> 2358 | M21: ='Anglo American Platinum'!I58 -> 542.31844 | N21: ='Anglo American Platinum'!J58 -> 243.02397 | O21: ='Anglo American Platinum'!K58 -> 202.81167 | P21: ='Anglo American Platinum'!L58 -> 203.29852 | R21: ='Impala Platinum'!I57 -> 510.3352 | S21: ='Impala Platinum'!J57 -> 381.62262 | T21: ='Impala Platinum'!K57 -> 600 | U21: ='Impala Platinum'!L57 -> 650.13744
B22: Скорректированная дебиторская задолженность на НДС | C22: =C21/1.2 -> 390 | D22: =D21/1.2 -> 705 | E22: =E21/1.2 -> 636.66667 | F22: =F21/1.2 -> 1145 | H22: =H21/1.18 -> 3316.9492 | I22: =I21/1.18 -> 3660.1695 | J22: =J21/1.18 -> 3556.7797 | K22: =K21/1.18 -> 1998.3051 | M22: =M21/1.14 -> 475.71793 | N22: =N21/1.14 -> 213.17892 | O22: =O21/1.14 -> 177.90497 | P22: =P21/1.14 -> 178.33203 | R22: =R21/1.14 -> 447.66245 | S22: =S21/1.14 -> 334.75668 | T22: =T21/1.14 -> 526.31579 | U22: =U21/1.14 -> 570.296
B23: Средняя скорректированная дебиторская задолженность | C23: =C22 -> 390 | D23: =AVERAGE(C22:D22) -> 547.5 | E23: =AVERAGE(D22:E22) -> 670.83333 | F23: =AVERAGE(E22:F22) -> 890.83333 | H23: =H22 -> 3316.9492 | I23: =AVERAGE(H22:I22) -> 3488.5593 | J23: =AVERAGE(I22:J22) -> 3608.4746 | K23: =AVERAGE(J22:K22) -> 2777.5424 | M23: =M22 -> 475.71793 | N23: =AVERAGE(M22:N22) -> 344.44842 | O23: =AVERAGE(N22:O22) -> 195.54195 | P23: =AVERAGE(O22:P22) -> 178.1185 | R23: =R22 -> 447.66245 | S23: =AVERAGE(R22:S22) -> 391.20957 | T23: =AVERAGE(S22:T22) -> 430.53624 | U23: =AVERAGE(T22:U22) -> 548.30589
B24: Выручка | C24: =Норникель!C9 -> 17852 | D24: =Норникель!D9 -> 16876 | E24: =Норникель!E9 -> 14409 | F24: =Норникель!F9 -> 12535 | H24: =Vale!C6 -> 54502 | I24: =Vale!D6 -> 43839 | J24: =Vale!E6 -> 41784 | K24: =Vale!F6 -> 38056 | M24: ='Anglo American Platinum'!I8 -> 13932.987 | N24: ='Anglo American Platinum'!J8 -> 10781.209 | O24: ='Anglo American Platinum'!K8 -> 7010.861 | P24: ='Anglo American Platinum'!L8 -> 5825.0668 | R24: ='Impala Platinum'!I6 -> 8413.961 | S24: ='Impala Platinum'!J6 -> 7774.77 | T24: ='Impala Platinum'!K6 -> 5998.5369 | U24: ='Impala Platinum'!L6 -> 4617.7445
B25: Период погашения дебиторской задолженности (дн.) | C25: =C23/C24*365 -> 7.9738965 | D25: =D23/D24*365 -> 11.841521 | E25: =E23/E24*365 -> 16.993141 | F25: =F23/F24*365 -> 25.939702 | H25: =H23/H24*365 -> 22.213615 | I25: =I23/I24*365 -> 29.045465 | J25: =J23/J24*365 -> 31.521473 | K25: =K23/K24*365 -> 26.639767 | M25: =M23/M24*365 -> 12.462298 | N25: =N23/N24*365 -> 11.661371 | O25: =O23/O24*365 -> 10.18032 | P25: =P23/P24*365 -> 11.160946 | R25: =R23/R24*365 -> 19.419723 | S25: =S23/S24*365 -> 18.366008 | T25: =T23/T24*365 -> 26.197343 | U25: =U23/U24*365 -> 43.339698
B26: Себестоимость реализованной продукции | C26: =-Норникель!C10+Норникель!C11 -> 4304 | D26: =-Норникель!D10+Норникель!D11 -> 5293 | E26: =-Норникель!E10+Норникель!E11 -> 5656 | F26: =-Норникель!F10+Норникель!F11 -> 5576 | H26: =-Vale!C7 -> 21729 | I26: =-Vale!D7 -> 24028 | J26: =-Vale!E7 -> 24089 | K26: =-Vale!F7 -> 24265 | M26: =-'Anglo American Platinum'!I9 -> 7107.5325 | N26: =-'Anglo American Platinum'!J9 -> 6148.3574 | O26: =-'Anglo American Platinum'!K9 -> 5828.3624 | P26: =-'Anglo American Platinum'!L9 -> 4851.3629 | R26: =-'Impala Platinum'!I7 -> 4942.8571 | S26: =-'Impala Platinum'!J7 -> 5062.2208 | T26: =-'Impala Platinum'!K7 -> 4741.4744 | U26: =-'Impala Platinum'!L7 -> 4325.5478
B27: =Норникель!B54 -> Запасы | C27: =Норникель!C54 -> 3026 | D27: =Норникель!D54 -> 4945 | E27: =Норникель!E54 -> 3817 | F27: =Норникель!F54 -> 3114 | H27: =Vale!C52 -> 4377 | I27: =Vale!D52 -> 4482 | J27: =Vale!E52 -> 4684 | K27: =Vale!F52 -> 4605 | M27: ='Anglo American Platinum'!I57 -> 3595.1816 | N27: ='Anglo American Platinum'!J57 -> 1818.8691 | O27: ='Anglo American Platinum'!K57 -> 1291.9363 | P27: ='Anglo American Platinum'!L57 -> 1361.1325 | R27: ='Impala Platinum'!I56 -> 1585.9637 | S27: ='Impala Platinum'!J56 -> 1468.8998 | T27: ='Impala Platinum'!K56 -> 1290.1857 | U27: ='Impala Platinum'!L56 -> 1461.1325
B28: Средняя величина запасов | C28: =C27 -> 3026 | D28: =AVERAGE(C27:D27) -> 3985.5 | E28: =AVERAGE(D27:E27) -> 4381 | F28: =AVERAGE(E27:F27) -> 3465.5 | H28: =H27 -> 4377 | I28: =AVERAGE(H27:I27) -> 4429.5 | J28: =AVERAGE(I27:J27) -> 4583 | K28: =AVERAGE(J27:K27) -> 4644.5 | M28: =M27 -> 3595.1816 | N28: =AVERAGE(M27:N27) -> 2707.0253 | O28: =AVERAGE(N27:O27) -> 1555.4027 | P28: =AVERAGE(O27:P27) -> 1326.5344 | R28: =R27 -> 1585.9637 | S28: =AVERAGE(R27:S27) -> 1527.4318 | T28: =AVERAGE(S27:T27) -> 1379.5427 | U28: =AVERAGE(T27:U27) -> 1375.6591
B29: Коэффициет оборачиваемости запасов | C29: =C26/C28 -> 1.4223397 | D29: =D26/D28 -> 1.3280642 | E29: =E26/E28 -> 1.2910294 | F29: =F26/F28 -> 1.609003 | H29: =H26/H28 -> 4.9643592 | I29: =I26/I28 -> 5.42454 | J29: =J26/J28 -> 5.2561641 | K29: =K26/K28 -> 5.224459 | M29: =M26/M28 -> 1.9769606 | N29: =N26/N28 -> 2.2712597 | O29: =O26/O28 -> 3.7471726 | P29: =P26/P28 -> 3.6571708 | R29: =R26/R28 -> 3.1166269 | S29: =S26/S28 -> 3.3142042 | T29: =T26/T28 -> 3.4369898 | U29: =U26/U28 -> 3.1443458
B30: Период оборачиваемости запасов (дн.) | C30: =365/C29 -> 256.61942 | D30: =365/D29 -> 274.8361 | E30: =365/E29 -> 282.72012 | F30: =365/F29 -> 226.84855 | H30: =365/H29 -> 73.524092 | I30: =365/I29 -> 67.286811 | J30: =365/J29 -> 69.442277 | K30: =365/K29 -> 69.863693 | M30: =365/M29 -> 184.62684 | N30: =365/N29 -> 160.70377 | O30: =365/O29 -> 97.406776 | P30: =365/P29 -> 99.803925 | R30: =365/R29 -> 117.11379 | S30: =365/S29 -> 110.13202 | T30: =365/T29 -> 106.19758 | U30: =365/U29 -> 116.08138 | W30: очень большие значения в сравнении с конкурентами
B31: Кредиторская задолженность | C31: =Норникель!C89 -> 2224 | D31: =Норникель!D89 -> 1381 | E31: =Норникель!E89 -> 1273 | F31: =Норникель!F89 -> 1209 | H31: =Vale!C74+Vale!C77 -> 5787 | I31: =Vale!D74+Vale!D77 -> 6133 | J31: =Vale!E74+Vale!E77 -> 6948 | K31: =Vale!F74+Vale!F77 -> 5777 | M31: ='Anglo American Platinum'!I82 -> 1753.4916 | N31: ='Anglo American Platinum'!J82 -> 1645.1752 | O31: ='Anglo American Platinum'!K82 -> 1301.8568 | P31: ='Anglo American Platinum'!L82 -> 1288.5102 | R31: ='Impala Platinum'!I83 -> 1130.5866 | S31: ='Impala Platinum'!J83 -> 948.24831 | T31: ='Impala Platinum'!K83 -> 850.98143 | U31: ='Impala Platinum'!L83 -> 813.52391
B32: Закупки в кредит (себестоимость реализованных товаров) | C32: =-Норникель!C10 -> 5057 | D32: =-Норникель!D10 -> 6103 | E32: =-Норникель!E10 -> 6344 | F32: =-Норникель!F10 -> 6232 | H32: =-Vale!C7 -> 21729 | I32: =-Vale!D7 -> 24028 | J32: =-Vale!E7 -> 24089 | K32: =-Vale!F7 -> 24265 | M32: =-'Anglo American Platinum'!I9 -> 7107.5325 | N32: =-'Anglo American Platinum'!J9 -> 6148.3574 | O32: =-'Anglo American Platinum'!K9 -> 5828.3624 | P32: =-'Anglo American Platinum'!L9 -> 4851.3629 | R32: =-'Impala Platinum'!I7 -> 4942.8571 | S32: =-'Impala Platinum'!J7 -> 5062.2208 | T32: =-'Impala Platinum'!K7 -> 4741.4744 | U32: =-'Impala Platinum'!L7 -> 4325.5478
B33: Период погашения кредиторской задолженности (дн.) | C33: =C31/C32*365 -> 160.52205 | D33: =D31/D32*365 -> 82.592987 | E33: =E31/E32*365 -> 73.241646 | F33: =F31/F32*365 -> 70.809531 | H33: =H31/H32*365 -> 97.209029 | I33: =I31/I32*365 -> 93.164017 | J33: =J31/J32*365 -> 105.2771 | K33: =K31/K32*365 -> 86.899032 | M33: =M31/M32*365 -> 90.048754 | N33: =N31/N32*365 -> 97.666563 | O33: =O31/O32*365 -> 81.528513 | P33: =P31/P32*365 -> 96.943111 | R33: =R31/R32*365 -> 83.486958 | S33: =S31/S32*365 -> 68.371304 | T33: =T31/T32*365 -> 65.508784 | U33: =U31/U32*365 -> 68.64708
B34: Операционный цикл денежных средств (дн.) | C34: =C25+C30-C33 -> 104.07127 | D34: =D25+D30-D33 -> 204.08464 | E34: =E25+E30-E33 -> 226.47162 | F34: =F25+F30-F33 -> 181.97872 | H34: =H25+H30-H33 -> -1.4713223 | I34: =I25+I30-I33 -> 3.1682595 | J34: =J25+J30-J33 -> -4.3133481 | K34: =K25+K30-K33 -> 9.6044279 | M34: =M25+M30-M33 -> 107.04039 | N34: =N25+N30-N33 -> 74.698582 | O34: =O25+O30-O33 -> 26.058583 | P34: =P25+P30-P33 -> 14.02176 | R34: =R25+R30-R33 -> 53.046558 | S34: =S25+S30-S33 -> 60.126723 | T34: =T25+T30-T33 -> 66.886138 | U34: =U25+U30-U33 -> 90.773998 | W34: очень большие значения в сравнении с конкурентами
B36: Коэффициенты рентабельности | W36: у всех все падает - не очень хороший знак, но примерно отраслевые значения
B37: PBIT | C37: =Норникель!C17 -> 9536 | D37: =Норникель!D17 -> 7581 | E37: =Норникель!E17 -> 5540 | F37: =Норникель!F17 -> 3574 | H37: =Vale!C14 -> 27693 | I37: =Vale!D14 -> 17208 | J37: =Vale!E14 -> 14205 | K37: =Vale!F14 -> 10788 | M37: ='Anglo American Platinum'!I10 -> 6825.4545 | N37: ='Anglo American Platinum'!J10 -> 4632.8515 | O37: ='Anglo American Platinum'!K10 -> 1182.4986 | P37: ='Anglo American Platinum'!L10 -> 973.7039 | R37: ='Impala Platinum'!I8 -> 3471.1039 | S37: ='Impala Platinum'!J8 -> 2712.5493 | T37: ='Impala Platinum'!K8 -> 1257.0625 | U37: ='Impala Platinum'!L8 -> 292.19669
B38: Активы | C38: =Норникель!C64 -> 23435 | D38: =Норникель!D64 -> 25795 | E38: =Норникель!E64 -> 23580 | F38: =Норникель!F64 -> 23170 | H38: =Vale!C71 -> 89442 | I38: =Vale!D71 -> 86894 | J38: =Vale!E71 -> 94186 | K38: =Vale!F71 -> 80152 | M38: ='Anglo American Platinum'!I63 -> 12580.237 | N38: ='Anglo American Platinum'!J63 -> 10873.632 | O38: ='Anglo American Platinum'!K63 -> 8976.9231 | P38: ='Anglo American Platinum'!L63 -> 9397.6361 | R38: ='Impala Platinum'!I63 -> 8832.0531 | S38: ='Impala Platinum'!J63 -> 9593.5464 | T38: ='Impala Platinum'!K63 -> 8985.9947 | U38: ='Impala Platinum'!L63 -> 7309.2358
B39: Краткосрочные обязательства | C39: =Норникель!C98 -> 8083 | D39: =Норникель!D98 -> 7689 | E39: =Норникель!E98 -> 8831 | F39: =Норникель!F98 -> 5919 | H39: =Vale!C89 -> 15198 | I39: =Vale!D89 -> 13891 | J39: =Vale!E89 -> 14655 | K39: =Vale!F89 -> 1309 | M39: ='Anglo American Platinum'!I81 -> 3943.2961 | N39: ='Anglo American Platinum'!J81 -> 3568.3467 | O39: ='Anglo American Platinum'!K81 -> 2490.1326 | P39: ='Anglo American Platinum'!L81 -> 2479.4393 | R39: ='Impala Platinum'!I90 -> 1242.5279 | S39: ='Impala Platinum'!J90 -> 1019.4837 | T39: ='Impala Platinum'!K90 -> 937.50663 | U39: ='Impala Platinum'!L90 -> 926.0033
B40: Задействованный капитал (CE) | C40: =C38-C39 -> 15352 | D40: =D38-D39 -> 18106 | E40: =E38-E39 -> 14749 | F40: =F38-F39 -> 17251 | H40: =H38-H39 -> 74244 | I40: =I38-I39 -> 73003 | J40: =J38-J39 -> 79531 | K40: =K38-K39 -> 78843 | M40: =M38-M39 -> 8636.9413 | N40: =N38-N39 -> 7305.2858 | O40: =O38-O39 -> 6486.7905 | P40: =P38-P39 -> 6918.1968 | R40: =R38-R39 -> 7589.5251 | S40: =S38-S39 -> 8574.0627 | T40: =T38-T39 -> 8048.4881 | U40: =U38-U39 -> 6383.2325
B41: Рентабельность задействованного капитала (ROCE) | C41: =C37/C40 -> 0.62115685 | D41: =D37/D40 -> 0.41870098 | E41: =E37/E40 -> 0.37561869 | F41: =F37/F40 -> 0.2071764 | H41: =H37/H40 -> 0.37299984 | I41: =I37/I40 -> 0.23571634 | J41: =J37/J40 -> 0.1786096 | K41: =K37/K40 -> 0.13682889 | M41: =M37/M40 -> 0.79026293 | N41: =N37/N40 -> 0.634178 | O41: =O37/O40 -> 0.18229332 | P41: =P37/P40 -> 0.14074533 | R41: =R37/R40 -> 0.45735456 | S41: =S37/S40 -> 0.31636686 | T41: =T37/T40 -> 0.15618616 | U41: =U37/U40 -> 0.045775661
B42: =Норникель!B12 -> Валовая прибыль | C42: =Норникель!C12 -> 12042 | D42: =Норникель!D12 -> 9963 | E42: =Норникель!E12 -> 7377 | F42: =Норникель!F12 -> 5647 | H42: =Vale!C8 -> 32773 | I42: =Vale!D8 -> 19811 | J42: =Vale!E8 -> 17695 | K42: =Vale!F8 -> 13791 | M42: ='Anglo American Platinum'!I10 -> 6825.4545 | N42: ='Anglo American Platinum'!J10 -> 4632.8515 | O42: ='Anglo American Platinum'!K10 -> 1182.4986 | P42: ='Anglo American Platinum'!L10 -> 973.7039 | R42: ='Impala Platinum'!I8 -> 3471.1039 | S42: ='Impala Platinum'!J8 -> 2712.5493 | T42: ='Impala Platinum'!K8 -> 1257.0625 | U42: ='Impala Platinum'!L8 -> 292.19669
B43: Выручка | C43: =Норникель!C9 -> 17852 | D43: =Норникель!D9 -> 16876 | E43: =Норникель!E9 -> 14409 | F43: =Норникель!F9 -> 12535 | H43: =Vale!C6 -> 54502 | I43: =Vale!D6 -> 43839 | J43: =Vale!E6 -> 41784 | K43: =Vale!F6 -> 38056 | M43: ='Anglo American Platinum'!I8 -> 13932.987 | N43: ='Anglo American Platinum'!J8 -> 10781.209 | O43: ='Anglo American Platinum'!K8 -> 7010.861 | P43: ='Anglo American Platinum'!L8 -> 5825.0668 | R43: ='Impala Platinum'!I6 -> 8413.961 | S43: ='Impala Platinum'!J6 -> 7774.77 | T43: ='Impala Platinum'!K6 -> 5998.5369 | U43: ='Impala Platinum'!L6 -> 4617.7445
B44: Маржа валовой прибыли (Gross profit margin) | C44: =C42/C43 -> 0.67454627 | D44: =D42/D43 -> 0.59036502 | E44: =E42/E43 -> 0.51197168 | F44: =F42/F43 -> 0.4504986 | H44: =H42/H43 -> 0.60131738 | I44: =I42/I43 -> 0.45190356 | J44: =J42/J43 -> 0.42348746 | K44: =K42/K43 -> 0.36238701 | M44: =M42/M43 -> 0.48987733 | N44: =N42/N43 -> 0.4297154 | O44: =O42/O43 -> 0.16866667 | P44: =P42/P43 -> 0.16715755 | R44: =R42/R43 -> 0.412541 | S44: =S42/S43 -> 0.34889126 | T44: =T42/T43 -> 0.20956151 | U44: =U42/U43 -> 0.063276928
B45: Чистая прибыль | C45: =Норникель!C24 -> 6974 | D45: =Норникель!D24 -> 5854 | E45: =Норникель!E24 -> 2870 | F45: =Норникель!F24 -> 1815 | H45: =Vale!C21 -> 24844 | I45: =Vale!D21 -> 16810 | J45: =Vale!E21 -> 8105 | K45: =Vale!F21 -> 6166 | M45: ='Anglo American Platinum'!I23 -> 5131.2338 | N45: ='Anglo American Platinum'!J23 -> 3238.8962 | O45: ='Anglo American Platinum'!K23 -> 756.66854 | P45: ='Anglo American Platinum'!L23 -> 395.13629 | R45: ='Impala Platinum'!I21 -> 3107.4675 | S45: ='Impala Platinum'!J21 -> 2177.3325 | T45: ='Impala Platinum'!K21 -> 347.6646 | U45: ='Impala Platinum'!L21 -> -916.67557
B46: Выручка | C46: =Норникель!C9 -> 17852 | D46: =Норникель!D9 -> 16876 | E46: =Норникель!E9 -> 14409 | F46: =Норникель!F9 -> 12535 | H46: =Vale!C6 -> 54502 | I46: =Vale!D6 -> 43839 | J46: =Vale!E6 -> 41784 | K46: =Vale!F6 -> 38056 | M46: ='Anglo American Platinum'!I8 -> 13932.987 | N46: ='Anglo American Platinum'!J8 -> 10781.209 | O46: ='Anglo American Platinum'!K8 -> 7010.861 | P46: ='Anglo American Platinum'!L8 -> 5825.0668 | R46: ='Impala Platinum'!I6 -> 8413.961 | S46: ='Impala Platinum'!J6 -> 7774.77 | T46: ='Impala Platinum'!K6 -> 5998.5369 | U46: ='Impala Platinum'!L6 -> 4617.7445
B47: Маржа чистой прибыли (Net profit margin) | C47: =C45/C46 -> 0.39065651 | D47: =D45/D46 -> 0.34688315 | E47: =E45/E46 -> 0.19918107 | F47: =F45/F46 -> 0.14479458 | H47: =H45/H46 -> 0.45583648 | I47: =I45/I46 -> 0.38344853 | J47: =J45/J46 -> 0.19397377 | K47: =K45/K46 -> 0.16202439 | M47: =M45/M46 -> 0.36827952 | N47: =N45/N46 -> 0.3004205 | O47: =O45/O46 -> 0.10792805 | P47: =P45/P46 -> 0.067833778 | R47: =R45/R46 -> 0.36932279 | S47: =S45/S46 -> 0.28005104 | T47: =T45/T46 -> 0.057958234 | U47: =U45/U46 -> -0.19851154
B48: Чистая прибыль | C48: =Норникель!C24 -> 6974 | D48: =Норникель!D24 -> 5854 | E48: =Норникель!E24 -> 2870 | F48: =Норникель!F24 -> 1815 | H48: =Vale!C21 -> 24844 | I48: =Vale!D21 -> 16810 | J48: =Vale!E21 -> 8105 | K48: =Vale!F21 -> 6166 | M48: ='Anglo American Platinum'!I23 -> 5131.2338 | N48: ='Anglo American Platinum'!J23 -> 3238.8962 | O48: ='Anglo American Platinum'!K23 -> 756.66854 | P48: ='Anglo American Platinum'!L23 -> 395.13629 | R48: ='Impala Platinum'!I21 -> 3107.4675 | S48: ='Impala Platinum'!J21 -> 2177.3325 | T48: ='Impala Platinum'!K21 -> 347.6646 | U48: ='Impala Platinum'!L21 -> -916.67557
B49: Собственный капитал | C49: =Норникель!C73 -> 4788 | D49: =Норникель!D73 -> 8567 | E49: =Норникель!E73 -> 7595 | F49: =Норникель!F73 -> 8097 | H49: =Vale!C111 -> 35306 | I49: =Vale!D111 -> 37358 | J49: =Vale!E111 -> 40981 | K49: =Vale!F111 -> 34528 | M49: ='Anglo American Platinum'!I72 -> 7147.3464 | N49: ='Anglo American Platinum'!J72 -> 5959.5575 | O49: ='Anglo American Platinum'!K72 -> 5306.8966 | P49: ='Anglo American Platinum'!L72 -> 5613.6888 | R49: ='Impala Platinum'!I66 -> 1479.6788 | S49: ='Impala Platinum'!J66 -> 1418.5618 | T49: ='Impala Platinum'!K66 -> 1369.7082 | U49: ='Impala Platinum'!L66 -> 1709.5107
B50: Рентабельность собственного капитала (ROE) | C50: =C48/C49 -> 1.4565581 | D50: =D48/D49 -> 0.68331972 | E50: =E48/E49 -> 0.37788018 | F50: =F48/F49 -> 0.2241571 | H50: =H48/H49 -> 0.70367643 | I50: =I48/I49 -> 0.44997056 | J50: =J48/J49 -> 0.19777458 | K50: =K48/K49 -> 0.1785797 | M50: =M48/M49 -> 0.71792152 | N50: =N48/N49 -> 0.54347931 | O50: =O48/O49 -> 0.14258212 | P50: =P48/P49 -> 0.070387993 | R50: =R48/R49 -> 2.100096 | S50: =S48/S49 -> 1.5348873 | T50: =T48/T49 -> 0.25382384 | U50: =U48/U49 -> -0.53622102
B51: Чистая прибыль | C51: =Норникель!C24 -> 6974 | D51: =Норникель!D24 -> 5854 | E51: =Норникель!E24 -> 2870 | F51: =Норникель!F24 -> 1815 | H51: =Vale!C21 -> 24844 | I51: =Vale!D21 -> 16810 | J51: =Vale!E21 -> 8105 | K51: =Vale!F21 -> 6166 | M51: ='Anglo American Platinum'!I23 -> 5131.2338 | N51: ='Anglo American Platinum'!J23 -> 3238.8962 | O51: ='Anglo American Platinum'!K23 -> 756.66854 | P51: ='Anglo American Platinum'!L23 -> 395.13629 | R51: ='Impala Platinum'!I21 -> 3107.4675 | S51: ='Impala Platinum'!J21 -> 2177.3325 | T51: ='Impala Platinum'!K21 -> 347.6646 | U51: ='Impala Platinum'!L21 -> -916.67557
B52: Активы | C52: =Норникель!C64 -> 23435 | D52: =Норникель!E64 -> 23580 | E52: =Норникель!E64 -> 23580 | F52: =Норникель!F64 -> 23170 | H52: =Vale!C71 -> 89442 | I52: =Vale!D71 -> 86894 | J52: =Vale!E71 -> 94186 | K52: =Vale!F71 -> 80152 | M52: ='Anglo American Platinum'!I63 -> 12580.237 | N52: ='Anglo American Platinum'!J63 -> 10873.632 | O52: ='Anglo American Platinum'!K63 -> 8976.9231 | P52: ='Anglo American Platinum'!L63 -> 9397.6361 | R52: ='Impala Platinum'!I63 -> 8832.0531 | S52: ='Impala Platinum'!J63 -> 9593.5464 | T52: ='Impala Platinum'!K63 -> 8985.9947 | U52: ='Impala Platinum'!L63 -> 7309.2358
B53: Средняя величина активов | D53: =AVERAGE(C52:D52) -> 23507.5 | E53: =AVERAGE(D52:E52) -> 23580 | F53: =AVERAGE(E52:F52) -> 23375 | I53: =AVERAGE(H52:I52) -> 88168 | J53: =AVERAGE(I52:J52) -> 90540 | K53: =AVERAGE(J52:K52) -> 87169 | N53: =AVERAGE(M52:N52) -> 11726.935 | O53: =AVERAGE(N52:O52) -> 9925.2778 | P53: =AVERAGE(O52:P52) -> 9187.2796 | S53: =AVERAGE(R52:S52) -> 9212.7997 | T53: =AVERAGE(S52:T52) -> 9289.7705 | U53: =AVERAGE(T52:U52) -> 8147.6153
B54: Рентабельность собственных активов (ROA) | D54: =D51/D53 -> 0.24902691 | E54: =E51/E53 -> 0.12171332 | F54: =F51/F53 -> 0.077647059 | I54: =I51/I53 -> 0.19065874 | J54: =J51/J53 -> 0.089518445 | K54: =K51/K53 -> 0.070736156 | N54: =N51/N53 -> 0.2761929 | O54: =O51/O53 -> 0.07623651 | P54: =P51/P53 -> 0.043009064 | S54: =S51/S53 -> 0.23633776 | T54: =T51/T53 -> 0.037424455 | U54: =U51/U53 -> -0.11250845
B55: Выручка | C55: =Норникель!C9 -> 17852 | D55: =Норникель!D9 -> 16876 | E55: =Норникель!E9 -> 14409 | F55: =Норникель!F9 -> 12535 | H55: =Vale!C6 -> 54502 | I55: =Vale!D6 -> 43839 | J55: =Vale!E6 -> 41784 | K55: =Vale!F6 -> 38056 | M55: ='Anglo American Platinum'!I8 -> 13932.987 | N55: ='Anglo American Platinum'!J8 -> 10781.209 | O55: ='Anglo American Platinum'!K8 -> 7010.861 | P55: ='Anglo American Platinum'!L8 -> 5825.0668 | R55: ='Impala Platinum'!I6 -> 8413.961 | S55: ='Impala Platinum'!J6 -> 7774.77 | T55: ='Impala Platinum'!K6 -> 5998.5369 | U55: ='Impala Platinum'!L6 -> 4617.7445
B56: Активы | C56: =Норникель!C64 -> 23435 | D56: =Норникель!D64 -> 25795 | E56: =Норникель!E64 -> 23580 | F56: =Норникель!F64 -> 23170 | H56: =Vale!C71 -> 89442 | I56: =Vale!D71 -> 86894 | J56: =Vale!E71 -> 94186 | K56: =Vale!F71 -> 80152 | M56: ='Anglo American Platinum'!I63 -> 12580.237 | N56: ='Anglo American Platinum'!J63 -> 10873.632 | O56: ='Anglo American Platinum'!K63 -> 8976.9231 | P56: ='Anglo American Platinum'!L63 -> 9397.6361 | R56: ='Impala Platinum'!I63 -> 8832.0531 | S56: ='Impala Platinum'!J63 -> 9593.5464 | T56: ='Impala Platinum'!K63 -> 8985.9947 | U56: ='Impala Platinum'!L63 -> 7309.2358
B57: Средняя величина активов | D57: =AVERAGE(C56:D56) -> 24615 | E57: =AVERAGE(D56:E56) -> 24687.5 | F57: =AVERAGE(E56:F56) -> 23375 | I57: =AVERAGE(H56:I56) -> 88168 | J57: =AVERAGE(I56:J56) -> 90540 | K57: =AVERAGE(J56:K56) -> 87169 | N57: =AVERAGE(M56:N56) -> 11726.935 | O57: =AVERAGE(N56:O56) -> 9925.2778 | P57: =AVERAGE(O56:P56) -> 9187.2796 | S57: =AVERAGE(R56:S56) -> 9212.7997 | T57: =AVERAGE(S56:T56) -> 9289.7705 | U57: =AVERAGE(T56:U56) -> 8147.6153
B58: Оборачиваемость активов (asset turnover) | D58: =D55/D57 -> 0.68559821 | E58: =E55/E57 -> 0.5836557 | F58: =F55/F57 -> 0.53625668 | I58: =I55/I57 -> 0.49722121 | J58: =J55/J57 -> 0.46149768 | K58: =K55/K57 -> 0.43657722 | N58: =N55/N57 -> 0.91935437 | O58: =O55/O57 -> 0.70636421 | P58: =P55/P57 -> 0.63403609 | S58: =S55/S57 -> 0.84390959 | T58: =T55/T57 -> 0.64571421 | U58: =U55/U57 -> 0.56676026
B60: Коэффициенты финансовой устойчивости
B61: =B50 -> Рентабельность собственного капитала (ROE) | C61: =C50 -> 1.4565581 | D61: =D50 -> 0.68331972 | E61: =E50 -> 0.37788018 | F61: =F50 -> 0.2241571 | H61: =H50 -> 0.70367643 | I61: =I50 -> 0.44997056 | J61: =J50 -> 0.19777458 | K61: =K50 -> 0.1785797 | M61: =M50 -> 0.71792152 | N61: =N50 -> 0.54347931 | O61: =O50 -> 0.14258212 | P61: =P50 -> 0.070387993 | R61: =R50 -> 2.100096 | S61: =S50 -> 1.5348873 | T61: =T50 -> 0.25382384 | U61: =U50 -> -0.53622102
B62: =B54 -> Рентабельность собственных активов (ROA) | C62: =C54 -> 0 | D62: =D54 -> 0.24902691 | E62: =E54 -> 0.12171332 | F62: =F54 -> 0.077647059 | H62: =H54 -> 0 | I62: =I54 -> 0.19065874 | J62: =J54 -> 0.089518445 | K62: =K54 -> 0.070736156 | M62: =M54 -> 0 | N62: =N54 -> 0.2761929 | O62: =O54 -> 0.07623651 | P62: =P54 -> 0.043009064 | R62: =R54 -> 0 | S62: =S54 -> 0.23633776 | T62: =T54 -> 0.037424455 | U62: =U54 -> -0.11250845
B63: Коэффициент финансового рычага | D63: =D61/D62 -> 2.7439594 | E63: =E61/E62 -> 3.1046741 | F63: =F61/F62 -> 2.8868717 | I63: =I61/I62 -> 2.3600835 | J63: =J61/J62 -> 2.2093165 | K63: =K61/K62 -> 2.5245887 | N63: =N61/N62 -> 1.9677526 | O63: =O61/O62 -> 1.8702603 | P63: =P61/P62 -> 1.6365851 | S63: =S61/S62 -> 6.494465 | T63: =T61/T62 -> 6.7822989 | U63: =U61/U62 -> 4.766051
B64: Обязательства | C64: =Норникель!C100 -> 18647 | D64: =Норникель!D100 -> 17228 | E64: =Норникель!E100 -> 15985 | F64: =Норникель!F100 -> 15073 | H64: =Vale!C105 -> 54136 | I64: =Vale!D105 -> 49536 | J64: =Vale!E105 -> 53205 | K64: =Vale!F105 -> 45624 | M64: ='Anglo American Platinum'!I80+'Anglo American Platinum'!I81 -> 5432.8911 | N64: ='Anglo American Platinum'!J80+'Anglo American Platinum'!J81 -> 4914.075 | O64: ='Anglo American Platinum'!K80+'Anglo American Platinum'!K81 -> 3670.0265 | P64: ='Anglo American Platinum'!L80+'Anglo American Platinum'!L81 -> 3783.9472 | R64: ='Impala Platinum'!I91 -> 2499.9302 | S64: ='Impala Platinum'!J91 -> 2261.5857 | T64: ='Impala Platinum'!K91 -> 2299.7878 | U64: ='Impala Platinum'!L91 -> 1997.2512
B65: Активы | C65: =Норникель!C64 -> 23435 | D65: =Норникель!D64 -> 25795 | E65: =Норникель!E64 -> 23580 | F65: =Норникель!F64 -> 23170 | H65: =Vale!C71 -> 89442 | I65: =Vale!D71 -> 86894 | J65: =Vale!E71 -> 94186 | K65: =Vale!F71 -> 80152 | M65: ='Anglo American Platinum'!I63 -> 12580.237 | N65: ='Anglo American Platinum'!J63 -> 10873.632 | O65: ='Anglo American Platinum'!K63 -> 8976.9231 | P65: ='Anglo American Platinum'!L63 -> 9397.6361 | R65: ='Impala Platinum'!I63 -> 8832.0531 | S65: ='Impala Platinum'!J63 -> 9593.5464 | T65: ='Impala Platinum'!K63 -> 8985.9947 | U65: ='Impala Platinum'!L63 -> 7309.2358
B66: Коэффициент долговой нагрузки (Debt ratio) | C66: =C64/C65 -> 0.79569021 | D66: =D64/D65 -> 0.66788137 | E66: =E64/E65 -> 0.677905 | F66: =F64/F65 -> 0.65053949 | H66: =H64/H65 -> 0.60526375 | I66: =I64/I65 -> 0.57007388 | J66: =J64/J65 -> 0.56489287 | K66: =K64/K65 -> 0.56921848 | M66: =M64/M65 -> 0.43185918 | N66: =N64/N65 -> 0.45192579 | O66: =O64/O65 -> 0.408829 | P66: =P64/P65 -> 0.40264884 | R66: =R64/R65 -> 0.28305199 | S66: =S64/S65 -> 0.23574032 | T66: =T64/T65 -> 0.25593024 | U66: =U64/U65 -> 0.27325035
B67: Долгосрочные обязательства | C67: =Норникель!C84 -> 10564 | D67: =Норникель!D84 -> 9539 | E67: =Норникель!E84 -> 7154 | F67: =Норникель!F84 -> 9154 | H67: =Vale!C104 -> 38938 | I67: =Vale!D104 -> 35645 | J67: =Vale!E104 -> 3855 | K67: =Vale!F104 -> 32534 | M67: ='Anglo American Platinum'!I80 -> 1489.595 | N67: ='Anglo American Platinum'!J80 -> 1345.7283 | O67: ='Anglo American Platinum'!K80 -> 1179.8939 | P67: ='Anglo American Platinum'!L80 -> 1304.508 | R67: ='Impala Platinum'!I81 -> 1257.4022 | S67: ='Impala Platinum'!J81 -> 1242.102 | T67: ='Impala Platinum'!K81 -> 1362.2812 | U67: ='Impala Platinum'!L81 -> 1071.2479
B68: Собственный капитал | C68: =Норникель!C89 -> 2224 | D68: =Норникель!D89 -> 1381 | E68: =Норникель!E89 -> 1273 | F68: =Норникель!F89 -> 1209 | H68: =Vale!C111 -> 35306 | I68: =Vale!D111 -> 37358 | J68: =Vale!E111 -> 40981 | K68: =Vale!F111 -> 34528 | M68: ='Anglo American Platinum'!I72 -> 7147.3464 | N68: ='Anglo American Platinum'!J72 -> 5959.5575 | O68: ='Anglo American Platinum'!K72 -> 5306.8966 | P68: ='Anglo American Platinum'!L72 -> 5613.6888 | R68: ='Impala Platinum'!I66 -> 1479.6788 | S68: ='Impala Platinum'!J66 -> 1418.5618 | T68: ='Impala Platinum'!K66 -> 1369.7082 | U68: ='Impala Platinum'!L66 -> 1709.5107
B69: Gearing | C69: =C67/(C68+C67) -> 0.82608696 | D69: =D67/(D68+D67) -> 0.8735348 | E69: =E67/(E68+E67) -> 0.84893794 | F69: =F67/(F68+F67) -> 0.88333494 | H69: =H67/(H68+H67) -> 0.52445989 | I69: =I67/(I68+I67) -> 0.48826761 | J69: =J67/(J68+J67) -> 0.085980016 | K69: =K67/(K68+K67) -> 0.48513316 | M69: =M67/(M68+M67) -> 0.17246788 | N69: =N67/(N68+N67) -> 0.18421296 | O69: =O67/(O68+O67) -> 0.18189179 | P69: =P67/(P68+P67) -> 0.18856185 | R69: =R67/(R68+R67) -> 0.45939533 | S69: =S67/(S68+S67) -> 0.46683915 | T69: =T67/(T68+T67) -> 0.49864072 | U69: =U67/(U68+U67) -> 0.38523585 | W69: заемный капитал у многих растет
B70: Leverage | C70: =C68/(C68+C67) -> 0.17391304 | D70: =D68/(D68+D67) -> 0.1264652 | E70: =E68/(E68+E67) -> 0.15106206 | F70: =F68/(F68+F67) -> 0.11666506 | H70: =H68/(H68+H67) -> 0.47554011 | I70: =I68/(I68+I67) -> 0.51173239 | J70: =J68/(J68+J67) -> 0.91401998 | K70: =K68/(K68+K67) -> 0.51486684 | M70: =M68/(M68+M67) -> 0.82753212 | N70: =N68/(N68+N67) -> 0.81578704 | O70: =O68/(O68+O67) -> 0.81810821 | P70: =P68/(P68+P67) -> 0.81143815 | R70: =R68/(R68+R67) -> 0.54060467 | S70: =S68/(S68+S67) -> 0.53316085 | T70: =T68/(T68+T67) -> 0.50135928 | U70: =U68/(U68+U67) -> 0.61476415
B71: Чистая прибыль до налогооблажения | C71: =Норникель!C22 -> 9285 | D71: =Норникель!D22 -> 7379 | E71: =Норникель!E22 -> 3534 | F71: =Норникель!F22 -> 2404 | H71: =Vale!C19 -> 29541 | I71: =Vale!D19 -> 19781 | J71: =Vale!E19 -> 11151 | K71: =Vale!F19 -> 6696 | M71: ='Anglo American Platinum'!I21 -> 7033.1818 | N71: ='Anglo American Platinum'!J21 -> 4386.8594 | O71: ='Anglo American Platinum'!K21 -> 1019.0771 | P71: ='Anglo American Platinum'!L21 -> 517.31694 | R71: ='Impala Platinum'!I21 -> 3107.4675 | S71: ='Impala Platinum'!J21 -> 2177.3325 | T71: ='Impala Platinum'!K21 -> 347.6646 | U71: ='Impala Platinum'!L21 -> -916.67557
B72: Проценты к получению | C72: =Норникель!C21 -> 52 | D72: =Норникель!D21 -> 150 | E72: =Норникель!E21 -> 41 | F72: =Норникель!F21 -> 69 | H72: =Vale!C15 -> 337 | I72: =Vale!D15 -> 520 | J72: =Vale!E15 -> 432 | K72: =Vale!F15 -> 422 | M72: ='Anglo American Platinum'!I11 -> 46.298701 | N72: ='Anglo American Platinum'!J11 -> 63.863338 | O72: ='Anglo American Platinum'!K11 -> 67.416995 | P72: ='Anglo American Platinum'!L11 -> 52.592197 | R72: ='Impala Platinum'!I15 -> 49.87013 | S72: ='Impala Platinum'!J15 -> 52.890933 | T72: ='Impala Platinum'!K15 -> 100.84412 | U72: ='Impala Platinum'!L15 -> 57.509353
B73: Проценты к уплате | C73: =Норникель!C19 -> -279 | D73: =Норникель!D19 -> -493 | E73: =Норникель!E19 -> -567 | F73: =Норникель!F19 -> -896 | H73: =Vale!C16 -> -1249 | I73: =Vale!D16 -> -1179 | J73: =Vale!E16 -> -1459 | K73: =Vale!F16 -> -1473 | M73: ='Anglo American Platinum'!I16 -> -23.181818 | N73: ='Anglo American Platinum'!J16 -> -25.098555 | O73: ='Anglo American Platinum'!K16 -> -36.29713 | P73: ='Anglo American Platinum'!L16 -> -61.036879 | R73: ='Impala Platinum'!I16 -> -61.428571 | S73: ='Impala Platinum'!J16 -> -36.925099 | T73: ='Impala Platinum'!K16 -> -34.608891 | U73: ='Impala Platinum'!L16 -> -51.30946
B74: EBIT | C74: =C71+C72+C73 -> 9058 | D74: =D71+D72+D73 -> 7036 | E74: =E71+E72+E73 -> 3008 | F74: =F71+F72+F73 -> 1577 | H74: =H71+H72+H73 -> 28629 | I74: =I71+I72+I73 -> 19122 | J74: =J71+J72+J73 -> 10124 | K74: =K71+K72+K73 -> 5645 | M74: =M71+M72+M73 -> 7056.2987 | N74: =N71+N72+N73 -> 4425.6242 | O74: =O71+O72+O73 -> 1050.197 | P74: =P71+P72+P73 -> 508.87226 | R74: =R71+R72+R73 -> 3095.9091 | S74: =S71+S72+S73 -> 2193.2983 | T74: =T71+T72+T73 -> 413.89983 | U74: =U71+U72+U73 -> -910.47568
B75: Коэффициент покрытия процентов (Interest cover) | C75: =ABS(C74/C73) -> 32.46595 | D75: =ABS(D74/D73) -> 14.271805 | E75: =ABS(E74/E73) -> 5.3051146 | F75: =ABS(F74/F73) -> 1.7600446 | H75: =ABS(H74/H73) -> 22.921537 | I75: =ABS(I74/I73) -> 16.21883 | J75: =ABS(J74/J73) -> 6.9389993 | K75: =ABS(K74/K73) -> 3.832315 | M75: =ABS(M74/M73) -> 304.38936 | N75: =ABS(N74/N73) -> 176.32984 | O75: =ABS(O74/O73) -> 28.933333 | P75: =ABS(P74/P73) -> 8.3371278 | R75: =ABS(R74/R73) -> 50.39852 | S75: =ABS(S74/S73) -> 59.398577 | T75: =ABS(T74/T73) -> 11.95935 | U75: =ABS(U74/U73) -> 17.744792 | W75: падает - это очень плохо, еще и упал ниже минимальных адекватных значений

Sheet Горизонтальный анализ
B2: ОТЧЁТ О ПРИБЫЛЯХ И УБЫТКАХ | C2: в миллионах долларов США | G2: Абсолютное изменение | J2: Темп роста | M2: Темп прироста
C3: 2021 | D3: 2022 | E3: 2023 | F3: 2024 | G3: 2021-2022 | H3: 2022-2023 | I3: 2023-2024 | J3: 2021-2022 | K3: 2022-2023 | L3: 2023-2024 | M3: 2021-2022 | N3: 2022-2023 | O3: 2023-2024
B5: Выручка
B6: Выручка от реализации металлов | C6: 17103 | D6: 16073 | E6: 13702 | F6: 11848 | G6: =D6-C6 -> -1030 | H6: =E6-D6 -> -2371 | I6: =F6-E6 -> -1854 | J6: =D6/C6 -> 0.93977665 | K6: =E6/D6 -> 0.85248553 | L6: =F6/E6 -> 0.86469129 | M6: =G6/C6 -> -0.060223353 | N6: =H6/D6 -> -0.14751447 | O6: =I6/E6 -> -0.13530871
B7: Выручка от прочей реализации | C7: 749 | D7: 803 | E7: 707 | F7: 687 | G7: =D7-C7 -> 54 | H7: =E7-D7 -> -96 | I7: =F7-E7 -> -20 | J7: =D7/C7 -> 1.0720961 | K7: =E7/D7 -> 0.88044832 | L7: =F7/E7 -> 0.97171146 | M7: =G7/C7 -> 0.072096128 | N7: =H7/D7 -> -0.11955168 | O7: =I7/E7 -> -0.028288543
B8: Итого выручка | C8: 17852 | D8: 16876 | E8: 14409 | F8: 12535 | G8: =D8-C8 -> -976 | H8: =E8-D8 -> -2467 | I8: =F8-E8 -> -1874 | J8: =D8/C8 -> 0.94532825 | K8: =E8/D8 -> 0.85381607 | L8: =F8/E8 -> 0.8699424 | M8: =G8/C8 -> -0.054671745 | N8: =H8/D8 -> -0.14618393 | O8: =I8/E8 -> -0.1300576 | P8: Выручка падает, себестоимость растет
B9: Себестоимость реализованных металлов | C9: -5057 | D9: -6103 | E9: -6344 | F9: -6232 | G9: =D9-C9 -> -1046 | H9: =E9-D9 -> -241 | I9: =F9-E9 -> 112 | J9: =D9/C9 -> 1.206842 | K9: =E9/D9 -> 1.0394888 | L9: =F9/E9 -> 0.98234552 | M9: =G9/C9 -> 0.206842 | N9: =H9/D9 -> 0.039488776 | O9: =I9/E9 -> -0.017654477
B10: Себестоимость прочей реализации | C10: -753 | D10: -810 | E10: -688 | F10: -656 | G10: =D10-C10 -> -57 | H10: =E10-D10 -> 122 | I10: =F10-E10 -> 32 | J10: =D10/C10 -> 1.0756972 | K10: =E10/D10 -> 0.84938272 | L10: =F10/E10 -> 0.95348837 | M10: =G10/C10 -> 0.075697211 | N10: =H10/D10 -> -0.15061728 | O10: =I10/E10 -> -0.046511628
B11: Валовая прибыль | C11: 12042 | D11: 9963 | E11: 7377 | F11: 5647 | G11: =D11-C11 -> -2079 | H11: =E11-D11 -> -2586 | I11: =F11-E11 -> -1730 | J11: =D11/C11 -> 0.82735426 | K11: =E11/D11 -> 0.74043963 | L11: =F11/E11 -> 0.76548733 | M11: =G11/C11 -> -0.17264574 | N11: =H11/D11 -> -0.25956037 | O11: =I11/E11 -> -0.23451267
B12: Административные расходы | C12: -989 | D12: -1353 | E12: -1093 | F12: -1046 | G12: =D12-C12 -> -364 | H12: =E12-D12 -> 260 | I12: =F12-E12 -> 47 | J12: =D12/C12 -> 1.3680485 | K12: =E12/D12 -> 0.80783444 | L12: =F12/E12 -> 0.95699909 | M12: =G12/C12 -> 0.36804853 | N12: =H12/D12 -> -0.19216556 | O12: =I12/E12 -> -0.043000915
B13: Коммерческие расходы | C13: 184 | D13: 261 | E13: 296 | F13: 408 | G13: =D13-C13 -> 77 | H13: =E13-D13 -> 35 | I13: =F13-E13 -> 112 | J13: =D13/C13 -> 1.4184783 | K13: =E13/D13 -> 1.1340996 | L13: =F13/E13 -> 1.3783784 | M13: =G13/C13 -> 0.41847826 | N13: =H13/D13 -> 0.13409962 | O13: =I13/E13 -> 0.37837838 | P13: Проблемы с логистикой: растут комерческие расходы и убыкти от обеценения нефти
B14: Убыток от обесценения нефинансовых активов, нетто | C14: 48 | D14: 90 | E14: 179 | F14: 441 | G14: =D14-C14 -> 42 | H14: =E14-D14 -> 89 | I14: =F14-E14 -> 262 | J14: =D14/C14 -> 1.875 | K14: =E14/D14 -> 1.9888889 | L14: =F14/E14 -> 2.4636872 | M14: =G14/C14 -> 0.875 | N14: =H14/D14 -> 0.98888889 | O14: =I14/E14 -> 1.4636872
B15: Прочие операционные расходы, нетто | C15: -1285 | D15: -678 | E15: -269 | F15: -178 | G15: =D15-C15 -> 607 | H15: =E15-D15 -> 409 | I15: =F15-E15 -> 91 | J15: =D15/C15 -> 0.52762646 | K15: =E15/D15 -> 0.39675516 | L15: =F15/E15 -> 0.66171004 | M15: =G15/C15 -> -0.47237354 | N15: =H15/D15 -> -0.60324484 | O15: =I15/E15 -> -0.33828996
B16: Прибыль от операционной деятельности | C16: 9536 | D16: 7581 | E16: 5540 | F16: 3574 | G16: =D16-C16 -> -1955 | H16: =E16-D16 -> -2041 | I16: =F16-E16 -> -1966 | J16: =D16/C16 -> 0.79498742 | K16: =E16/D16 -> 0.7307743 | L16: =F16/E16 -> 0.64512635 | M16: =G16/C16 -> -0.20501258 | N16: =H16/D16 -> -0.2692257 | O16: =I16/E16 -> -0.35487365
B17: (Отрицательные)/положительные курсовые разницы, нетто | C17: -53 | D17: 251 | E17: -1512 | F17: -343 | G17: =D17-C17 -> 304 | H17: =E17-D17 -> -1763 | I17: =F17-E17 -> 1169 | J17: =D17/C17 -> -4.7358491 | K17: =E17/D17 -> -6.0239044 | L17: =F17/E17 -> 0.22685185 | M17: =G17/C17 -> -5.7358491 | N17: =H17/D17 -> -7.0239044 | O17: =I17/E17 -> -0.77314815
B18: Финансовые расходы, нетто | C18: -279 | D18: -493 | E18: -567 | F18: -896 | G18: =D18-C18 -> -214 | H18: =E18-D18 -> -74 | I18: =F18-E18 -> -329 | J18: =D18/C18 -> 1.7670251 | K18: =E18/D18 -> 1.1501014 | L18: =F18/E18 -> 1.5802469 | M18: =G18/C18 -> 0.76702509 | N18: =H18/D18 -> 0.15010142 | O18: =I18/E18 -> 0.58024691
B19: Прибыль/(убыток) от выбытия дочерних организаций и зарубежных совместных операций | C19: 29 | D19: -110 | E19: 32 | F19: 0 | G19: =D19-C19 -> -139 | H19: =E19-D19 -> 142 | I19: =F19-E19 -> -32 | J19: =D19/C19 -> -3.7931034 | K19: =E19/D19 -> -0.29090909 | L19: =F19/E19 -> 0 | M19: =G19/C19 -> -4.7931034 | N19: =H19/D19 -> -1.2909091 | O19: =I19/E19 -> -1
B20: Прибыль от инвестиционной деятельности, нетто | C20: 52 | D20: 150 | E20: 41 | F20: 69 | G20: =D20-C20 -> 98 | H20: =E20-D20 -> -109 | I20: =F20-E20 -> 28 | J20: =D20/C20 -> 2.8846154 | K20: =E20/D20 -> 0.27333333 | L20: =F20/E20 -> 1.6829268 | M20: =G20/C20 -> 1.8846154 | N20: =H20/D20 -> -0.72666667 | O20: =I20/E20 -> 0.68292683
B21: Прибыль до налогообложения | C21: 9285 | D21: 7379 | E21: 3534 | F21: 2404 | G21: =D21-C21 -> -1906 | H21: =E21-D21 -> -3845 | I21: =F21-E21 -> -1130 | J21: =D21/C21 -> 0.79472267 | K21: =E21/D21 -> 0.47892668 | L21: =F21/E21 -> 0.68024901 | M21: =G21/C21 -> -0.20527733 | N21: =H21/D21 -> -0.52107332 | O21: =I21/E21 -> -0.31975099
B22: Расходы по налогу на прибыль | C22: -2311 | D22: -1525 | E22: -664 | F22: -589 | G22: =D22-C22 -> 786 | H22: =E22-D22 -> 861 | I22: =F22-E22 -> 75 | J22: =D22/C22 -> 0.65988749 | K22: =E22/D22 -> 0.43540984 | L22: =F22/E22 -> 0.88704819 | M22: =G22/C22 -> -0.34011251 | N22: =H22/D22 -> -0.56459016 | O22: =I22/E22 -> -0.11295181
B23: Прибыль за год | C23: 6974 | D23: 5854 | E23: 2870 | F23: 1815 | G23: =D23-C23 -> -1120 | H23: =E23-D23 -> -2984 | I23: =F23-E23 -> -1055 | J23: =D23/C23 -> 0.8394035 | K23: =E23/D23 -> 0.49026307 | L23: =F23/E23 -> 0.63240418 | M23: =G23/C23 -> -0.1605965 | N23: =H23/D23 -> -0.50973693 | O23: =I23/E23 -> -0.36759582
B25: ОТЧЁТ О ФИНАНСОВОМ ПОЛОЖЕНИИ | C25: в миллионах долларов США | G25: Абсолютное изменение | J25: Темп роста | M25: Темп прироста
C26: 2021 | D26: 2022 | E26: 2023 | F26: 2024 | G26: 2021-2022 | H26: 2022-2023 | I26: 2023-2024 | J26: 2021-2022 | K26: 2022-2023 | L26: 2023-2024 | M26: 2021-2022 | N26: 2022-2023 | O26: 2023-2024
B28: АКТИВЫ
B29: Внеоборотные активы
B30: Основные средства | C30: 12699 | D30: 16264 | E30: 15181 | F30: 15261 | G30: =D30-C30 -> 3565 | H30: =E30-D30 -> -1083 | I30: =F30-E30 -> 80 | J30: =D30/C30 -> 1.2807308 | K30: =E30/D30 -> 0.93341121 | L30: =F30/E30 -> 1.0052697 | M30: =G30/C30 -> 0.28073077 | N30: =H30/D30 -> -0.066588785 | O30: =I30/E30 -> 0.0052697451 | P30: Эффект пересчета в валюту представления
B31: Нематериальные активы | C31: 265 | D31: 302 | E31: 238 | F31: 206 | G31: =D31-C31 -> 37 | H31: =E31-D31 -> -64 | I31: =F31-E31 -> -32 | J31: =D31/C31 -> 1.1396226 | K31: =E31/D31 -> 0.78807947 | L31: =F31/E31 -> 0.86554622 | M31: =G31/C31 -> 0.13962264 | N31: =H31/D31 -> -0.21192053 | O31: =I31/E31 -> -0.13445378
B32: Инвестиции в ассоциированные организации и совместные предприятия | D32: 8 | E32: 76 | F32: 181 | G32: =D32-C32 -> 8 | H32: =E32-D32 -> 68 | I32: =F32-E32 -> 105 | K32: =E32/D32 -> 9.5 | L32: =F32/E32 -> 2.3815789 | N32: =H32/D32 -> 8.5 | O32: =I32/E32 -> 1.3815789
B33: Прочие финансовые активы | C33: 89 | D33: 113 | E33: 58 | F33: 57 | G33: =D33-C33 -> 24 | H33: =E33-D33 -> -55 | I33: =F33-E33 -> -1 | J33: =D33/C33 -> 1.2696629 | K33: =E33/D33 -> 0.51327434 | L33: =F33/E33 -> 0.98275862 | M33: =G33/C33 -> 0.26966292 | N33: =H33/D33 -> -0.48672566 | O33: =I33/E33 -> -0.017241379
B34: Отложенные налоговые активы | C34: 167 | D34: 340 | E34: 335 | F34: 328 | G34: =D34-C34 -> 173 | H34: =E34-D34 -> -5 | I34: =F34-E34 -> -7 | J34: =D34/C34 -> 2.0359281 | K34: =E34/D34 -> 0.98529412 | L34: =F34/E34 -> 0.97910448 | M34: =G34/C34 -> 1.0359281 | N34: =H34/D34 -> -0.014705882 | O34: =I34/E34 -> -0.020895522
B35: Прочие внеоборотные активы | C35: 345 | D35: 365 | E35: 350 | F35: 292 | G35: =D35-C35 -> 20 | H35: =E35-D35 -> -15 | I35: =F35-E35 -> -58 | J35: =D35/C35 -> 1.057971 | K35: =E35/D35 -> 0.95890411 | L35: =F35/E35 -> 0.83428571 | M35: =G35/C35 -> 0.057971014 | N35: =H35/D35 -> -0.04109589 | O35: =I35/E35 -> -0.16571429
B36: ИТОГО ВНЕОБОРОТНЫЕ АКТИВЫ | C36: 13565 | D36: 17392 | E36: 16238 | F36: 16325 | G36: =D36-C36 -> 3827 | H36: =E36-D36 -> -1154 | I36: =F36-E36 -> 87 | J36: =D36/C36 -> 1.2821231 | K36: =E36/D36 -> 0.93364765 | L36: =F36/E36 -> 1.0053578 | M36: =G36/C36 -> 0.28212311 | N36: =H36/D36 -> -0.066352346 | O36: =I36/E36 -> 0.0053578027
B37: Оборотные активы | P37: В целом, Норникель зачем-то в 22 достаточно много денег вложил в оборотные активы, а потом начал больше любить обычные денежки
B38: Запасы | C38: 3026 | D38: 4945 | E38: 3817 | F38: 3114 | G38: =D38-C38 -> 1919 | H38: =E38-D38 -> -1128 | I38: =F38-E38 -> -703 | J38: =D38/C38 -> 1.6341705 | K38: =E38/D38 -> 0.7718908 | L38: =F38/E38 -> 0.81582395 | M38: =G38/C38 -> 0.63417052 | N38: =H38/D38 -> -0.2281092 | O38: =I38/E38 -> -0.18417605
B39: Торговая и прочая дебиторская задолженность | C39: 468 | D39: 846 | E39: 764 | F39: 1374 | G39: =D39-C39 -> 378 | H39: =E39-D39 -> -82 | I39: =F39-E39 -> 610 | J39: =D39/C39 -> 1.8076923 | K39: =E39/D39 -> 0.90307329 | L39: =F39/E39 -> 1.7984293 | M39: =G39/C39 -> 0.80769231 | N39: =H39/D39 -> -0.096926714 | O39: =I39/E39 -> 0.79842932
B40: Авансы выданные и расходы будущих периодов | C40: 111 | D40: 192 | E40: 173 | F40: 135 | G40: =D40-C40 -> 81 | H40: =E40-D40 -> -19 | I40: =F40-E40 -> -38 | J40: =D40/C40 -> 1.7297297 | K40: =E40/D40 -> 0.90104167 | L40: =F40/E40 -> 0.78034682 | M40: =G40/C40 -> 0.72972973 | N40: =H40/D40 -> -0.098958333 | O40: =I40/E40 -> -0.21965318
B41: Прочие финансовые активы | C41: 43 | D41: 40 | E41: 3 | F41: 69 | G41: =D41-C41 -> -3 | H41: =E41-D41 -> -37 | I41: =F41-E41 -> 66 | J41: =D41/C41 -> 0.93023256 | K41: =E41/D41 -> 0.075 | L41: =F41/E41 -> 23 | M41: =G41/C41 -> -0.069767442 | N41: =H41/D41 -> -0.925 | O41: =I41/E41 -> 22
B42: Авансовые платежи по налогу на прибыль | C42: 203 | D42: 17 | E42: 101 | F42: 38 | G42: =D42-C42 -> -186 | H42: =E42-D42 -> 84 | I42: =F42-E42 -> -63 | J42: =D42/C42 -> 0.083743842 | K42: =E42/D42 -> 5.9411765 | L42: =F42/E42 -> 0.37623762 | M42: =G42/C42 -> -0.91625616 | N42: =H42/D42 -> 4.9411765 | O42: =I42/E42 -> -0.62376238
B43: Прочие налоги к возмещению | C43: 412 | D43: 477 | E43: 344 | F43: 292 | G43: =D43-C43 -> 65 | H43: =E43-D43 -> -133 | I43: =F43-E43 -> -52 | J43: =D43/C43 -> 1.157767 | K43: =E43/D43 -> 0.721174 | L43: =F43/E43 -> 0.84883721 | M43: =G43/C43 -> 0.15776699 | N43: =H43/D43 -> -0.278826 | O43: =I43/E43 -> -0.15116279
B44: Денежные средства и их эквиваленты | C44: 5547 | D44: 1882 | E44: 2139 | F44: 1822 | G44: =D44-C44 -> -3665 | H44: =E44-D44 -> 257 | I44: =F44-E44 -> -317 | J44: =D44/C44 -> 0.3392825 | K44: =E44/D44 -> 1.1365569 | L44: =F44/E44 -> 0.85179991 | M44: =G44/C44 -> -0.6607175 | N44: =H44/D44 -> 0.13655685 | O44: =I44/E44 -> -0.14820009
B45: Прочие оборотные активы | C45: 60 | D45: 4 | E45: 1 | F45: 1 | G45: =D45-C45 -> -56 | H45: =E45-D45 -> -3 | I45: =F45-E45 -> 0 | J45: =D45/C45 -> 0.066666667 | K45: =E45/D45 -> 0.25 | L45: =F45/E45 -> 1 | M45: =G45/C45 -> -0.93333333 | N45: =H45/D45 -> -0.75 | O45: =I45/E45 -> 0
B46: ИТОГО ОБОРОТНЫЕ АКТИВЫ | C46: 9870 | D46: 8403 | E46: 7342 | F46: 6845 | G46: =D46-C46 -> -1467 | H46: =E46-D46 -> -1061 | I46: =F46-E46 -> -497 | J46: =D46/C46 -> 0.85136778 | K46: =E46/D46 -> 0.87373557 | L46: =F46/E46 -> 0.93230727 | M46: =G46/C46 -> -0.14863222 | N46: =H46/D46 -> -0.12626443 | O46: =I46/E46 -> -0.067692727
B47: ИТОГО АКТИВЫ | C47: 23435 | D47: 25795 | E47: 23580 | F47: 23170 | G47: =D47-C47 -> 2360 | H47: =E47-D47 -> -2215 | I47: =F47-E47 -> -410 | J47: =D47/C47 -> 1.1007041 | K47: =E47/D47 -> 0.91413065 | L47: =F47/E47 -> 0.98261238 | M47: =G47/C47 -> 0.10070408 | N47: =H47/D47 -> -0.085869355 | O47: =I47/E47 -> -0.017387617
B49: КАПИТАЛ И ОБЯЗАТЕЛЬСТВА
B50: Капитал и резервы
B51: Уставный капитал | C51: 6 | D51: 6 | E51: 6 | F51: 6 | G51: =D51-C51 -> 0 | H51: =E51-D51 -> 0 | I51: =F51-E51 -> 0 | J51: =D51/C51 -> 1 | K51: =E51/D51 -> 1 | L51: =F51/E51 -> 1 | M51: =G51/C51 -> 0 | N51: =H51/D51 -> 0 | O51: =I51/E51 -> 0
B52: Эмиссионный доход | C52: 1218 | D52: 1212 | E52: 1212 | F52: 1212 | G52: =D52-C52 -> -6 | H52: =E52-D52 -> 0 | I52: =F52-E52 -> 0 | J52: =D52/C52 -> 0.99507389 | K52: =E52/D52 -> 1 | L52: =F52/E52 -> 1 | M52: =G52/C52 -> -0.0049261084 | N52: =H52/D52 -> 0 | O52: =I52/E52 -> 0
B53: Собственные акции, выкупленные у акционеров | C53: -305 | G53: =D53-C53 -> 305 | H53: =E53-D53 -> 0 | I53: =F53-E53 -> 0 | J53: =D53/C53 -> 0
B54: Резерв накопленных курсовых разниц и прочие резервы | C54: -5415 | D54: -4541 | E54: -6146 | F54: -6979 | G54: =D54-C54 -> 874 | H54: =E54-D54 -> -1605 | I54: =F54-E54 -> -833 | J54: =D54/C54 -> 0.83859649 | K54: =E54/D54 -> 1.3534464 | L54: =F54/E54 -> 1.1355353 | M54: =G54/C54 -> -0.16140351 | N54: =H54/D54 -> 0.35344638 | O54: =I54/E54 -> 0.13553531
B55: Нераспределенная прибыль | C55: 8184 | D55: 10448 | E55: 11324 | F55: 12638 | G55: =D55-C55 -> 2264 | H55: =E55-D55 -> 876 | I55: =F55-E55 -> 1314 | J55: =D55/C55 -> 1.2766373 | K55: =E55/D55 -> 1.0838438 | L55: =F55/E55 -> 1.1160367 | M55: =G55/C55 -> 0.27663734 | N55: =H55/D55 -> 0.083843798 | O55: =I55/E55 -> 0.11603674
B56: ИТОГО КАПИТАЛ | C56: 4788 | D56: 8567 | E56: 7595 | F56: 8097 | G56: =D56-C56 -> 3779 | H56: =E56-D56 -> -972 | I56: =F56-E56 -> 502 | J56: =D56/C56 -> 1.7892648 | K56: =E56/D56 -> 0.88654138 | L56: =F56/E56 -> 1.0660961 | M56: =G56/C56 -> 0.78926483 | N56: =H56/D56 -> -0.11345862 | O56: =I56/E56 -> 0.066096116
B57: Долгосрочные обязательства | P57: Тут долгосрочные обязательства сокращались до 2024 года, потом они насали наращиваться
B58: Кредиты и займы | C58: 8616 | D58: 7189 | E58: 5377 | F58: 7112 | G58: =D58-C58 -> -1427 | H58: =E58-D58 -> -1812 | I58: =F58-E58 -> 1735 | J58: =D58/C58 -> 0.8343779 | K58: =E58/D58 -> 0.74794825 | L58: =F58/E58 -> 1.3226706 | M58: =G58/C58 -> -0.1656221 | N58: =H58/D58 -> -0.25205175 | O58: =I58/E58 -> 0.32267063
B59: Обязательства по аренде | C59: 178 | D59: 190 | E59: 466 | F59: 381 | G59: =D59-C59 -> 12 | H59: =E59-D59 -> 276 | I59: =F59-E59 -> -85 | J59: =D59/C59 -> 1.0674157 | K59: =E59/D59 -> 2.4526316 | L59: =F59/E59 -> 0.81759657 | M59: =G59/C59 -> 0.06741573 | N59: =H59/D59 -> 1.4526316 | O59: =I59/E59 -> -0.18240343
B60: Оценочные обязательства | C60: 894 | D60: 916 | E60: 689 | F60: 881 | G60: =D60-C60 -> 22 | H60: =E60-D60 -> -227 | I60: =F60-E60 -> 192 | J60: =D60/C60 -> 1.0246085 | K60: =E60/D60 -> 0.75218341 | L60: =F60/E60 -> 1.2786647 | M60: =G60/C60 -> 0.024608501 | N60: =H60/D60 -> -0.24781659 | O60: =I60/E60 -> 0.27866473
B61: Социальные обязательства | C61: 633 | D61: 613 | E61: 399 | F61: 299 | G61: =D61-C61 -> -20 | H61: =E61-D61 -> -214 | I61: =F61-E61 -> -100 | J61: =D61/C61 -> 0.96840442 | K61: =E61/D61 -> 0.65089723 | L61: =F61/E61 -> 0.74937343 | M61: =G61/C61 -> -0.031595577 | N61: =H61/D61 -> -0.34910277 | O61: =I61/E61 -> -0.25062657
B62: Торговая и прочая долгосрочная кредиторская задолженность | C62: 55 | D62: 56 | E62: 51 | F62: 41 | G62: =D62-C62 -> 1 | H62: =E62-D62 -> -5 | I62: =F62-E62 -> -10 | J62: =D62/C62 -> 1.0181818 | K62: =E62/D62 -> 0.91071429 | L62: =F62/E62 -> 0.80392157 | M62: =G62/C62 -> 0.018181818 | N62: =H62/D62 -> -0.089285714 | O62: =I62/E62 -> -0.19607843
B63: Производные финансовые инструменты | C63: 72 | D63: 67 | E63: 0 | F63: 0 | G63: =D63-C63 -> -5 | H63: =E63-D63 -> -67 | I63: =F63-E63 -> 0 | J63: =D63/C63 -> 0.93055556 | K63: =E63/D63 -> 0 | M63: =G63/C63 -> -0.069444444 | N63: =H63/D63 -> -1
B64: Отложенные налоговые обязательства | C64: 73 | D64: 415 | E64: 142 | F64: 381 | G64: =D64-C64 -> 342 | H64: =E64-D64 -> -273 | I64: =F64-E64 -> 239 | J64: =D64/C64 -> 5.6849315 | K64: =E64/D64 -> 0.34216867 | L64: =F64/E64 -> 2.6830986 | M64: =G64/C64 -> 4.6849315 | N64: =H64/D64 -> -0.65783133 | O64: =I64/E64 -> 1.6830986
B65: Прочие долгосрочные обязательства | C65: 43 | D65: 93 | E65: 30 | F65: 59 | G65: =D65-C65 -> 50 | H65: =E65-D65 -> -63 | I65: =F65-E65 -> 29 | J65: =D65/C65 -> 2.1627907 | K65: =E65/D65 -> 0.32258065 | L65: =F65/E65 -> 1.9666667 | M65: =G65/C65 -> 1.1627907 | N65: =H65/D65 -> -0.67741935 | O65: =I65/E65 -> 0.96666667
B66: ИТОГО ДОЛГОСРОЧНЫЕ ОБЯЗАТЕЛЬСТВА | C66: 10564 | D66: 9539 | E66: 7154 | F66: 9154 | G66: =D66-C66 -> -1025 | H66: =E66-D66 -> -2385 | I66: =F66-E66 -> 2000 | J66: =D66/C66 -> 0.90297236 | K66: =E66/D66 -> 0.74997379 | L66: =F66/E66 -> 1.2795639 | M66: =G66/C66 -> -0.097027641 | N66: =H66/D66 -> -0.25002621 | O66: =I66/E66 -> 0.27956388
B67: Краткосрочные обязательства
B68: Кредиты и займы | C68: 1610 | D68: 4295 | E68: 4335 | F68: 2834 | G68: =D68-C68 -> 2685 | H68: =E68-D68 -> 40 | I68: =F68-E68 -> -1501 | J68: =D68/C68 -> 2.6677019 | K68: =E68/D68 -> 1.0093132 | L68: =F68/E68 -> 0.65374856 | M68: =G68/C68 -> 1.6677019 | N68: =H68/D68 -> 0.0093131548 | O68: =I68/E68 -> -0.34625144 | P68: В 2023 явно были серьезные проблемы с ликвидностью
B69: Обязательства по аренде | C69: 57 | D69: 43 | E69: 54 | F69: 81 | G69: =D69-C69 -> -14 | H69: =E69-D69 -> 11 | I69: =F69-E69 -> 27 | J69: =D69/C69 -> 0.75438596 | K69: =E69/D69 -> 1.255814 | L69: =F69/E69 -> 1.5 | M69: =G69/C69 -> -0.24561404 | N69: =H69/D69 -> 0.25581395 | O69: =I69/E69 -> 0.5
B70: Торговая и прочая кредиторская задолженность | C70: 2224 | D70: 1381 | E70: 1273 | F70: 1209 | G70: =D70-C70 -> -843 | H70: =E70-D70 -> -108 | I70: =F70-E70 -> -64 | J70: =D70/C70 -> 0.62095324 | K70: =E70/D70 -> 0.9217958 | L70: =F70/E70 -> 0.94972506 | M70: =G70/C70 -> -0.37904676 | N70: =H70/D70 -> -0.0782042 | O70: =I70/E70 -> -0.050274941
B71: Дивиденды к уплате | C71: 3146 | D71: 496 | E71: 1924 | F71: 721 | G71: =D71-C71 -> -2650 | H71: =E71-D71 -> 1428 | I71: =F71-E71 -> -1203 | J71: =D71/C71 -> 0.15766052 | K71: =E71/D71 -> 3.8790323 | L71: =F71/E71 -> 0.37474012 | M71: =G71/C71 -> -0.84233948 | N71: =H71/D71 -> 2.8790323 | O71: =I71/E71 -> -0.62525988
B72: Обязательства по вознаграждениям работникам | C72: 417 | D72: 585 | E72: 555 | F72: 444 | G72: =D72-C72 -> 168 | H72: =E72-D72 -> -30 | I72: =F72-E72 -> -111 | J72: =D72/C72 -> 1.4028777 | K72: =E72/D72 -> 0.94871795 | L72: =F72/E72 -> 0.8 | M72: =G72/C72 -> 0.4028777 | N72: =H72/D72 -> -0.051282051 | O72: =I72/E72 -> -0.2
B73: Оценочные обязательства | D73: 180 | E73: 90 | F73: 173 | G73: =D73-C73 -> 180 | H73: =E73-D73 -> -90 | I73: =F73-E73 -> 83 | K73: =E73/D73 -> 0.5 | L73: =F73/E73 -> 1.9222222 | N73: =H73/D73 -> -0.5 | O73: =I73/E73 -> 0.92222222
B74: Социальные обязательства | C74: 158 | D74: 201 | E74: 207 | F74: 164 | G74: =D74-C74 -> 43 | H74: =E74-D74 -> 6 | I74: =F74-E74 -> -43 | J74: =D74/C74 -> 1.2721519 | K74: =E74/D74 -> 1.0298507 | L74: =F74/E74 -> 0.79227053 | M74: =G74/C74 -> 0.2721519 | N74: =H74/D74 -> 0.029850746 | O74: =I74/E74 -> -0.20772947
B75: Производные финансовые инструменты | C75: 15 | D75: 0 | E75: 114 | F75: 0 | G75: =D75-C75 -> -15 | H75: =E75-D75 -> 114 | I75: =F75-E75 -> -114 | J75: =D75/C75 -> 0 | L75: =F75/E75 -> 0 | M75: =G75/C75 -> -1 | O75: =I75/E75 -> -1
B76: Обязательства по налогу на прибыль | C76: 41 | D76: 169 | E76: 7 | F76: 49 | G76: =D76-C76 -> 128 | H76: =E76-D76 -> -162 | I76: =F76-E76 -> 42 | J76: =D76/C76 -> 4.1219512 | K76: =E76/D76 -> 0.041420118 | L76: =F76/E76 -> 7 | M76: =G76/C76 -> 3.1219512 | N76: =H76/D76 -> -0.95857988 | O76: =I76/E76 -> 6
B77: Прочие налоговые обязательства | C77: 269 | D77: 339 | E77: 272 | F77: 244 | G77: =D77-C77 -> 70 | H77: =E77-D77 -> -67 | I77: =F77-E77 -> -28 | J77: =D77/C77 -> 1.260223 | K77: =E77/D77 -> 0.80235988 | L77: =F77/E77 -> 0.89705882 | M77: =G77/C77 -> 0.26022305 | N77: =H77/D77 -> -0.19764012 | O77: =I77/E77 -> -0.10294118
B78: Резервы | C78: 26 | G78: =D78-C78 -> -26 | H78: =E78-D78 -> 0 | I78: =F78-E78 -> 0 | J78: =D78/C78 -> 0 | M78: =G78/C78 -> -1
B79: ИТОГО КРАТКОСРОЧНЫЕ ОБЯЗАТЕЛЬСТВА | C79: 8083 | D79: 7689 | E79: 8831 | F79: 5919 | G79: =D79-C79 -> -394 | H79: =E79-D79 -> 1142 | I79: =F79-E79 -> -2912 | J79: =D79/C79 -> 0.95125572 | K79: =E79/D79 -> 1.1485239 | L79: =F79/E79 -> 0.67025252 | M79: =G79/C79 -> -0.048744278 | N79: =H79/D79 -> 0.14852387 | O79: =I79/E79 -> -0.32974748
B80: ИТОГО ОБЯЗАТЕЛЬСТВА | C80: 18647 | D80: 17228 | E80: 15985 | F80: 15073 | G80: =D80-C80 -> -1419 | H80: =E80-D80 -> -1243 | I80: =F80-E80 -> -912 | J80: =D80/C80 -> 0.92390197 | K80: =E80/D80 -> 0.92785001 | L80: =F80/E80 -> 0.94294651 | M80: =G80/C80 -> -0.076098032 | N80: =H80/D80 -> -0.072149988 | O80: =I80/E80 -> -0.057053488
B81: ИТОГО КАПИТАЛ И ОБЯЗАТЕЛЬСТВА | C81: 23435 | D81: 25795 | E81: 23580 | F81: 23170 | G81: =D81-C81 -> 2360 | H81: =E81-D81 -> -2215 | I81: =F81-E81 -> -410 | J81: =D81/C81 -> 1.1007041 | K81: =E81/D81 -> 0.91413065 | L81: =F81/E81 -> 0.98261238 | M81: =G81/C81 -> 0.10070408 | N81: =H81/D81 -> -0.085869355 | O81: =I81/E81 -> -0.017387617

Sheet Вертикальный анализ
B2: ОТЧЁТ О ПРИБЫЛЯХ И УБЫТКАХ | D2: в миллионах долларов США | H2: Удельный вес к выручке
D3: 2021 | E3: 2022 | F3: 2023 | G3: 2024 | H3: 2021 | I3: 2022 | J3: 2023 | K3: 2024
B5: Выручка
B6: Выручка от реализации металлов | D6: 17103 | E6: 16073 | F6: 13702 | G6: 11848 | H6: =D6/D$8 -> 0.95804392 | I6: =E6/E$8 -> 0.95241763 | J6: =F6/F$8 -> 0.95093344 | K6: =G6/G$8 -> 0.94519346
B7: Выручка от прочей реализации | D7: 749 | E7: 803 | F7: 707 | G7: 687 | H7: =D7/D$8 -> 0.041956083 | I7: =E7/E$8 -> 0.047582365 | J7: =F7/F$8 -> 0.049066556 | K7: =G7/G$8 -> 0.054806542
B8: ИТОГО ВЫРУЧКА | D8: 17852 | E8: 16876 | F8: 14409 | G8: 12535 | H8: =D8/D$8 -> 1 | I8: =E8/E$8 -> 1 | J8: =F8/F$8 -> 1 | K8: =G8/G$8 -> 1 | L8: Выручка падает, себестоимость растет - очень грустная тенденция
B9: Себестоимость реализованных металлов | C9: Себестоимость реал. металлов | D9: 5057 | E9: 6103 | F9: 6344 | G9: 6232 | H9: =D9/D$8 -> 0.28327358 | I9: =E9/E$8 -> 0.36163783 | J9: =F9/F$8 -> 0.44028038 | K9: =G9/G$8 -> 0.49716793
B10: Себестоимость прочей реализации | C10: С-ть проч. реализации | D10: -753 | E10: -810 | F10: -688 | G10: -656 | H10: =D10/D$8 -> -0.042180148 | I10: =E10/E$8 -> -0.047997156 | J10: =F10/F$8 -> -0.047747935 | K10: =G10/G$8 -> -0.052333466
B11: Валовая прибыль | D11: 12042 | E11: 9963 | F11: 7377 | G11: 5647 | H11: =D11/D$8 -> 0.67454627 | I11: =E11/E$8 -> 0.59036502 | J11: =F11/F$8 -> 0.51197168 | K11: =G11/G$8 -> 0.4504986
B12: Административные расходы | C12: Адм. расходы | D12: -989 | E12: -1353 | F12: -1093 | G12: -1046 | H12: =D12/D$8 -> -0.055399955 | I12: =E12/E$8 -> -0.080173027 | J12: =F12/F$8 -> -0.075855368 | K12: =G12/G$8 -> -0.08344635
B13: Коммерческие расходы | C13: Комм. расходы | D13: -184 | E13: -261 | F13: -296 | G13: -408 | H13: =D13/D$8 -> -0.010306968 | I13: =E13/E$8 -> -0.01546575 | J13: =F13/F$8 -> -0.020542716 | K13: =G13/G$8 -> -0.032548863
B14: Убыток от обесценения нефинансовых активов, нетто | C14: Убыток от обесценения НФА | D14: -48 | E14: -90 | F14: -179 | G14: -441 | H14: =D14/D$8 -> -0.0026887744 | I14: =E14/E$8 -> -0.0053330173 | J14: =F14/F$8 -> -0.012422791 | K14: =G14/G$8 -> -0.035181492
B15: Прочие операционные расходы, нетто | C15: Прочие оп. расходы | D15: -1285 | E15: -678 | F15: -269 | G15: -178 | H15: =D15/D$8 -> -0.07198073 | I15: =E15/E$8 -> -0.040175397 | J15: =F15/F$8 -> -0.018668888 | K15: =G15/G$8 -> -0.014200239
B16: Прибыль от операционной деятельности | D16: 9536 | E16: 7581 | F16: 5540 | G16: 3574 | H16: =D16/D$8 -> 0.53416984 | I16: =E16/E$8 -> 0.44921782 | J16: =F16/F$8 -> 0.38448192 | K16: =G16/G$8 -> 0.28512166
B17: (Отрицательные)/положительные курсовые разницы, нетто | C17: Курсовые разницы | D17: -53 | E17: 251 | F17: -1512 | G17: -343 | H17: =D17/D$8 -> -0.002968855 | I17: =E17/E$8 -> 0.014873193 | J17: =F17/F$8 -> -0.10493442 | K17: =G17/G$8 -> -0.027363383
B18: Финансовые расходы, нетто | C18: Фин. расходы | D18: -279 | E18: -493 | F18: -567 | G18: -896 | H18: =D18/D$8 -> -0.015628501 | I18: =E18/E$8 -> -0.029213084 | J18: =F18/F$8 -> -0.039350406 | K18: =G18/G$8 -> -0.071479856
B19: Прибыль/(убыток) от выбытия дочерних организаций и зарубежных совместных операций | C19: Выбытие доч. орг. и заруб. операций | D19: 29 | E19: -110 | F19: 32 | G19: 0 | H19: =D19/D$8 -> 0.0016244678 | I19: =E19/E$8 -> -0.0065181323 | J19: =F19/F$8 -> 0.0022208342 | K19: =G19/G$8 -> 0
B20: Прибыль от инвестиционной деятельности, нетто | C20: Инвест. Деятельность | D20: 52 | E20: 150 | F20: 41 | G20: 69 | H20: =D20/D$8 -> 0.0029128389 | I20: =E20/E$8 -> 0.0088883622 | J20: =F20/F$8 -> 0.0028454438 | K20: =G20/G$8 -> 0.0055045872
B21: Прибыль до налогообложения | D21: 9285 | E21: 7379 | F21: 3534 | G21: 2404 | H21: =D21/D$8 -> 0.52010979 | I21: =E21/E$8 -> 0.43724816 | J21: =F21/F$8 -> 0.24526338 | K21: =G21/G$8 -> 0.19178301
B22: Расходы по налогу на прибыль | C22: Расх. по налогу на прибыль | D22: -2311 | E22: -1525 | F22: -664 | G22: -589 | H22: =D22/D$8 -> -0.12945328 | I22: =E22/E$8 -> -0.090365015 | J22: =F22/F$8 -> -0.04608231 | K22: =G22/G$8 -> -0.046988432
B23: Прибыль за год | D23: 6974 | E23: 5854 | F23: 2870 | G23: 1815 | H23: =D23/D$8 -> 0.39065651 | I23: =E23/E$8 -> 0.34688315 | J23: =F23/F$8 -> 0.19918107 | K23: =G23/G$8 -> 0.14479458
B25: ОТЧЁТ О ФИНАНСОВОМ ПОЛОЖЕНИИ | D25: в миллионах долларов США | H25: Удельный вес в итоговой величине | L25: Удельный вес в промежуточном значении
D26: 2021 | E26: 2022 | F26: 2023 | G26: 2024 | H26: 2021 | I26: 2022 | J26: 2023 | K26: 2024 | L26: 2021 | M26: 2022 | N26: 2023 | O26: 2024
B28: АКТИВЫ
B29: Внеоборотные активы
B30: Основные средства | C30: Основные средства | D30: 12699 | E30: 16264 | F30: 15181 | G30: 15261 | H30: =D30/D$47 -> 0.5418818 | I30: =E30/E$47 -> 0.63050979 | J30: =F30/F$47 -> 0.64380831 | K30: =G30/G$47 -> 0.65865343 | L30: =D30/D$36 -> 0.93615923 | M30: =E30/E$36 -> 0.93514259 | N30: =F30/F$36 -> 0.93490578 | O30: =G30/G$36 -> 0.93482389
B31: Нематериальные активы | C31: Нематериальные активы | D31: 265 | E31: 302 | F31: 238 | G31: 206 | H31: =D31/D$47 -> 0.011307873 | I31: =E31/E$47 -> 0.011707695 | J31: =F31/F$47 -> 0.010093299 | K31: =G31/G$47 -> 0.0088908071 | L31: =D31/D$36 -> 0.019535569 | M31: =E31/E$36 -> 0.017364305 | N31: =F31/F$36 -> 0.014656977 | O31: =G31/G$36 -> 0.012618683
B32: Инвестиции в ассоциированные организации и совместные предприятия | C32: Инвестиции в асс. орг. и совм. предпр. | E32: 8 | F32: 76 | G32: 181 | H32: =D32/D$47 -> 0 | I32: =E32/E$47 -> 0.00031013762 | J32: =F32/F$47 -> 0.0032230704 | K32: =G32/G$47 -> 0.0078118256 | L32: =D32/D$36 -> 0 | M32: =E32/E$36 -> 0.0004599816 | N32: =F32/F$36 -> 0.0046803794 | O32: =G32/G$36 -> 0.011087289
B33: Прочие финансовые активы | C33: Прочие финансовые активы | D33: 89 | E33: 113 | F33: 58 | G33: 57 | H33: =D33/D$47 -> 0.0037977384 | I33: =E33/E$47 -> 0.0043806939 | J33: =F33/F$47 -> 0.0024597116 | K33: =G33/G$47 -> 0.0024600777 | L33: =D33/D$36 -> 0.0065610026 | M33: =E33/E$36 -> 0.0064972401 | N33: =F33/F$36 -> 0.0035718685 | O33: =G33/G$36 -> 0.0034915773
B34: Отложенные налоговые активы | C34: Отложенные налоговые активы | D34: 167 | E34: 340 | F34: 335 | G34: 328 | H34: =D34/D$47 -> 0.0071260934 | I34: =E34/E$47 -> 0.013180849 | J34: =F34/F$47 -> 0.014206955 | K34: =G34/G$47 -> 0.014156237 | L34: =D34/D$36 -> 0.012311095 | M34: =E34/E$36 -> 0.019549218 | N34: =F34/F$36 -> 0.02063062 | O34: =G34/G$36 -> 0.020091884
B35: Прочие внеоборотные активы | C35: Прочие внеоборотные активы | D35: 345 | E35: 365 | F35: 350 | G35: 292 | H35: =D35/D$47 -> 0.01472157 | I35: =E35/E$47 -> 0.014150029 | J35: =F35/F$47 -> 0.014843087 | K35: =G35/G$47 -> 0.012602503 | L35: =D35/D$36 -> 0.0254331 | M35: =E35/E$36 -> 0.020986661 | N35: =F35/F$36 -> 0.021554379 | O35: =G35/G$36 -> 0.017886677
B36: ИТОГО ВНЕОБОРОТНЫЕ АКТИВЫ | D36: 13565 | E36: 17392 | F36: 16238 | G36: 16325 | H36: =D36/D$47 -> 0.57883508 | I36: =E36/E$47 -> 0.67423919 | J36: =F36/F$47 -> 0.68863444 | K36: =G36/G$47 -> 0.70457488 | L36: =D36/D$36 -> 1 | M36: =E36/E$36 -> 1 | N36: =F36/F$36 -> 1 | O36: =G36/G$36 -> 1
B37: Оборотные активы
B38: Запасы | C38: Запасы | D38: 3026 | E38: 4945 | F38: 3817 | G38: 3114 | H38: =D38/D$47 -> 0.12912311 | I38: =E38/E$47 -> 0.19170382 | J38: =F38/F$47 -> 0.16187447 | K38: =G38/G$47 -> 0.13439793 | L38: =D38/D$46 -> 0.30658561 | M38: =E38/E$46 -> 0.5884803 | N38: =F38/F$46 -> 0.51988559 | O38: =G38/G$46 -> 0.45493061
B39: Торговая и прочая дебиторская задолженность | C39: Торг. и пр. ДЗ | D39: 468 | E39: 846 | F39: 764 | G39: 1374 | H39: =D39/D$47 -> 0.01997013 | I39: =E39/E$47 -> 0.032797054 | J39: =F39/F$47 -> 0.032400339 | K39: =G39/G$47 -> 0.05930082 | L39: =D39/D$46 -> 0.047416413 | M39: =E39/E$46 -> 0.10067833 | N39: =F39/F$46 -> 0.10405884 | O39: =G39/G$46 -> 0.20073046 | P39: Дебиторка стабильно растет - немного странно
B40: Авансы выданные и расходы будущих периодов | C40: Ав. выданные и расх. буд. пер. | D40: 111 | E40: 192 | F40: 173 | G40: 135 | H40: =D40/D$47 -> 0.0047365052 | I40: =E40/E$47 -> 0.007443303 | J40: =F40/F$47 -> 0.007336726 | K40: =G40/G$47 -> 0.0058264998 | L40: =D40/D$46 -> 0.011246201 | M40: =E40/E$46 -> 0.022848983 | N40: =F40/F$46 -> 0.023563062 | O40: =G40/G$46 -> 0.019722425
B41: Прочие финансовые активы | C41: Прочие фин. активы | D41: 43 | E41: 40 | F41: 3 | G41: 69 | H41: =D41/D$47 -> 0.0018348624 | I41: =E41/E$47 -> 0.0015506881 | J41: =F41/F$47 -> 0.00012722646 | K41: =G41/G$47 -> 0.0029779888 | L41: =D41/D$46 -> 0.0043566363 | M41: =E41/E$46 -> 0.0047602047 | N41: =F41/F$46 -> 0.00040860801 | O41: =G41/G$46 -> 0.010080351
B42: Авансовые платежи по налогу на прибыль | C42: Ав. плат. по налогу на прибыль | D42: 203 | E42: 17 | F42: 101 | G42: 38 | H42: =D42/D$47 -> 0.0086622573 | I42: =E42/E$47 -> 0.00065904245 | J42: =F42/F$47 -> 0.0042832909 | K42: =G42/G$47 -> 0.0016400518 | L42: =D42/D$46 -> 0.020567376 | M42: =E42/E$46 -> 0.002023087 | N42: =F42/F$46 -> 0.01375647 | O42: =G42/G$46 -> 0.0055514974
B43: Прочие налоги к возмещению | C43: Пр. налоги к возмещению | D43: 412 | E43: 477 | F43: 344 | G43: 292 | H43: =D43/D$47 -> 0.017580542 | I43: =E43/E$47 -> 0.018491956 | J43: =F43/F$47 -> 0.014588634 | K43: =G43/G$47 -> 0.012602503 | L43: =D43/D$46 -> 0.041742655 | M43: =E43/E$46 -> 0.056765441 | N43: =F43/F$46 -> 0.046853718 | O43: =G43/G$46 -> 0.042658875
B44: Денежные средства и их эквиваленты | C44: ДС и их экв. | D44: 5547 | E44: 1882 | F44: 2139 | G44: 1822 | H44: =D44/D$47 -> 0.23669725 | I44: =E44/E$47 -> 0.072959876 | J44: =F44/F$47 -> 0.090712468 | K44: =G44/G$47 -> 0.078636167 | L44: =D44/D$46 -> 0.56200608 | M44: =E44/E$46 -> 0.22396763 | N44: =F44/F$46 -> 0.29133751 | O44: =G44/G$46 -> 0.26617969 | P44: В 2021 году запасов было мало, а денег много, а в 22 наоборот
B45: Прочие оборотные активы | C45: Пр. оборотные активы | D45: 60 | E45: 4 | F45: 1 | G45: 1 | H45: =D45/D$47 -> 0.0025602731 | I45: =E45/E$47 -> 0.00015506881 | J45: =F45/F$47 -> 4.2408821e-05 | K45: =G45/G$47 -> 4.3159258e-05 | L45: =D45/D$46 -> 0.0060790274 | M45: =E45/E$46 -> 0.00047602047 | N45: =F45/F$46 -> 0.00013620267 | O45: =G45/G$46 -> 0.00014609204
B46: ИТОГО ОБОРОТНЫЕ АКТИВЫ | D46: 9870 | E46: 8403 | F46: 7342 | G46: 6845 | H46: =D46/D$47 -> 0.42116492 | I46: =E46/E$47 -> 0.32576081 | J46: =F46/F$47 -> 0.31136556 | K46: =G46/G$47 -> 0.29542512 | L46: =D46/D$46 -> 1 | M46: =E46/E$46 -> 1 | N46: =F46/F$46 -> 1 | O46: =G46/G$46 -> 1
B47: ИТОГО АКТИВЫ | D47: 23435 | E47: 25795 | F47: 23580 | G47: 23170 | H47: =D47/D$47 -> 1 | I47: =E47/E$47 -> 1 | J47: =F47/F$47 -> 1 | K47: =G47/G$47 -> 1
B49: КАПИТАЛ И ОБЯЗАТЕЛЬСТВА
B50: Капитал и резервы
B51: Уставный капитал | D51: 6 | E51: 6 | F51: 6 | G51: 6 | H51: =D51/D$81 -> 0.00025602731 | I51: =E51/E$81 -> 0.00023260322 | J51: =F51/F$81 -> 0.00025445293 | K51: =G51/G$81 -> 0.00025895555 | L51: =D51/D$56 -> 0.0012531328 | M51: =E51/E$56 -> 0.00070036185 | N51: =F51/F$56 -> 0.00078999342 | O51: =G51/G$56 -> 0.00074101519
B52: Эмиссионный доход | D52: 1218 | E52: 1212 | F52: 1212 | G52: 1212 | H52: =D52/D$81 -> 0.051973544 | I52: =E52/E$81 -> 0.04698585 | J52: =F52/F$81 -> 0.051399491 | K52: =G52/G$81 -> 0.05230902 | L52: =D52/D$56 -> 0.25438596 | M52: =E52/E$56 -> 0.14147309 | N52: =F52/F$56 -> 0.15957867 | O52: =G52/G$56 -> 0.14968507
B53: Собственные акции, выкупленные у акционеров | D53: -305 | H53: =D53/D$81 -> -0.013014722 | I53: =E53/E$81 -> 0 | J53: =F53/F$81 -> 0 | K53: =G53/G$81 -> 0 | L53: =D53/D$56 -> -0.063700919 | M53: =E53/E$56 -> 0 | N53: =F53/F$56 -> 0 | O53: =G53/G$56 -> 0
B54: Резерв накопленных курсовых разниц и прочие резервы | D54: -5415 | E54: -4541 | F54: -6146 | G54: -6979 | H54: =D54/D$81 -> -0.23106465 | I54: =E54/E$81 -> -0.17604187 | J54: =F54/F$81 -> -0.26064461 | K54: =G54/G$81 -> -0.30120846 | L54: =D54/D$56 -> -1.1309524 | M54: =E54/E$56 -> -0.5300572 | N54: =F54/F$56 -> -0.80921659 | O54: =G54/G$56 -> -0.86192417
B55: Нераспределенная прибыль | D55: 8184 | E55: 10448 | F55: 11324 | G55: 12638 | H55: =D55/D$81 -> 0.34922125 | I55: =E55/E$81 -> 0.40503974 | J55: =F55/F$81 -> 0.48023749 | K55: =G55/G$81 -> 0.5454467 | L55: =D55/D$56 -> 1.7092732 | M55: =E55/E$56 -> 1.2195634 | N55: =F55/F$56 -> 1.4909809 | O55: =G55/G$56 -> 1.560825
B56: ИТОГО КАПИТАЛ | D56: 4788 | E56: 8567 | F56: 7595 | G56: 8097 | H56: =D56/D$81 -> 0.20430979 | I56: =E56/E$81 -> 0.33211863 | J56: =F56/F$81 -> 0.322095 | K56: =G56/G$81 -> 0.34946051 | L56: =D56/D$56 -> 1 | M56: =E56/E$56 -> 1 | N56: =F56/F$56 -> 1 | O56: =G56/G$56 -> 1
B57: Долгосрочные обязательства
B58: Кредиты и займы | C58: Кредиты и займы | D58: 8616 | E58: 7189 | F58: 5377 | G58: 7112 | H58: =D58/D$81 -> 0.36765522 | I58: =E58/E$81 -> 0.27869742 | J58: =F58/F$81 -> 0.22803223 | K58: =G58/G$81 -> 0.30694864 | L58: =D58/D$66 -> 0.81560015 | M58: =E58/E$66 -> 0.75364294 | N58: =F58/F$66 -> 0.75160749 | O58: =G58/G$66 -> 0.77692812
B59: Обязательства по аренде | C59: Обязательства по аренде | D59: 178 | E59: 190 | F59: 466 | G59: 381 | H59: =D59/D$81 -> 0.0075954769 | I59: =E59/E$81 -> 0.0073657686 | J59: =F59/F$81 -> 0.019762511 | K59: =G59/G$81 -> 0.016443677 | L59: =D59/D$66 -> 0.016849678 | M59: =E59/E$66 -> 0.01991823 | N59: =F59/F$66 -> 0.065138384 | O59: =G59/G$66 -> 0.041621149
B60: Оценочные обязательства | C60: Оценочные обязательства | D60: 894 | E60: 916 | F60: 689 | G60: 881 | H60: =D60/D$81 -> 0.038148069 | I60: =E60/E$81 -> 0.035510758 | J60: =F60/F$81 -> 0.029219678 | K60: =G60/G$81 -> 0.038023306 | L60: =D60/D$66 -> 0.084627035 | M60: =E60/E$66 -> 0.096026837 | N60: =F60/F$66 -> 0.096309757 | O60: =G60/G$66 -> 0.09624208
B61: Социальные обязательства | C61: Социальные обязательства | D61: 633 | E61: 613 | F61: 399 | G61: 299 | H61: =D61/D$81 -> 0.027010881 | I61: =E61/E$81 -> 0.023764295 | J61: =F61/F$81 -> 0.01692112 | K61: =G61/G$81 -> 0.012904618 | L61: =D61/D$66 -> 0.059920485 | M61: =E61/E$66 -> 0.064262501 | N61: =F61/F$66 -> 0.055772994 | O61: =G61/G$66 -> 0.032663317
B62: Торговая и прочая долгосрочная кредиторская задолженность | C62: Торг. и пр. долгосрочная КЗ | D62: 55 | E62: 56 | F62: 51 | G62: 41 | H62: =D62/D$81 -> 0.002346917 | I62: =E62/E$81 -> 0.0021709634 | J62: =F62/F$81 -> 0.0021628499 | K62: =G62/G$81 -> 0.0017695296 | L62: =D62/D$66 -> 0.0052063612 | M62: =E62/E$66 -> 0.0058706363 | N62: =F62/F$66 -> 0.0071288789 | O62: =G62/G$66 -> 0.0044789163
B63: Производные финансовые инструменты | C63: Производные фин. инстр. | D63: 72 | E63: 67 | F63: 0 | G63: 0 | H63: =D63/D$81 -> 0.0030723277 | I63: =E63/E$81 -> 0.0025974026 | J63: =F63/F$81 -> 0 | K63: =G63/G$81 -> 0 | L63: =D63/D$66 -> 0.0068156002 | M63: =E63/E$66 -> 0.007023797 | N63: =F63/F$66 -> 0 | O63: =G63/G$66 -> 0
B64: Отложенные налоговые обязательства | C64: Отлож. налоговые об-ва | D64: 73 | E64: 415 | F64: 142 | G64: 381 | H64: =D64/D$81 -> 0.0031149989 | I64: =E64/E$81 -> 0.016088389 | J64: =F64/F$81 -> 0.0060220526 | K64: =G64/G$81 -> 0.016443677 | L64: =D64/D$66 -> 0.0069102613 | M64: =E64/E$66 -> 0.043505609 | N64: =F64/F$66 -> 0.019849036 | O64: =G64/G$66 -> 0.041621149
B65: Прочие долгосрочные обязательства | C65: Пр. долгосрочные об-ва | D65: 43 | E65: 93 | F65: 30 | G65: 59 | H65: =D65/D$81 -> 0.0018348624 | I65: =E65/E$81 -> 0.0036053499 | J65: =F65/F$81 -> 0.0012722646 | K65: =G65/G$81 -> 0.0025463962 | L65: =D65/D$66 -> 0.0040704279 | M65: =E65/E$66 -> 0.0097494496 | N65: =F65/F$66 -> 0.0041934582 | O65: =G65/G$66 -> 0.0064452698
B66: ИТОГО ДОЛГОСРОЧНЫЕ ОБЯЗАТЕЛЬСТВА | D66: 10564 | E66: 9539 | F66: 7154 | G66: 9154 | H66: =D66/D$81 -> 0.45077875 | I66: =E66/E$81 -> 0.36980035 | J66: =F66/F$81 -> 0.30339271 | K66: =G66/G$81 -> 0.39507984 | L66: =D66/D$66 -> 1 | M66: =E66/E$66 -> 1 | N66: =F66/F$66 -> 1 | O66: =G66/G$66 -> 1
B67: Краткосрочные обязательства
B68: Кредиты и займы | C68: Кредиты и займы | D68: 1610 | E68: 4295 | F68: 4335 | G68: 2834 | H68: =D68/D$81 -> 0.068700661 | I68: =E68/E$81 -> 0.16650514 | J68: =F68/F$81 -> 0.18384224 | K68: =G68/G$81 -> 0.12231334 | L68: =D68/D$79 -> 0.19918347 | M68: =E68/E$79 -> 0.55859019 | N68: =F68/F$79 -> 0.49088438 | O68: =G68/G$79 -> 0.47879709 | P68: Очень большой рост - явно сильно не хватает ликвидности
B69: Обязательства по аренде | C69: Обязательства по аренде | D69: 57 | E69: 43 | F69: 54 | G69: 81 | H69: =D69/D$81 -> 0.0024322594 | I69: =E69/E$81 -> 0.0016669897 | J69: =F69/F$81 -> 0.0022900763 | K69: =G69/G$81 -> 0.0034958999 | L69: =D69/D$79 -> 0.0070518372 | M69: =E69/E$79 -> 0.0055924047 | N69: =F69/F$79 -> 0.0061148228 | O69: =G69/G$79 -> 0.013684744
B70: Торговая и прочая кредиторская задолженность | C70: Торг. и пр. КЗ | D70: 2224 | E70: 1381 | F70: 1273 | G70: 1209 | H70: =D70/D$81 -> 0.094900789 | I70: =E70/E$81 -> 0.053537507 | J70: =F70/F$81 -> 0.053986429 | K70: =G70/G$81 -> 0.052179543 | L70: =D70/D$79 -> 0.27514537 | M70: =E70/E$79 -> 0.17960723 | N70: =F70/F$79 -> 0.14415129 | O70: =G70/G$79 -> 0.20425748 | P70: В 2024 как-то мир оживать начал
B71: Дивиденды к уплате | C71: Дивиденды к уплате | D71: 3146 | E71: 496 | F71: 1924 | G71: 721 | H71: =D71/D$81 -> 0.13424365 | I71: =E71/E$81 -> 0.019228533 | J71: =F71/F$81 -> 0.081594572 | K71: =G71/G$81 -> 0.031117825 | L71: =D71/D$79 -> 0.38921193 | M71: =E71/E$79 -> 0.064507738 | N71: =F71/F$79 -> 0.21786887 | O71: =G71/G$79 -> 0.12181112
B72: Обязательства по вознаграждениям работникам | C72: Об-ва по вознагр. работникам | D72: 417 | E72: 585 | F72: 555 | G72: 444 | H72: =D72/D$81 -> 0.017793898 | I72: =E72/E$81 -> 0.022678814 | J72: =F72/F$81 -> 0.023536896 | K72: =G72/G$81 -> 0.01916271 | L72: =D72/D$79 -> 0.051589756 | M72: =E72/E$79 -> 0.076082716 | N72: =F72/F$79 -> 0.06284679 | O72: =G72/G$79 -> 0.075012671
B73: Оценочные обязательства | C73: Оценочные обязательства | E73: 180 | F73: 90 | G73: 173 | H73: =D73/D$81 -> 0 | I73: =E73/E$81 -> 0.0069780965 | J73: =F73/F$81 -> 0.0038167939 | K73: =G73/G$81 -> 0.0074665516 | L73: =D73/D$79 -> 0 | M73: =E73/E$79 -> 0.023410066 | N73: =F73/F$79 -> 0.010191371 | O73: =G73/G$79 -> 0.02922791
B74: Социальные обязательства | C74: Социальные обязательства | D74: 158 | E74: 201 | F74: 207 | G74: 164 | H74: =D74/D$81 -> 0.0067420525 | I74: =E74/E$81 -> 0.0077922078 | J74: =F74/F$81 -> 0.008778626 | K74: =G74/G$81 -> 0.0070781183 | L74: =D74/D$79 -> 0.019547198 | M74: =E74/E$79 -> 0.026141241 | N74: =F74/F$79 -> 0.023440154 | O74: =G74/G$79 -> 0.027707383
B75: Производные финансовые инструменты | C75: Производные фин. инстр. | D75: 15 | E75: 0 | F75: 114 | G75: 0 | H75: =D75/D$81 -> 0.00064006827 | I75: =E75/E$81 -> 0 | J75: =F75/F$81 -> 0.0048346056 | K75: =G75/G$81 -> 0 | L75: =D75/D$79 -> 0.0018557466 | M75: =E75/E$79 -> 0 | N75: =F75/F$79 -> 0.01290907 | O75: =G75/G$79 -> 0
B76: Обязательства по налогу на прибыль | C76: Об-ва по налогу на прибыль | D76: 41 | E76: 169 | F76: 7 | G76: 49 | H76: =D76/D$81 -> 0.0017495199 | I76: =E76/E$81 -> 0.0065516573 | J76: =F76/F$81 -> 0.00029686175 | K76: =G76/G$81 -> 0.0021148036 | L76: =D76/D$79 -> 0.0050723741 | M76: =E76/E$79 -> 0.021979451 | N76: =F76/F$79 -> 0.00079266221 | O76: =G76/G$79 -> 0.0082784254
B77: Прочие налоговые обязательства | C77: Пр. налоговые об-ва | D77: 269 | E77: 339 | F77: 272 | G77: 244 | H77: =D77/D$81 -> 0.011478558 | I77: =E77/E$81 -> 0.013142082 | J77: =F77/F$81 -> 0.011535199 | K77: =G77/G$81 -> 0.010530859 | L77: =D77/D$79 -> 0.033279723 | M77: =E77/E$79 -> 0.044088958 | N77: =F77/F$79 -> 0.030800589 | O77: =G77/G$79 -> 0.04122318
B78: Резервы | C78: Резервы | D78: 26 | H78: =D78/D$81 -> 0.0011094517 | I78: =E78/E$81 -> 0 | J78: =F78/F$81 -> 0 | K78: =G78/G$81 -> 0 | L78: =D78/D$79 -> 0.0032166275 | M78: =E78/E$79 -> 0 | N78: =F78/F$79 -> 0 | O78: =G78/G$79 -> 0
B79: ИТОГО КРАТКОСРОЧНЫЕ ОБЯЗАТЕЛЬСТВА | D79: 8083 | E79: 7689 | F79: 8831 | G79: 5919 | H79: =D79/D$81 -> 0.34491146 | I79: =E79/E$81 -> 0.29808102 | J79: =F79/F$81 -> 0.3745123 | K79: =G79/G$81 -> 0.25545965 | L79: =D79/D$79 -> 1 | M79: =E79/E$79 -> 1 | N79: =F79/F$79 -> 1 | O79: =G79/G$79 -> 1
B80: ИТОГО ОБЯЗАТЕЛЬСТВА | D80: 18647 | E80: 17228 | F80: 15985 | G80: 15073 | H80: =D80/D$81 -> 0.79569021 | I80: =E80/E$81 -> 0.66788137 | J80: =F80/F$81 -> 0.677905 | K80: =G80/G$81 -> 0.65053949
B81: ИТОГО КАПИТАЛ И ОБЯЗАТЕЛЬСТВА | D81: 23435 | E81: 25795 | F81: 23580 | G81: 23170 | H81: =D81/D$81 -> 1 | I81: =E81/E$81 -> 1 | J81: =F81/F$81 -> 1 | K81: =G81/G$81 -> 1

Sheet Норникель
B2: КОНСОЛИДИРОВАННЫЙ
B3: ОТЧЁТ О ПРИБЫЛЯХ И УБЫТКАХ | D3: #VALUE!
B4: в миллионах долларов США | C4: За год, закончившийся 31 декабря
C5: 2021 | D5: 2022 | E5: 2023 | F5: 2024
B6: Выручка
B7: Выручка от реализации металлов | C7: 17103 | D7: 16073 | E7: 13702 | F7: 11848
B8: Выручка от прочей реализации | C8: 749 | D8: 803 | E8: 707 | F8: 687
B9: Итого выручка | C9: 17852 | D9: 16876 | E9: 14409 | F9: 12535
B10: Себестоимость реализованных металлов | C10: -5057 | D10: -6103 | E10: -6344 | F10: -6232
B11: Себестоимость прочей реализации | C11: -753 | D11: -810 | E11: -688 | F11: -656
B12: Валовая прибыль | C12: 12042 | D12: 9963 | E12: 7377 | F12: 5647
B13: Административные расходы | C13: -989 | D13: -1353 | E13: -1093 | F13: -1046
B14: Коммерческие расходы | C14: -184 | D14: -261 | E14: -296 | F14: -408
B15: Убыток от обесценения нефинансовых активов, нетто | C15: -48 | D15: -90 | E15: -179 | F15: -441
B16: Прочие операционные расходы, нетто | C16: -1285 | D16: -678 | E16: -269 | F16: -178
B17: Прибыль от операционной деятельности | C17: 9536 | D17: 7581 | E17: 5540 | F17: 3574
B18: (Отрицательные)/положительные курсовые разницы, нетто | C18: -53 | D18: 251 | E18: -1512 | F18: -343
... B24: Прибыль за год | C24: 6974 | D24: 5854 | E24: 2870 | F24: 1815
B26: КОНСОЛИДИРОВАННЫЙ
B27: ОТЧЁТ О СОВОКУПНОМ ДОХОДЕ | D27: #VALUE!
B28: в миллионах долларов США | C28: За год, закончившийся 31 декабря
C29: 2021 | D29: 2022 | E29: 2023 | F29: 2024
B30: Прибыль за год | C30: 6974 | D30: 5854 | E30: 2870 | F30: 1815
B31: Прочий совокупный доход/(расход)
B32: Статьи, которые реклассифицированы или впоследствии могут быть реклассифицированы в состав прибыли или убытка:
B33: Реклассификация резерва курсовых разниц по выбывшим зарубежным операциям, в состав прибыли или убытка | C33: 20 | D33: 0 | E33: 0 | F33: 0
B34: Эффект пересчета зарубежных операций и прочие резервы | C34: -2 | D34: 29 | E34: -31 | F34: -4
B35: Статьи, которые впоследствии не будут реклассифицированы в состав прибыли или убытка:
B36: Эффект пересчета в валюту представления | C36: 80 | D36: 891 | E36: -1825 | F36: -1016
B37: Прочий совокупный (расход)/доход за период с учетом эффекта налогообложения | C37: 98 | D37: 920 | E37: (1 856) | F37: (1 020)
B38: Общий совокупный доход за период с учетом эффекта налогообложения | C38: 7072 | D38: 6774 | E38: 1014 | F38: 795
B40: КОНСОЛИДИРОВАННЫЙ
B41: ОТЧЁТ О ФИНАНСОВОМ ПОЛОЖЕНИИ | D41: #VALUE!
B42: в миллионах долларов США | C42: За год, закончившийся 31 декабря
C43: 2021 | D43: 2022 | E43: 2023 | F43: 2024
B44: АКТИВЫ
B45: Внеоборотные активы
B46: Основные средства | C46: 12699 | D46: 16264 | E46: 15181 | F46: 15261
B47: Нематериальные активы | C47: 265 | D47: 302 | E47: 238 | F47: 206
B48: Инвестиции в ассоциированные организации и совместные предприятия | D48: 8 | E48: 76 | F48: 181
B49: Прочие финансовые активы | C49: 89 | D49: 113 | E49: 58 | F49: 57
B50: Отложенные налоговые активы | C50: 167 | D50: 340 | E50: 335 | F50: 328
B51: Прочие внеоборотные активы | C51: 345 | D51: 365 | E51: 350 | F51: 292
B52: ИТОГО ВНЕОБОРОТНЫЕ АКТИВЫ | C52: 13565 | D52: 17392 | E52: 16238 | F52: 16325
B53: Оборотные активы
B54: Запасы | C54: 3026 | D54: 4945 | E54: 3817 | F54: 3114
B55: Торговая и прочая дебиторская задолженность | C55: 468 | D55: 846 | E55: 764 | F55: 1374
B56: Авансы выданные и расходы будущих периодов | C56: 111 | D56: 192 | E56: 173 | F56: 135
B57: Прочие финансовые активы | C57: 43 | D57: 40 | E57: 3 | F57: 69
B58: Авансовые платежи по налогу на прибыль | C58: 203 | D58: 17 | E58: 101 | F58: 38
B59: Прочие налоги к возмещению | C59: 412 | D59: 477 | E59: 344 | F59: 292
B60: Денежные средства и их эквиваленты | C60: 5547 | D60: 1882 | E60: 2139 | F60: 1822
B61: Прочие оборотные активы | C61: 60 | D61: 4 | E61: 1 | F61: 1
B62: ИТОГО ОБОРОТНЫЕ АКТИВЫ | C62: 9870 | D62: 8403 | E62: 7342 | F62: 6845
B64: ИТОГО АКТИВЫ | C64: 23435 | D64: 25795 | E64: 23580 | F64: 23170
B66: КАПИТАЛ И ОБЯЗАТЕЛЬСТВА
B67: Капитал и резервы
B68: Уставный капитал | C68: 6 | D68: 6 | E68: 6 | F68: 6
B69: Эмиссионный доход | C69: 1218 | D69: 1212 | E69: 1212 | F69: 1212
B70: Собственные акции, выкупленные у акционеров | C70: -305
B71: Резерв накопленных курсовых разниц и прочие резервы | C71: -5415 | D71: -4541 | E71: -6146 | F71: -6979
B72: Нераспределенная прибыль | C72: 8184 | D72: 10448 | E72: 11324 | F72: 12638
B73: ИТОГО КАПИТАЛ | C73: 4788 | D73: 8567 | E73: 7595 | F73: 8097
B75: Долгосрочные обязательства
B76: Кредиты и займы | C76: 8616 | D76: 7189 | E76: 5377 | F76: 7112
B77: Обязательства по аренде | C77: 178 | D77: 190 | E77: 466 | F77: 381
B78: Оценочные обязательства | C78: 894 | D78: 916 | E78: 689 | F78: 881
B79: Социальные обязательства | C79: 633 | D79: 613 | E79: 399 | F79: 299
B80: Торговая и прочая долгосрочная кредиторская задолженность | C80: 55 | D80: 56 | E80: 51 | F80: 41
B81: Производные финансовые инструменты | C81: 72 | D81: 67 | E81: 0 | F81: 0
B82: Отложенные налоговые обязательства | C82: 73 | D82: 415 | E82: 142 | F82: 381
B83: Прочие долгосрочные обязательства | C83: 43 | D83: 93 | E83: 30 | F83: 59
B84: ИТОГО ДОЛГОСРОЧНЫЕ ОБЯЗАТЕЛЬСТВА | C84: 10564 | D84: 9539 | E84: 7154 | F84: 9154
B86: Краткосрочные обязательства
B87: Кредиты и займы | C87: 1610 | D87: 4295 | E87: 4335 | F87: 2834
B88: Обязательства по аренде | C88: 57 | D88: 43 | E88: 54 | F88: 81
B89: Торговая и прочая кредиторская задолженность | C89: 2224 | D89: 1381 | E89: 1273 | F89: 1209
B90: Дивиденды к уплате | C90: 3146 | D90: 496 | E90: 1924 | F90: 721
B91: Обязательства по вознаграждениям работникам | C91: 417 | D91: 585 | E91: 555 | F91: 444
B92: Оценочные обязательства | D92: 180 | E92: 90 | F92: 173
B93: Социальные обязательства | C93: 158 | D93: 201 | E93: 207 | F93: 164
B94: Производные финансовые инструменты | C94: 15 | D94: 0 | E94: 114 | F94: 0
B95: Обязательства по налогу на прибыль | C95: 41 | D95: 169 | E95: 7 | F95: 49
B96: Прочие налоговые обязательства | C96: 269 | D96: 339 | E96: 272 | F96: 244
B97: Резервы | C97: 26
B98: ИТОГО КРАТКОСРОЧНЫЕ ОБЯЗАТЕЛЬСТВА | C98: 8083 | D98: 7689 | E98: 8831 | F98: 5919
B100: ИТОГО ОБЯЗАТЕЛЬСТВА | C100: 18647 | D100: 17228 | E100: 15985 | F100: 15073
B102: ИТОГО КАПИТАЛ И ОБЯЗАТЕЛЬСТВА | C102: 23435 | D102: 25795 | E102: 23580 | F102: 23170
B104: Амортизация | C104: 928 | D104: 1026 | E104: 1165 | F104: 1181

Sheet Vale
B2: КОНСОЛИДИРОВАННЫЙ
B3: ОТЧЁТ О ПРИБЫЛЯХ И УБЫТКАХ | D3: #VALUE!
B4: в миллионах долларов США | C4: За год, закончившийся 31 декабря
C5: 2021 | D5: 2022 | E5: 2023 | F5: 2024
B6: Выручка | C6: 54502 | D6: 43839 | E6: 41784 | F6: 38056
B7: Себестоимость проданных товаров и оказанных услуг | C7: -21729 | D7: -24028 | E7: -24089 | F7: -24265
B8: Валовая прибыль | C8: 32773 | D8: 19811 | E8: 17695 | F8: 13791
B9: Коммерческие и административные расходы | C9: -481 | D9: -515 | E9: -553 | F9: -622
B10: Исследования и разработки | C10: -549 | D10: -660 | E10: -723 | F10: -790
B11: Подготовка к эксплуатации и остановка производства | C11: -648 | D11: -479 | E11: -450 | F11: -403
B12: Убыток от обесценения нефинансовых активов нетто | C12: -426 | D12: 773 | E12: -266 | F12: 301
B13: Прочие операционные расходы нетто | C13: -2976 | D13: -1722 | E13: -1498 | F13: -1489
B14: Прибыль от операционной деятельности | C14: 27693 | D14: 17208 | E14: 14205 | F14: 10788
B15: Финансовые доходы | C15: 337 | D15: 520 | E15: 432 | F15: 422
B16: Финансовые расходы нетто | C16: -1249 | D16: -1179 | E16: -1459 | F16: -1473
B17: Результаты участия в акционерном капитале и прочие результаты деятельности ассоциированных компаний и совместных предприятий | C17: -1271 | D17: 2927 | E17: -919 | F17: -2772
... B21: Прибыль за год | C21: 24844 | D21: 16810 | E21: 8105 | F21: 6166
B23: КОНСОЛИДИРОВАННЫЙ
B24: ОТЧЁТ О СОВОКУПНОМ ДОХОДЕ | D24: #VALUE!
B25: в миллионах долларов США | C25: За год, закончившийся 31 декабря
C26: 2021 | D26: 2022 | E26: 2023 | F26: 2024
B27: Прибыль за год | C27: 22468 | D27: 18870 | E27: 8105 | F27: 5975
B28: Прочий совокупный доход/(расход)
B29: Статьи которые реклассифицированы или впоследствии могут быть реклассифицированы в состав прибыли или убытка:
B30: Эффект пересчета в валюту представления | C30: 918 | D30: -1306 | E30: -522 | F30: 2237
B31: Хеджирование чистых инвестиций | C31: -118 | D31: 81 | E31: 139 | F31: -500
B32: Хеджирование денежных потоков | C32: 3 | D32: 19 | E32: -19 | F32: -
B33: Реклассификация накопленной корректировки при пересчете в отчет о прибылях и убытках | C33: -4749 | D33: -483 | E33: - | F33: -1115
B34: Статьи которые впоследствии не будут реклассифицированы в состав прибыли или убытка:
B35: Корректировки при пересчете данных Материнской компании | C35: -2174 | D35: 2259 | E35: 2966 | F35: -9172
B36: Обязательства по пенсионным выплатам | C36: 475 | D36: 269 | E36: -68 | F36: 102
B37: Корректировки справедливой стоимости долей участия в капитале оцениваемых по справедливой стоимости через прочий совокупный доход | C37: 397 | D37: - | E37: 13 | F37: -
C38: -1302 | D38: 2528 | E38: 2911 | F38: -9070
B39: Прочий совокупный (расход)/доход за период с учетом эффекта налогообложения | C39: 17220 | D39: -2473 | E39: 10614 | F39: 15362
B40: Общий совокупный доход за период с учетом эффекта налогообложения | C40: 17199 | D40: -2189 | E40: 10489 | F40: 15282
B42: КОНСОЛИДИРОВАННЫЙ
B43: ОТЧЁТ О ФИНАНСОВОМ ПОЛОЖЕНИИ | D43: #VALUE!
B44: в миллионах долларов США | C44: За год, закончившийся 31 декабря
C45: 2021 | D45: 2022 | E45: 2023 | F45: 2024
B46: АКТИВЫ
B47: Оборотные активы
B48: Денежные средства и их эквиваленты | C48: 11721 | D48: 4736 | E48: 3609 | F48: 4953
B49: Краткосрочные инвестиции | C49: 184 | D49: 61 | E49: 51 | F49: 53
B50: Дебиторская задолженность | C50: 3914 | D50: 4319 | E50: 4197 | F50: 2358
B51: Прочие финансовые активы | C51: 111 | D51: 342 | E51: 271 | F51: 53
B52: Запасы | C52: 4377 | D52: 4482 | E52: 4684 | F52: 4605
B53: Подлежащие возмещению налоги | C53: 862 | D53: 1272 | E53: 900 | F53: 1100
B54: Судебные депозиты | C54: - | D54: - | E54: 611 | F54: -
B55: Другое | C55: 215 | D55: 314 | E55: 444 | F55: 359
C56: 21384 | D56: 15526 | E56: 14767 | F56: 13481
B57: Внеоборотные активы предназначенные для продажи | C57: 976 | D57: - | E57: 3933 | F57: -
C58: 22360 | D58: 15526 | E58: 18700 | F58: 13481
B59: Внеоборотные активы
B60: Судебные депозиты | C60: 1220 | D60: 1215 | E60: 798 | F60: 537
B61: Прочие финансовые активы | C61: 143 | D61: 280 | E61: 593 | F61: 82
B62: Подлежащие возмещению налоги | C62: 935 | D62: 111 | E62: 1374 | F62: 1297
B63: Отложенные налоги на прибыль | C63: 11441 | D63: 10770 | E63: 9565 | F63: 8244
B64: Другое | C64: 650 | D64: 1019 | E64: 1257 | F64: 1466
C65: 14389 | D65: 14394 | E65: 13587 | F65: 11626
B67: Инвестиции в ассоциированные и совместные предприятия | C67: 1751 | D67: 1798 | E67: 1872 | F67: 4547
B68: Нематериальные активы | C68: 9011 | D68: 10238 | E68: 11631 | F68: 10514
B69: Основные средства оборужование | C69: 41931 | D69: 44938 | E69: 48396 | F69: 39984
C70: 67082 | D70: 71368 | E70: 75486 | F70: 66671
B71: ИТОГО АКТИВЫ | C71: 89442 | D71: 86894 | E71: 94186 | F71: 80152
B73: Текущие обязательства
B74: Поставщики и подрядчики | C74: 3475 | D74: 4461 | E74: 5272 | F74: 4234
B75: Кредиты и займы | C75: 1030 | D75: 307 | E75: 824 | F75: 102
B76: Договоры аренды | C76: 174 | D76: 182 | E76: 197 | F76: 147
B77: Прочие финансовые обязательства | C77: 2312 | D77: 1672 | E77: 1676 | F77: 1543
B78: Налоги подлежащие уплате | C78: 2177 | D78: 470 | E78: 1314 | F78: 574
B79: Программы расчетов ("РЕФИС") | C79: 324 | D79: 371 | E79: 428 | F79: 353
B80: Обязательства связанные с Брумадиньо | C80: 1156 | D80: 944 | E80: 1057 | F80: 714
B81: Обязательства связанные с ассоциированными компаниями и совместными предприятиями | C81: 1785 | D81: 1911 | E81: 837 | F81: 1844
B82: Определение характеристик плотин и обязательств по выбытию активов | C82: 621 | D82: 661 | E82: 1035 | F82: 833
B83: Положения для судебного разбирательства | C83: 93 | D83: 106 | E83: 114 | F83: 119
B84: Выплаты сотрудникам | C84: 952 | D84: 930 | E84: 964 | F84: 1012
B85: Выплачиваемые дивиденды | C85: - | D85: 1383 | E85: - | F85: 330
B86: Другое | C86: 744 | D86: 493 | E86: 376 | F86: 367
C87: 14843 | D87: 13891 | E87: 14094 | F87: 13090
B88: Обязательства связанные с внеоборотными активами предназначенными для продажи | C88: 355 | E88: 561 | F88: -
B89: ИТОГО КРАТКОСРОЧНЫЕ ОБЯЗАТЕЛЬСТВА | C89: 15198 | D89: 13891 | E89: 14655 | F89: 1309
B90: Долгосрочные обязательства
B91: Кредиты и займы | C91: 11150 | D91: 10874 | E91: 11647 | F91: 13772
B92: Договоры аренды | C92: 1428 | D92: 1349 | E92: 1255 | F92: 566
B93: Долговые обязательства акционеров с участием | C93: 3419 | D93: 2725 | E93: 2874 | F93: 2217
B94: Прочие финансовые обязательства | C94: 2571 | D94: 2843 | E94: 3373 | F94: 2347
B95: Программы расчетов ("РЕФИС") | C95: 1964 | D95: 1869 | E95: 1723 | F95: 1007
B96: Отложенные налоги на прибыль | C96: 1881 | D96: 1413 | E96: 870 | F96: 445
B97: Обязательства связанные с Брумадиньо | C97: 2381 | D97: 2368 | E97: 2003 | F97: 1256
B98: Обязательства связанные с ассоциированными компаниями и совместными предприятиями | C98: 1327 | D98: 1410 | E98: 3590 | F98: 1819
B99: Определение характеристик плотин и обязательств по выбытию активов | C99: 7482 | D99: 652 | E99: 6694 | F99: 493
B100: Положения для судебного разбирательства | C100: 1012 | D100: 1186 | E100: 885 | F100: 894
B101: Выплаты сотрудникам | C101: 1533 | D101: 1260 | E101: 1381 | F101: 1118
B102: Потоковые транзакции | C102: 1779 | D102: 1612 | E102: 1962 | F102: 1882
B103: Другое | C103: 137 | D103: 216 | E103: 293 | F103: 281
C104: 38938 | D104: 35645 | E104: 3855 | F104: 32534
B105: ИТОГО ОБЯЗАТЕЛЬСТВА | C105: 54136 | D105: 49536 | E105: 53205 | F105: 45624
B107: Собственный капитал
B109: Собственный капитал приходящийся на долю акционеров Vale S.A. | C109: 34472 | D109: 35867 | E109: 39461 | F109: 33406
B110: Капитал относящийся к неконтролирующим долям участия | C110: 834 | D110: 1491 | E110: 1520 | F110: 1122
...

Sheet Anglo American Platinum
B2: КОНСОЛИДИРОВАННЫЙ | H2: КОНСОЛИДИРОВАННЫЙ
B3: ОТЧЁТ О ПРИБЫЛЯХ И УБЫТКАХ | D3: #VALUE! | H3: ОТЧЁТ О ПРИБЫЛЯХ И УБЫТКАХ | J3: #VALUE!
B4: в миллионах южноафриканских рэнд | C4: За год, закончившийся 31 декабря | H4: в миллионах долларов США (пересчёт по среднегодовому курсу) | I4: За год, закончившийся 31 декабря
C5: 2021 | D5: 2022 | E5: 2023 | F5: 2024 | I5: 2021 | J5: 2022 | K5: 2023 | L5: 2024 | N5: Курс USD
B6: Валовой доход | C6: 214580 | D6: 164104 | E6: 124604 | F6: 109007 | H6: Валовой доход | I6: =C6/$O$16 -> 13933.766 | J6: =D6/$O$15 -> 10782.129 | K6: =E6/$O$14 -> 7012.0428 | L6: =F6/$O$13 -> 5826.1358 | N6: Year-end rate (R/USD):
B7: Выплаченные комиссионные | C7: -12 | D7: -14 | E7: -21 | F7: -20 | H7: Выплаченные комиссионные | I7: =C7/$O$16 -> -0.77922078 | J7: =D7/$O$15 -> -0.91984231 | K7: =E7/$O$14 -> -1.181767 | L7: =F7/$O$13 -> -1.0689471 | N7: 2024 | O7: 18.19
B8: Итого выручка | C8: 214568 | D8: 164090 | E8: 124583 | F8: 108987 | H8: Итого выручка | I8: =C8/$O$16 -> 13932.987 | J8: =D8/$O$15 -> 10781.209 | K8: =E8/$O$14 -> 7010.861 | L8: =F8/$O$13 -> 5825.0668 | N8: 2023 | O8: 18.85
B9: Себестоимость продаж | C9: -109456 | D9: -93578 | E9: -103570 | F9: -90769 | H9: Себестоимость продаж | I9: =C9/$O$16 -> -7107.5325 | J9: =D9/$O$15 -> -6148.3574 | K9: =E9/$O$14 -> -5828.3624 | L9: =F9/$O$13 -> -4851.3629 | N9: 2022 | O9: 16.27
B10: Валовая прибыль | C10: 105112 | D10: 70512 | E10: 21013 | F10: 18218 | H10: Валовая прибыль | I10: =C10/$O$16 -> 6825.4545 | J10: =D10/$O$15 -> 4632.8515 | K10: =E10/$O$14 -> 1182.4986 | L10: =F10/$O$13 -> 973.7039 | N10: 2021 | O10: 14.32
B11: Финансовый доход | C11: 713 | D11: 972 | E11: 1198 | F11: 984 | H11: Финансовый доход | I11: =C11/$O$16 -> 46.298701 | J11: =D11/$O$15 -> 63.863338 | K11: =E11/$O$14 -> 67.416995 | L11: =F11/$O$13 -> 52.592197
B12: Полученные дивиденды | C12: 14 | D12: — | E12: — | F12: — | H12: Полученные дивиденды | I12: =C12/$O$16 -> 0.90909091 | J12: — | K12: — | L12: — | N12: Average rate:
B13: Прочие доходы | C13: 2447 | D13: 896 | E13: 121 | F13: 42 | H13: Прочие доходы | I13: =C13/$O$16 -> 158.8961 | J13: =D13/$O$15 -> 58.869908 | K13: =E13/$O$14 -> 6.809229 | L13: =F13/$O$13 -> 2.2447889 | N13: 2024 | O13: 18.71
B14: Резерв на покрытие ожидаемых кредитных убытков | C14: -125 | D14: 195 | E14: -17 | F14: -30 | H14: Резерв на покрытие ожидаемых кредитных убытков | I14: =C14/$O$16 -> -8.1168831 | J14: =D14/$O$15 -> 12.812089 | K14: =E14/$O$14 -> -0.95666854 | L14: =F14/$O$13 -> -1.6034206 | N14: 2023 | O14: 17.77
B15: Оценка справедливой стоимости финансовых активов и обязательств и инвестиций в экологические трасты | C15: 4494 | D15: -2384 | E15: 607 | F15: -276 | H15: Оценка справедливой стоимости финансовых активов и обязательств и инвестиций в экологические трасты | I15: =C15/$O$16 -> 291.81818 | J15: =D15/$O$15 -> -156.63601 | K15: =E15/$O$14 -> 34.158694 | L15: =F15/$O$13 -> -14.75147 | N15: 2022 | O15: 15.22
B16: Финансовые расходы | C16: -357 | D16: -382 | E16: -645 | F16: -1142 | H16: Финансовые расходы | I16: =C16/$O$16 -> -23.181818 | J16: =D16/$O$15 -> -25.098555 | K16: =E16/$O$14 -> -36.29713 | L16: =F16/$O$13 -> -61.036879 | N16: 2021 | O16: 15.4
B17: Доля (убытка)/ прибыли от предприятий, учитываемых в составе собственного капитала | C17: 952 | D17: -227 | E17: 219 | F17: -1296 | H17: Доля (убытка)/ прибыли от предприятий, учитываемых в составе собственного капитала | I17: =C17/$O$16 -> 61.818182 | J17: =D17/$O$15 -> -14.914586 | K17: =E17/$O$14 -> 12.324142 | L17: =F17/$O$13 -> -69.267771
B18: Расходы на развитие рынка и продвижение продукции | C18: -966 | D18: -1342 | E18: -1800 | F18: -1343 | H18: Расходы на развитие рынка и продвижение продукции | I18: =C18/$O$16 -> -62.727273 | J18: =D18/$O$15 -> -88.173456 | K18: =E18/$O$14 -> -101.29432 | L18: =F18/$O$13 -> -71.779797
B19: Списание незавершенных капитальных работ и основных средств | C19: -27 | D19: -456 | E19: -177 | F19: -1868 | H19: Списание незавершенных капитальных работ и основных средств | I19: =C19/$O$16 -> -1.7532468 | J19: =D19/$O$15 -> -29.960578 | K19: =E19/$O$14 -> -9.9606078 | L19: =F19/$O$13 -> -99.839658
B20: Прочие расходы | C20: -3946 | D20: -1016 | E20: -2410 | F20: -3610 | H20: Прочие расходы | I20: =C20/$O$16 -> -256.23377 | J20: =D20/$O$15 -> -66.754271 | K20: =E20/$O$14 -> -135.62183 | L20: =F20/$O$13 -> -192.94495
B21: Прибыль до налогообложения | C21: 108311 | D21: 66768 | E21: 18109 | F21: 9679 | H21: Прибыль до налогообложения | I21: =C21/$O$16 -> 7033.1818 | J21: =D21/$O$15 -> 4386.8594 | K21: =E21/$O$14 -> 1019.0771 | L21: =F21/$O$13 -> 517.31694
B22: Расходы по налогу на прибыль | C22: -29290 | D22: -17472 | E22: -4663 | F22: -2286 | H22: Расходы по налогу на прибыль | I22: =C22/$O$16 -> -1901.9481 | J22: =D22/$O$15 -> -1147.9632 | K22: =E22/$O$14 -> -262.40855 | L22: =F22/$O$13 -> -122.18065
B23: Прибыль за год | C23: 79021 | D23: 49296 | E23: 13446 | F23: 7393 | H23: Прибыль за год | I23: =C23/$O$16 -> 5131.2338 | J23: =D23/$O$15 -> 3238.8962 | K23: =E23/$O$14 -> 756.66854 | L23: =F23/$O$13 -> 395.13629
B25: КОНСОЛИДИРОВАННЫЙ | H25: КОНСОЛИДИРОВАННЫЙ
B26: ОТЧЁТ О СОВОКУПНОМ ДОХОДЕ | D26: #VALUE! | H26: ОТЧЁТ О СОВОКУПНОМ ДОХОДЕ | J26: #VALUE!
B27: в миллионах южноафриканских рэнд | C27: За год, закончившийся 31 декабря | H27: в миллионах долларов США (пересчёт по среднегодовому курсу) | I27: За год, закончившийся 31 декабря
C28: 2021 | D28: 2022 | E28: 2023 | F28: 2024 | I28: 2021 | J28: 2022 | K28: 2023 | L28: 2024
B29: Прибыль за год | C29: 79021 | D29: 49296 | E29: 13446 | F29: 7393 | H29: Прибыль за год | I29: =C29/$O$16 -> 5131.2338 | J29: =D29/$O$15 -> 3238.8962 | K29: =E29/$O$14 -> 756.66854 | L29: =F29/$O$13 -> 395.13629
B30: Статьи, которые реклассифицированы или впоследствии могут быть реклассифицированы в состав прибыли или убытка: | C30: 712 | D30: 792 | E30: 2206 | F30: 308 | H30: Статьи, которые реклассифицированы или впоследствии могут быть реклассифицированы в состав прибыли или убытка: | I30: =C30/$O$16 -> 46.233766 | J30: =D30/$O$15 -> 52.036794 | K30: =E30/$O$14 -> 124.14181 | L30: =F30/$O$13 -> 16.461785
B31: Прибыль от пересчета иностранной валюты | C31: 712 | D31: 792 | E31: 2206 | F31: 308 | H31: Прибыль от пересчета иностранной валюты | I31: =C31/$O$16 -> 46.233766 | J31: =D31/$O$15 -> 52.036794 | K31: =E31/$O$14 -> 124.14181 | L31: =F31/$O$13 -> 16.461785
B32: Статьи, которые впоследствии не будут реклассифицированы в состав прибыли или убытка: | C32: -258 | D32: -866 | E32: -398 | F32: -154 | H32: Статьи, которые впоследствии не будут реклассифицированы в состав прибыли или убытка: | I32: =C32/$O$16 -> -16.753247 | J32: =D32/$O$15 -> -56.898817 | K32: =E32/$O$14 -> -22.397299 | L32: =F32/$O$13 -> -8.2308926
B33: Чистые убытки по инвестициям в долевые инструменты, оцениваемым по справедливой стоимости через прочий совокупный доход | H33: Чистые убытки по инвестициям в долевые инструменты, оцениваемым по справедливой стоимости через прочий совокупный доход
B34: доход (FVTOCI) | C34: -355 | D34: -913 | E34: -416 | F34: -201 | H34: доход (FVTOCI) | I34: =C34/$O$16 -> -23.051948 | J34: =D34/$O$15 -> -59.986859 | K34: =E34/$O$14 -> -23.410242 | L34: =F34/$O$13 -> -10.742918
B35: Налоговые последствия | C35: 97 | D35: 47 | E35: 18 | F35: 47 | H35: Налоговые последствия | I35: =C35/$O$16 -> 6.2987013 | J35: =D35/$O$15 -> 3.088042 | K35: =E35/$O$14 -> 1.0129432 | L35: =F35/$O$13 -> 2.5120257
B36: Прочий совокупный (расход)/доход за период с учетом эффекта налогообложения | C36: 454 | D36: -74 | E36: 1808 | F36: 154 | H36: Прочий совокупный (расход)/доход за период с учетом эффекта налогообложения | I36: =C36/$O$16 -> 29.480519 | J36: =D36/$O$15 -> -4.8620237 | K36: =E36/$O$14 -> 101.74451 | L36: =F36/$O$13 -> 8.2308926
B37: Общий совокупный доход за период | C37: 79475 | D37: 49222 | E37: 15254 | F37: 7547 | H37: Общий совокупный доход за период | I37: =C37/$O$16 -> 5160.7143 | J37: =D37/$O$15 -> 3234.0342 | K37: =E37/$O$14 -> 858.41306 | L37: =F37/$O$13 -> 403.36718
B39: КОНСОЛИДИРОВАННЫЙ | H39: КОНСОЛИДИРОВАННЫЙ
B40: ОТЧЁТ О ФИНАНСОВОМ ПОЛОЖЕНИИ | E40: #VALUE! | H40: ОТЧЁТ О ФИНАНСОВОМ ПОЛОЖЕНИИ | J40: #VALUE!
B41: в миллионах южноафриканских рэнд | C41: За год, закончившийся 31 декабря | H41: в миллионах долларов США (пересчёт по курсу на конец года) | I41: За год, закончившийся 31 декабря
C42: 2021 | D42: 2022 | E42: 2023 | F42: 2024 | I42: 2021 | J42: 2022 | K42: 2023 | L42: 2024
B43: АКТИВЫ | H43: АКТИВЫ
B44: Внеоборотные активы | H44: Внеоборотные активы
B45: Основные средства | C45: 52167 | D45: 59225 | E45: 68063 | F45: 76262 | H45: Основные средства | I45: =C45/$O$10 -> 3642.9469 | J45: =D45/$O$9 -> 3640.1352 | K45: =E45/$O$8 -> 3610.7692 | L45: =F45/$O$7 -> 4192.5234
B46: Незавершенные капитальные работы | C46: 14319 | D46: 19940 | E46: 24435 | F46: 25954 | H46: Незавершенные капитальные работы | I46: =C46/$O$10 -> 999.93017 | J46: =D46/$O$9 -> 1225.5685 | K46: =E46/$O$8 -> 1296.2865 | L46: =F46/$O$7 -> 1426.8279
B47: Запасы | C47: 6468 | D47: 3381 | E47: 2326 | F47: 5328 | H47: Запасы | I47: =C47/$O$10 -> 451.67598 | J47: =D47/$O$9 -> 207.80578 | K47: =E47/$O$8 -> 123.39523 | L47: =F47/$O$7 -> 292.90819
B48: Прочие финансовые активы | C48: 1963 | D48: 1952 | E48: 2317 | F48: 2300 | H48: Прочие финансовые активы | I48: =C48/$O$10 -> 137.08101 | J48: =D48/$O$9 -> 119.97541 | K48: =E48/$O$8 -> 122.91777 | L48: =F48/$O$7 -> 126.4431
B49: Инвестиции, принадлежащие экологическим фондам | C49: 1147 | D49: 1147 | E49: 1051 | F49: 1187 | H49: Инвестиции, принадлежащие экологическим фондам | I49: =C49/$O$10 -> 80.097765 | J49: =D49/$O$9 -> 70.497849 | K49: =E49/$O$8 -> 55.755968 | L49: =F49/$O$7 -> 65.255635
B50: Инвестиции в ассоциированные и совместные предприятия | C50: 967 | D50: 968 | E50: 833 | F50: 1028 | H50: Инвестиции в ассоциированные и совместные предприятия | I50: =C50/$O$10 -> 67.527933 | J50: =D50/$O$9 -> 59.496005 | K50: =E50/$O$8 -> 44.190981 | L50: =F50/$O$7 -> 56.514568
B51: Гудвил | C51: 397 | D51: 397 | E51: 397 | F51: 397 | H51: Гудвил | I51: =C51/$O$10 -> 27.723464 | J51: =D51/$O$9 -> 24.400738 | K51: =E51/$O$8 -> 21.061008 | L51: =F51/$O$7 -> 21.825179
B52: Отложенное налогообложение | C52: — | D52: 140 | E52: 140 | F52: 77 | H52: Отложенное налогообложение | J52: =D52/$O$9 -> 8.6047941 | K52: =E52/$O$8 -> 7.4270557 | L52: =F52/$O$7 -> 4.2330951
B53: Прочая дебиторская задолженность | C53: 53 | D53: 54 | E53: 70 | F53: — | H53: Прочая дебиторская задолженность | I53: =C53/$O$10 -> 3.7011173 | J53: =D53/$O$9 -> 3.318992 | K53: =E53/$O$8 -> 3.7135279
B54: ИТОГО ВНЕОБОРОТНЫЕ АКТИВЫ | C54: 77481 | D54: 87204 | E54: 99632 | F54: 112533 | H54: ИТОГО ВНЕОБОРОТНЫЕ АКТИВЫ | I54: =C54/$O$10 -> 5410.6844 | J54: =D54/$O$9 -> 5359.8033 | K54: =E54/$O$8 -> 5285.5172 | L54: =F54/$O$7 -> 6186.5311
B55: Текущие активы | H55: Текущие активы | I55: =C55/$O$10 -> 0 | J55: =D55/$O$9 -> 0 | K55: =E55/$O$8 -> 0 | L55: =F55/$O$7 -> 0
B56: Денежные средства и их эквиваленты | C56: 37569 | D56: 48934 | E56: 36279 | F56: 25423 | H56: Денежные средства и их эквиваленты | I56: =C56/$O$10 -> 2623.5335 | J56: =D56/$O$9 -> 3007.6214 | K56: =E56/$O$8 -> 1924.6154 | L56: =F56/$O$7 -> 1397.6361
B57: Запасы | C57: 51483 | D57: 29593 | E57: 24353 | F57: 24759 | H57: Запасы | I57: =C57/$O$10 -> 3595.1816 | J57: =D57/$O$9 -> 1818.8691 | K57: =E57/$O$8 -> 1291.9363 | L57: =F57/$O$7 -> 1361.1325
B58: Торговая и прочая дебиторская задолженность | C58: 7766 | D58: 3954 | E58: 3823 | F58: 3698 | H58: Торговая и прочая дебиторская задолженность | I58: =C58/$O$10 -> 542.31844 | J58: =D58/$O$9 -> 243.02397 | K58: =E58/$O$8 -> 202.81167 | L58: =F58/$O$7 -> 203.29852
B59: Прочие активы | C59: 3024 | D59: 3862 | E59: 2784 | F59: 2546 | H59: Прочие активы | I59: =C59/$O$10 -> 211.17318 | J59: =D59/$O$9 -> 237.36939 | K59: =E59/$O$8 -> 147.69231 | L59: =F59/$O$7 -> 139.96701
B60: Налогообложение | C60: 2431 | D60: 3200 | E60: 2306 | F60: 1643 | H60: Налогообложение | I60: =C60/$O$10 -> 169.76257 | J60: =D60/$O$9 -> 196.68101 | K60: =E60/$O$8 -> 122.33422 | L60: =F60/$O$7 -> 90.324354
B61: Прочие финансовые активы | C61: 395 | D61: 167 | E61: 38 | F61: 341 | H61: Прочие финансовые активы | I61: =C61/$O$10 -> 27.583799 | J61: =D61/$O$9 -> 10.26429 | K61: =E61/$O$8 -> 2.0159151 | L61: =F61/$O$7 -> 18.746564
B62: ИТОГО ТЕКУЩИЕ АКТИВЫ | C62: 102668 | D62: 89710 | E62: 69583 | F62: 58410 | H62: ИТОГО ТЕКУЩИЕ АКТИВЫ | I62: =C62/$O$10 -> 7169.5531 | J62: =D62/$O$9 -> 5513.8291 | K62: =E62/$O$8 -> 3691.4058 | L62: =F62/$O$7 -> 3211.105
B63: ИТОГО АКТИВЫ | C63: 180149 | D63: 176914 | E63: 169215 | F63: 170943 | H63: ИТОГО АКТИВЫ | I63: =C63/$O$10 -> 12580.237 | J63: =D63/$O$9 -> 10873.632 | K63: =E63/$O$8 -> 8976.9231 | L63: =F63/$O$7 -> 9397.6361
B64: КАПИТАЛ И ОБЯЗАТЕЛЬСТВА | H64: КАПИТАЛ И ОБЯЗАТЕЛЬСТВА
B65: Акционерный капитал и резервы | H65: Акционерный капитал и резервы
B66: Акционерный капитал | C66: 26 | D66: 26 | E66: 26 | F66: 26 | H66: Акционерный капитал | I66: =C66/$O$10 -> 1.8156425 | J66: =D66/$O$9 -> 1.5980332 | K66: =E66/$O$8 -> 1.3793103 | L66: =F66/$O$7 -> 1.4293568
B67: Эмиссионный доход | C67: 22782 | D67: 22784 | E67: 22744 | F67: 22407 | H67: Эмиссионный доход | I67: =C67/$O$10 -> 1590.9218 | J67: =D67/$O$9 -> 1400.3688 | K67: =E67/$O$8 -> 1206.5782 | L67: =F67/$O$7 -> 1231.8307
B68: Нераспределенная прибыль | C68: 74942 | D68: 69488 | E68: 70461 | F68: 72120 | H68: Нераспределенная прибыль | I68: =C68/$O$10 -> 5233.3799 | J68: =D68/$O$9 -> 4270.9281 | K68: =E68/$O$8 -> 3737.9841 | L68: =F68/$O$7 -> 3964.8158
B69: Резерв по пересчету иностранной валюты | C69: 3399 | D69: 4268 | E69: 6474 | F69: 6782 | H69: Резерв по пересчету иностранной валюты | I69: =C69/$O$10 -> 237.36034 | J69: =D69/$O$9 -> 262.32329 | K69: =E69/$O$8 -> 343.44828 | L69: =F69/$O$7 -> 372.84222
B70: Переоценка инвестиций в акционерный капитал, безвозвратно отраженных в FVTOCI | C70: 1064 | D70: 210 | E70: -93 | F70: 404 | H70: Переоценка инвестиций в акционерный капитал, безвозвратно отраженных в FVTOCI | I70: =C70/$O$10 -> 74.301676 | J70: =D70/$O$9 -> 12.907191 | K70: =E70/$O$8 -> -4.933687 | L70: =F70/$O$7 -> 22.210005
B71: Неконтролирующие доли участия | C71: 137 | D71: 186 | E71: 423 | F71: 374 | H71: Неконтролирующие доли участия | I71: =C71/$O$10 -> 9.5670391 | J71: =D71/$O$9 -> 11.432084 | K71: =E71/$O$8 -> 22.440318 | L71: =F71/$O$7 -> 20.560748
B72: ИТОГО АКЦИОНЕРНЫЙ КАПИТАЛ | C72: 102350 | D72: 96962 | E72: 100035 | F72: 102113 | H72: ИТОГО АКЦИОНЕРНЫЙ КАПИТАЛ | I72: =C72/$O$10 -> 7147.3464 | J72: =D72/$O$9 -> 5959.5575 | K72: =E72/$O$8 -> 5306.8966 | L72: =F72/$O$7 -> 5613.6888
B73: Долгосрочные обязательства | H73: Долгосрочные обязательства | I73: =C73/$O$10 -> 0 | J73: =D73/$O$9 -> 0 | K73: =E73/$O$8 -> 0 | L73: =F73/$O$7 -> 0
B74: Отложенное налогообложение | C74: 15648 | D74: 17138 | E74: 19131 | F74: 20645 | H74: Отложенное налогообложение | I74: =C74/$O$10 -> 1092.7374 | J74: =D74/$O$9 -> 1053.3497 | K74: =E74/$O$8 -> 1014.9072 | L74: =F74/$O$7 -> 1134.9643
B75: Экологические обязательства | C75: 2318 | D75: 2906 | E75: 2734 | F75: 2538 | H75: Экологические обязательства | I75: =C75/$O$10 -> 161.87151 | J75: =D75/$O$9 -> 178.61094 | K75: =E75/$O$8 -> 145.03979 | L75: =F75/$O$7 -> 139.52721
B76: Обязательства по аренде | C76: 2943 | D76: 1540 | E76: 365 | F76: 535 | H76: Обязательства по аренде | I76: =C76/$O$10 -> 205.51676 | J76: =D76/$O$9 -> 94.652735 | K76: =E76/$O$8 -> 19.363395 | L76: =F76/$O$7 -> 29.411765
B77: Выплаты сотрудникам | C77: 330 | D77: 273 | E77: 11 | F77: 11 | H77: Выплаты сотрудникам | I77: =C77/$O$10 -> 23.044693 | J77: =D77/$O$9 -> 16.779348 | K77: =E77/$O$8 -> 0.58355438 | L77: =F77/$O$7 -> 0.60472787
B78: Прочие финансовые обязательства | C78: 81 | D78: 27 | E78: — | F78: — | H78: Прочие финансовые обязательства | I78: =C78/$O$10 -> 5.6564246 | J78: =D78/$O$9 -> 1.659496
B79: Заемные средства | C79: 11 | D79: 11 | E79: — | F79: — | H79: Заемные средства | I79: =C79/$O$10 -> 0.76815642 | J79: =D79/$O$9 -> 0.67609096
B80: ИТОГО ДОЛГОСРОЧНЫЕ ОБЯЗАТЕЛЬСТВА | C80: 21331 | D80: 21895 | E80: 22241 | F80: 23729 | H80: ИТОГО ДОЛГОСРОЧНЫЕ ОБЯЗАТЕЛЬСТВА | I80: =C80/$O$10 -> 1489.595 | J80: =D80/$O$9 -> 1345.7283 | K80: =E80/$O$8 -> 1179.8939 | L80: =F80/$O$7 -> 1304.508
B81: Текущие обязательства | C81: 56468 | D81: 58057 | E81: 46939 | F81: 45101 | H81: Текущие обязательства | I81: =C81/$O$10 -> 3943.2961 | J81: =D81/$O$9 -> 3568.3467 | K81: =E81/$O$8 -> 2490.1326 | L81: =F81/$O$7 -> 2479.4393
B82: Торговая и прочая кредиторская задолженность | C82: 25110 | D82: 26767 | E82: 24540 | F82: 23438 | H82: Торговая и прочая кредиторская задолженность | I82: =C82/$O$10 -> 1753.4916 | J82: =D82/$O$9 -> 1645.1752 | K82: =E82/$O$8 -> 1301.8568 | L82: =F82/$O$7 -> 1288.5102
B83: Прочие обязательства | C83: 28240 | D83: 25605 | E83: 13247 | F83: 13951 | H83: Прочие обязательства | I83: =C83/$O$10 -> 1972.067 | J83: =D83/$O$9 -> 1573.7554 | K83: =E83/$O$8 -> 702.75862 | L83: =F83/$O$7 -> 766.95987
B84: Заемные средства | C84: 50 | D84: 55 | E84: 7117 | F84: 6003 | H84: Заемные средства | I84: =C84/$O$10 -> 3.4916201 | J84: =D84/$O$9 -> 3.3804548 | K84: =E84/$O$8 -> 377.55968 | L84: =F84/$O$7 -> 330.01649
B85: Прочие финансовые обязательства | C85: 2697 | D85: 2677 | E85: 1266 | F85: 635 | H85: Прочие финансовые обязательства | I85: =C85/$O$10 -> 188.33799 | J85: =D85/$O$9 -> 164.53596 | K85: =E85/$O$8 -> 67.161804 | L85: =F85/$O$7 -> 34.909291
B86: Резерв | C86: 30 | D86: 7 | E86: 109 | F86: 467 | H86: Резерв | I86: =C86/$O$10 -> 2.0949721 | J86: =D86/$O$9 -> 0.4302397 | K86: =E86/$O$8 -> 5.7824934 | L86: =F86/$O$7 -> 25.673447
B87: Обязательства по аренде | C87: 151 | D87: 103 | E87: 149 | F87: 336 | H87: Обязательства по аренде | I87: =C87/$O$10 -> 10.544693 | J87: =D87/$O$9 -> 6.3306699 | K87: =E87/$O$8 -> 7.9045093 | L87: =F87/$O$7 -> 18.471688
B88: Налогообложение | C88: 160 | D88: 1590 | E88: 511 | F88: 164 | H88: Налогообложение | I88: =C88/$O$10 -> 11.173184 | J88: =D88/$O$9 -> 97.725876 | K88: =E88/$O$8 -> 27.108753 | L88: =F88/$O$7 -> 9.0159428
B89: Экологические обязательства | C89: — | D89: 1248 | E89: — | F89: 107 | H89: Экологические обязательства | J89: =D89/$O$9 -> 76.705593 | L89: =F89/$O$7 -> 5.8823529
B90: Положение о выплате на основе акций | C90: 30 | D90: 5 | E90: — | F90: - | H90: Выплаты сотрудникам акциями | I90: =C90/$O$10 -> 2.0949721 | J90: =D90/$O$9 -> 0.30731407
B91: ИТОГО КАПИТАЛ И ОБЯЗАТЕЛЬСТВА | C91: 180149 | D91: 176914 | E91: 169215 | F91: 170943 | H91: ИТОГО КАПИТАЛ И ОБЯЗАТЕЛЬСТВА | I91: =C91/$O$10 -> 12580.237 | J91: =D91/$O$9 -> 10873.632 | K91: =E91/$O$8 -> 8976.9231 | L91: =F91/$O$7 -> 9397.6361

Sheet Impala Platinum
B2: КОНСОЛИДИРОВАННЫЙ | H2: КОНСОЛИДИРОВАННЫЙ
B3: ОТЧЁТ О ПРИБЫЛЯХ И УБЫТКАХ | D3: #VALUE! | H3: ОТЧЁТ О ПРИБЫЛЯХ И УБЫТКАХ | J3: #VALUE!
B4: в миллионах южноафриканских рэнд | C4: За год, закончившийся 30 июня | H4: в миллионах долларов США (пересчёт по среднегодовому курсу) | I4: За год, закончившийся 30 июня
C5: 2021 | D5: 2022 | E5: 2023 | F5: 2024 | I5: 2021 | J5: 2022 | K5: 2023 | L5: 2024 | N5: Курс USD/R
B6: Выручка | C6: 129575 | D6: 118332 | E6: 106594 | F6: 86398 | H6: Выручка | I6: =C6/$O$16 -> 8413.961 | J6: =D6/$O$15 -> 7774.77 | K6: =E6/$O$14 -> 5998.5369 | L6: =F6/$O$13 -> 4617.7445 | N6: Year-end rate (R/USD):
B7: Себестоимость продаж | C7: -76120 | D7: -77047 | E7: -84256 | F7: -80931 | H7: Себестоимость продаж | I7: =C7/$O$16 -> -4942.8571 | J7: =D7/$O$15 -> -5062.2208 | K7: =E7/$O$14 -> -4741.4744 | L7: =F7/$O$13 -> -4325.5478 | N7: 2024 | O7: 18.19
B8: Валовая прибыль | C8: 53455 | D8: 41285 | E8: 22338 | F8: 5467 | H8: Валовая прибыль | I8: =C8/$O$16 -> 3471.1039 | J8: =D8/$O$15 -> 2712.5493 | K8: =E8/$O$14 -> 1257.0625 | L8: =F8/$O$13 -> 292.19669 | N8: 2023 | O8: 18.85
B9: Обесценение | C9: 14728 | D9: — | E9: -15116 | F9: -21852 | H9: Обесценение | I9: =C9/$O$16 -> 956.36364 | J9: — | K9: =E9/$O$14 -> -850.64716 | L9: =F9/$O$13 -> -1167.9316 | N9: 2022 | O9: 16.27
B10: МСФО (IFRS) 2 "Расходы по сделке B-BBEE" | D10: — | E10: — | F10: -1932 | H10: МСФО (IFRS) 2 "Расходы по сделке B-BBEE" | I10: — | J10: — | K10: — | L10: =F10/$O$13 -> -103.26029 | N10: 2021 | O10: 14.32
B11: Убыток от переоценки ранее удерживаемых инвестиций в акционерный капитал до приобретения | H11: Убыток от переоценки ранее удерживаемых инвестиций в акционерный капитал до приобретения | I11: — | J11: — | K11: — | L11: —
B12: – Royal Bafokeng Platinum | D12: — | E12: -1772 | F12: — | H12: – Royal Bafokeng Platinum | I12: — | J12: — | K12: =E12/$O$14 -> -99.718627 | L12: — | N12: Average rate:
B13: Прочие доходы | C13: 214 | D13: 100 | E13: 240 | F13: 1170 | H13: Прочие доходы | I13: =C13/$O$16 -> 13.896104 | J13: =D13/$O$15 -> 6.5703022 | K13: =E13/$O$14 -> 13.505909 | L13: =F13/$O$13 -> 62.533405 | N13: 2024 | O13: 18.71
B14: Прочие расходы | C14: -2175 | D14: -539 | E14: -1319 | F14: -1289 | H14: Прочие расходы | I14: =C14/$O$16 -> -141.23377 | J14: =D14/$O$15 -> -35.413929 | K14: =E14/$O$14 -> -74.226224 | L14: =F14/$O$13 -> -68.89364 | N14: 2023 | O14: 17.77
B15: Финансовые доходы | C15: 768 | D15: 805 | E15: 1792 | F15: 1076 | H15: Финансовые доходы | I15: =C15/$O$16 -> 49.87013 | J15: =D15/$O$15 -> 52.890933 | K15: =E15/$O$14 -> 100.84412 | L15: =F15/$O$13 -> 57.509353 | N15: 2022 | O15: 15.22
B16: Финансовые затраты | C16: -946 | D16: -562 | E16: -615 | F16: -960 | H16: Финансовые затраты | I16: =C16/$O$16 -> -61.428571 | J16: =D16/$O$15 -> -36.925099 | K16: =E16/$O$14 -> -34.608891 | L16: =F16/$O$13 -> -51.30946 | N16: 2021 | O16: 15.4
B17: Чистая прибыль/(убытки) от операций с иностранной валютой | C17: -1336 | D17: -161 | E17: 857 | F17: -924 | H17: Чистая прибыль/(убытки) от операций с иностранной валютой | I17: =C17/$O$16 -> -86.753247 | J17: =D17/$O$15 -> -10.578187 | K17: =E17/$O$14 -> 48.227349 | L17: =F17/$O$13 -> -49.385355
B18: Доля (убытка)/прибыли предприятий, учитываемых в составе собственного капитала | C18: 3212 | D18: 4311 | E18: 3382 | F18: -1182 | H18: Доля (убытка)/прибыли предприятий, учитываемых в составе собственного капитала | I18: =C18/$O$16 -> 208.57143 | J18: =D18/$O$15 -> 283.24573 | K18: =E18/$O$14 -> 190.32077 | L18: =F18/$O$13 -> -63.174773
B19: Прибыль до налогообложения | C19: 67920 | D19: 45239 | E19: 9787 | F19: -20426 | H19: Прибыль до налогообложения | I19: =C19/$O$16 -> 4410.3896 | J19: =D19/$O$15 -> 2972.339 | K19: =E19/$O$14 -> 550.75971 | L19: =F19/$O$13 -> -1091.7157
B20: Расходы по налогу на прибыль | C20: -20065 | D20: -12100 | E20: -3609 | F20: 3275 | H20: Расходы по налогу на прибыль | I20: =C20/$O$16 -> -1302.9221 | J20: =D20/$O$15 -> -795.00657 | K20: =E20/$O$14 -> -203.0951 | L20: =F20/$O$13 -> 175.04009
B21: Прибыль за год | C21: 47855 | D21: 33139 | E21: 6178 | F21: -17151 | H21: Прибыль за год | I21: =C21/$O$16 -> 3107.4675 | J21: =D21/$O$15 -> 2177.3325 | K21: =E21/$O$14 -> 347.6646 | L21: =F21/$O$13 -> -916.67557
B23: КОНСОЛИДИРОВАННЫЙ | H23: КОНСОЛИДИРОВАННЫЙ
B24: ОТЧЁТ О СОВОКУПНОМ ДОХОДЕ | D24: #VALUE! | H24: ОТЧЁТ О СОВОКУПНОМ ДОХОДЕ | J24: #VALUE!
B25: в миллионах южноафриканских рэнд | C25: За год, закончившийся 30 июня | H25: в миллионах долларов США (пересчёт по среднегодовому курсу) | I25: За год, закончившийся 30 июня
C26: 2021 | D26: 2022 | E26: 2023 | F26: 2024 | I26: 2021 | J26: 2022 | K26: 2023 | L26: 2024
B27: Прибыль за год | C27: 47855 | D27: 33139 | E27: 6178 | F27: -17151 | H27: Прибыль за год | I27: =C27/$O$16 -> 3107.4675 | J27: =D27/$O$15 -> 2177.3325 | K27: =E27/$O$14 -> 347.6646 | L27: =F27/$O$13 -> -916.67557
B28: Прочий совокупный доход/(расход) | H28: Прочий совокупный доход/(расход)
B29: Статьи, которые реклассифицированы или впоследствии могут быть реклассифицированы в состав прибыли или убытка: | H29: Статьи, которые реклассифицированы или впоследствии могут быть реклассифицированы в состав прибыли или убытка:
B30: Курсовые разницы при пересчете зарубежных операций | C30: -4758 | D30: 4304 | E30: 5805 | F30: -1432 | H30: Курсовые разницы при пересчете зарубежных операций | I30: =C30/$O$16 -> -308.96104 | J30: =D30/$O$15 -> 282.78581 | K30: =E30/$O$14 -> 326.67417 | L30: =F30/$O$13 -> -76.536611
B31: Отложенный налог по нему | C31: 89 | D31: -106 | E31: -89 | F31: 673 | H31: Отложенный налог по нему | I31: =C31/$O$16 -> 5.7792208 | J31: =D31/$O$15 -> -6.9645204 | K31: =E31/$O$14 -> -5.0084412 | L31: =F31/$O$13 -> 35.970069
B32: Статьи, которые впоследствии не будут реклассифицированы в состав прибыли или убытка: | H32: Статьи, которые впоследствии не будут реклассифицированы в состав прибыли или убытка:
B33: Финансовые активы, оцениваемые по справедливой стоимости через прочий совокупный доход | C33: 31 | D33: 38 | E33: 152 | F33: 32 | H33: Финансовые активы, оцениваемые по справедливой стоимости через прочий совокупный доход | I33: =C33/$O$16 -> 2.012987 | J33: =D33/$O$15 -> 2.4967148 | K33: =E33/$O$14 -> 8.5537423 | L33: =F33/$O$13 -> 1.7103153
B34: Отложенный налог по нему | C34: — | D34: — | E34: — | F34: — | H34: Отложенный налог по нему
B35: Актуарный (убыток) / прибыль от медицинского пособия по окончании трудовой деятельности | C35: -3 | D35: 1 | E35: 5 | F35: -3 | H35: Актуарный (убыток) / прибыль от медицинского пособия по окончании трудовой деятельности | I35: =C35/$O$16 -> -0.19480519 | J35: =D35/$O$15 -> 0.065703022 | K35: =E35/$O$14 -> 0.2813731 | L35: =F35/$O$13 -> -0.16034206
B36: Отложенный налог по нему | C36: 1 | D36: — | E36: -1 | F36: 1 | H36: Отложенный налог по нему | I36: =C36/$O$16 -> 0.064935065 | K36: =E36/$O$14 -> -0.05627462 | L36: =F36/$O$13 -> 0.053447354
B37: Прочий совокупный (расход)/доход за период | C37: -4640 | D37: 4237 | E37: 5872 | F37: -729 | H37: Прочий совокупный (расход)/доход за период с учетом эффекта налогообложения | I37: =C37/$O$16 -> -301.2987 | J37: =D37/$O$15 -> 278.38371 | K37: =E37/$O$14 -> 330.44457 | L37: =F37/$O$13 -> -38.963121
B38: Общий совокупный доход за период | C38: 43215 | D38: 37376 | E38: 12050 | F38: -17880 | H38: Общий совокупный доход за период с учетом эффекта налогообложения | I38: =C38/$O$16 -> 2806.1688 | J38: =D38/$O$15 -> 2455.7162 | K38: =E38/$O$14 -> 678.10917 | L38: =F38/$O$13 -> -955.6387
B40: КОНСОЛИДИРОВАННЫЙ | H40: КОНСОЛИДИРОВАННЫЙ
B41: ОТЧЁТ О ФИНАНСОВОМ ПОЛОЖЕНИИ | D41: #VALUE! | H41: ОТЧЁТ О ФИНАНСОВОМ ПОЛОЖЕНИИ | J41: #VALUE!
B42: в миллионах южноафриканских рэнд | C42: За год, закончившийся 30 июня | H42: в миллионах долларов США (пересчёт по курсу на конец года) | I42: За год, закончившийся 30 июня
C43: 2021 | D43: 2022 | E43: 2023 | F43: 2024 | I43: 2021 | J43: 2022 | K43: 2023 | L43: 2024
B44: АКТИВЫ | H44: АКТИВЫ
B45: Внеоборотные активы | H45: Внеоборотные активы
B46: Основные средства | C46: 57709 | D46: 64513 | E46: 71176 | F46: 63502 | H46: Основные средства | I46: =C46/$O$10 -> 4029.9581 | J46: ='Impala Platinum'!D46/'Impala Platinum'!$O$9 -> 3965.1506 | K46: =E46/$O$8 -> 3775.9151 | L46: =F46/$O$7 -> 3491.039
B47: Инвестиционная собственность | C47: 90 | D47: 90 | E47: 88 | F47: 86 | H47: Инвестиционная собственность | I47: =C47/$O$10 -> 6.2849162 | J47: ='Impala Platinum'!D47/'Impala Platinum'!$O$9 -> 5.5316533 | K47: =E47/$O$8 -> 4.668435 | L47: =F47/$O$7 -> 4.7278725
B48: Goodwill | E48: 9870 | F48: 3523 | H48: Goodwill | I48: =C48/$O$10 -> 0 | J48: ='Impala Platinum'!D48/'Impala Platinum'!$O$9 -> 0 | K48: =E48/$O$8 -> 523.60743 | L48: =F48/$O$7 -> 193.67784
B49: Инвестиции в предприятия, учитываемые в капитале | C49: 7748 | D49: 26804 | E49: 12525 | F49: 10305 | H49: Инвестиции в предприятия, учитываемые в капитале | I49: =C49/$O$10 -> 541.06145 | J49: ='Impala Platinum'!D49/'Impala Platinum'!$O$9 -> 1647.4493 | K49: =E49/$O$8 -> 664.45623 | L49: =F49/$O$7 -> 566.52007
B50: Финансовые активы, оцениваемые по справедливой стоимости через прочий совокупный доход | C50: 425 | D50: 463 | E50: 661 | F50: 693 | H50: Финансовые активы, оцениваемые по справедливой стоимости через прочий совокупный доход | I50: =C50/$O$10 -> 29.678771 | J50: ='Impala Platinum'!D50/'Impala Platinum'!$O$9 -> 28.457283 | K50: =E50/$O$8 -> 35.066313 | L50: =F50/$O$7 -> 38.097856
B51: Инвестиции в восстановление окружающей среды | C51: — | D51: 315 | E51: 2506 | F51: 2776 | H51: Инвестиции в восстановление окружающей среды | J51: ='Impala Platinum'!D51/'Impala Platinum'!$O$9 -> 19.360787 | K51: =E51/$O$8 -> 132.9443 | L51: =F51/$O$7 -> 152.61132
B52: Прочие финансовые активы | C52: 84 | D52: 125 | E52: 1257 | F52: 1275 | H52: Прочие финансовые активы | I52: =C52/$O$10 -> 5.8659218 | J52: ='Impala Platinum'!D52/'Impala Platinum'!$O$9 -> 7.6828519 | K52: =E52/$O$8 -> 66.68435 | L52: =F52/$O$7 -> 70.093458
B53: Авансовые платежи и прочие активы | C53: 3747 | D53: 3597 | E53: 3541 | F53: 208 | H53: Авансовые платежи и прочие активы | I53: =C53/$O$10 -> 261.66201 | J53: ='Impala Platinum'!D53/'Impala Platinum'!$O$9 -> 221.08175 | K53: =E53/$O$8 -> 187.85146 | L53: =F53/$O$7 -> 11.434854
B54: ИТОГО ВНЕОБОРОТНЫЕ АКТИВЫ | C54: 69803 | D54: 95907 | E54: 101624 | F54: 82368 | H54: ИТОГО ВНЕОБОРОТНЫЕ АКТИВЫ | I54: =C54/$O$10 -> 4874.5112 | J54: ='Impala Platinum'!D54/'Impala Platinum'!$O$9 -> 5894.7142 | K54: =E54/$O$8 -> 5391.1936 | L54: =F54/$O$7 -> 4528.2023
B55: Оборотные активы | H55: Оборотные активы
B56: Запасы | C56: 22711 | D56: 23899 | E56: 24320 | F56: 26578 | H56: Запасы | I56: =C56/$O$10 -> 1585.9637 | J56: ='Impala Platinum'!D56/'Impala Platinum'!$O$9 -> 1468.8998 | K56: =E56/$O$8 -> 1290.1857 | L56: =F56/$O$7 -> 1461.1325
B57: Торговая и прочая дебиторская задолженность | C57: 7308 | D57: 6209 | E57: 11310 | F57: 11826 | H57: Торговая и прочая дебиторская задолженность | I57: =C57/$O$10 -> 510.3352 | J57: ='Impala Platinum'!D57/'Impala Platinum'!$O$9 -> 381.62262 | K57: =E57/$O$8 -> 600 | L57: =F57/$O$7 -> 650.13744
B58: Текущая задолженность по налогу | C58: 1064 | D58: 530 | E58: 1059 | F58: 791 | H58: Текущая задолженность по налогу | I58: =C58/$O$10 -> 74.301676 | J58: ='Impala Platinum'!D58/'Impala Platinum'!$O$9 -> 32.575292 | K58: =E58/$O$8 -> 56.180371 | L58: =F58/$O$7 -> 43.485432
B59: Прочие финансовые активы | C59: 1006 | D59: 1056 | E59: 23 | F59: 34 | H59: Прочие финансовые активы | I59: =C59/$O$10 -> 70.251397 | J59: ='Impala Platinum'!D59/'Impala Platinum'!$O$9 -> 64.904733 | K59: =E59/$O$8 -> 1.2201592 | L59: =F59/$O$7 -> 1.8691589
B60: Авансовые платежи и прочие активы | C60: 1109 | D60: 1981 | E60: 4230 | F60: 1729 | H60: Авансовые платежи и прочие активы | I60: =C60/$O$10 -> 77.444134 | J60: ='Impala Platinum'!D60/'Impala Platinum'!$O$9 -> 121.75784 | K60: =E60/$O$8 -> 224.40318 | L60: =F60/$O$7 -> 95.052226
B61: Денежные средства и их эквиваленты | C61: 23474 | D61: 26505 | E61: 26820 | F61: 9629 | H61: Денежные средства и их эквиваленты | I61: =C61/$O$10 -> 1639.2458 | J61: ='Impala Platinum'!D61/'Impala Platinum'!$O$9 -> 1629.0719 | K61: =E61/$O$8 -> 1422.8117 | L61: =F61/$O$7 -> 529.35679
B62: ИТОГО ОБОРОТНЫЕ АКТИВЫ | C62: 56672 | D62: 60180 | E62: 67762 | F62: 50587 | H62: ИТОГО ОБОРОТНЫЕ АКТИВЫ | I62: =C62/$O$10 -> 3957.5419 | J62: ='Impala Platinum'!D62/'Impala Platinum'!$O$9 -> 3698.8322 | K62: =E62/$O$8 -> 3594.8011 | L62: =F62/$O$7 -> 2781.0335
B63: ИТОГО АКТИВЫ | C63: 126475 | D63: 156087 | E63: 169386 | F63: 132955 | H63: ИТОГО АКТИВЫ | I63: =C63/$O$10 -> 8832.0531 | J63: ='Impala Platinum'!D63/'Impala Platinum'!$O$9 -> 9593.5464 | K63: =E63/$O$8 -> 8985.9947 | L63: =F63/$O$7 -> 7309.2358
B64: СОБСТВЕННЫЙ КАПИТАЛ И ОБЯЗАТЕЛЬСТВА | H64: СОБСТВЕННЫЙ КАПИТАЛ И ОБЯЗАТЕЛЬСТВА
B65: Собственный капитал | H65: Собственный капитал
B66: Акционерный капитал | C66: 21189 | D66: 23080 | E66: 25819 | F66: 31096 | H66: Акционерный капитал | I66: =C66/$O$10 -> 1479.6788 | J66: ='Impala Platinum'!D66/'Impala Platinum'!$O$9 -> 1418.5618 | K66: =E66/$O$8 -> 1369.7082 | L66: =F66/$O$7 -> 1709.5107
B67: Нераспределенная прибыль | C67: 59661 | D67: 81336 | E67: 74175 | F67: 44276 | H67: Нераспределенная прибыль | I67: =C67/$O$10 -> 4166.2709 | J67: ='Impala Platinum'!D67/'Impala Platinum'!$O$9 -> 4999.1395 | K67: =E67/$O$8 -> 3935.0133 | L67: =F67/$O$7 -> 2434.0847
B68: Резерв по пересчету иностранной валюты | C68: 4917 | D68: 8718 | E68: 13920 | F68: 13321 | H68: Резерв по пересчету иностранной валюты | I68: =C68/$O$10 -> 343.36592 | J68: ='Impala Platinum'!D68/'Impala Platinum'!$O$9 -> 535.83282 | K68: =E68/$O$8 -> 738.46154 | L68: =F68/$O$7 -> 732.32545
B69: Резерв для выплат на основе акций | C69: 1799 | D69: 1262 | E69: 480 | F69: 2221 | H69: Резерв для выплат на основе акций | I69: =C69/$O$10 -> 125.62849 | J69: ='Impala Platinum'!D69/'Impala Platinum'!$O$9 -> 77.566073 | K69: =E69/$O$8 -> 25.464191 | L69: =F69/$O$7 -> 122.10005
B70: Другие компоненты собственного капитала | C70: 263 | D70: 301 | E70: 453 | F70: 485 | H70: Другие компоненты собственного капитала | I70: =C70/$O$10 -> 18.365922 | J70: ='Impala Platinum'!D70/'Impala Platinum'!$O$9 -> 18.500307 | K70: =E70/$O$8 -> 24.03183 | L70: =F70/$O$7 -> 26.663002
B71: Собственный капитал, приходящийся на долю владельцев Компании | C71: 87829 | D71: 114697 | E71: 114847 | F71: 91399 | H71: Собственный капитал, приходящийся на долю владельцев Компании | I71: =C71/$O$10 -> 6133.3101 | J71: ='Impala Platinum'!D71/'Impala Platinum'!$O$9 -> 7049.6005 | K71: =E71/$O$8 -> 6092.679 | L71: =F71/$O$7 -> 5024.6839
B72: Неконтролирующие доли в капитале | C72: 2847 | D72: 4594 | E72: 11188 | F72: 5226 | H72: Неконтролирующие доли в капитале | I72: =C72/$O$10 -> 198.81285 | J72: ='Impala Platinum'!D72/'Impala Platinum'!$O$9 -> 282.36017 | K72: =E72/$O$8 -> 593.52785 | L72: =F72/$O$7 -> 287.30071
B73: Общий собственный капитал | C73: 90676 | D73: 119291 | E73: 126035 | F73: 96625 | H73: Общий собственный капитал | I73: =C73/$O$10 -> 6332.1229 | J73: ='Impala Platinum'!D73/'Impala Platinum'!$O$9 -> 7331.9607 | K73: =E73/$O$8 -> 6686.2069 | L73: =F73/$O$7 -> 5311.9846
B74: Долгосрочные обязательства | H74: Долгосрочные обязательства | I74: =C74/$O$10 -> 0 | J74: ='Impala Platinum'!D74/'Impala Platinum'!$O$9 -> 0 | K74: =E74/$O$8 -> 0
B75: Отложенный налог | C75: 14405 | D75: 16795 | E75: 19140 | F75: 13332 | H75: Отложенный налог | I75: =C75/$O$10 -> 1005.9358 | J75: ='Impala Platinum'!D75/'Impala Platinum'!$O$9 -> 1032.268 | K75: =E75/$O$8 -> 1015.3846 | L75: =F75/$O$7 -> 732.93018
B76: Резерв | C76: 2239 | D76: 2214 | E76: 2734 | F76: 2855 | H76: Резерв | I76: =C76/$O$10 -> 156.35475 | J76: ='Impala Platinum'!D76/'Impala Platinum'!$O$9 -> 136.07867 | K76: =E76/$O$8 -> 145.03979 | L76: =F76/$O$7 -> 156.95437
B77: Доходы будущих периодов | E77: 1238 | F77: 1259 | H77: Доходы будущих периодов | I77: =C77/$O$10 -> 0 | J77: ='Impala Platinum'!D77/'Impala Platinum'!$O$9 -> 0 | K77: =E77/$O$8 -> 65.676393 | L77: =F77/$O$7 -> 69.213854
B78: Заемные средства | C78: 1087 | D78: 957 | E78: 2255 | F78: 1912 | H78: Заемные средства | I78: =C78/$O$10 -> 75.907821 | J78: ='Impala Platinum'!D78/'Impala Platinum'!$O$9 -> 58.819914 | K78: =E78/$O$8 -> 119.62865 | L78: =F78/$O$7 -> 105.1127
B79: Прочие финансовые обязательства | C79: 24 | D79: 16 | E79: 8 | F79: — | H79: Прочие финансовые обязательства | I79: =C79/$O$10 -> 1.6759777 | J79: ='Impala Platinum'!D79/'Impala Platinum'!$O$9 -> 0.98340504 | K79: =E79/$O$8 -> 0.42440318
B80: Прочие обязательства | C80: 251 | D80: 227 | E80: 304 | F80: 128 | H80: Прочие обязательства | I80: =C80/$O$10 -> 17.527933 | J80: ='Impala Platinum'!D80/'Impala Platinum'!$O$9 -> 13.952059 | K80: =E80/$O$8 -> 16.127321 | L80: =F80/$O$7 -> 7.0368334
B81: ИТОГО ДОЛГОСРОЧНЫЕ ОБЯЗАТЕЛЬСТВА | C81: 18006 | D81: 20209 | E81: 25679 | F81: 19486 | H81: ИТОГО ДОЛГОСРОЧНЫЕ ОБЯЗАТЕЛЬСТВА | I81: =C81/$O$10 -> 1257.4022 | J81: ='Impala Platinum'!D81/'Impala Platinum'!$O$9 -> 1242.102 | K81: =E81/$O$8 -> 1362.2812 | L81: =F81/$O$7 -> 1071.2479
B82: Краткосрочные обязательства | H82: Краткосрочные обязательства
B83: Торговая и прочая кредиторская задолженность | C83: 16190 | D83: 15428 | E83: 16041 | F83: 14798 | H83: Торговая и прочая кредиторская задолженность | I83: =C83/$O$10 -> 1130.5866 | J83: ='Impala Platinum'!D83/'Impala Platinum'!$O$9 -> 948.24831 | K83: =E83/$O$8 -> 850.98143 | L83: =F83/$O$7 -> 813.52391
B84: Текущий налог, подлежащий уплате | C84: 653 | D84: 533 | E84: 242 | F84: 173 | H84: Текущий налог, подлежащий уплате | I84: =C84/$O$10 -> 45.600559 | J84: ='Impala Platinum'!D84/'Impala Platinum'!$O$9 -> 32.75968 | K84: =E84/$O$8 -> 12.838196 | L84: =F84/$O$7 -> 9.5107202
B85: Резерв | C85: 100 | D85: 98 | E85: 94 | F85: 55 | H85: Резерв | I85: =C85/$O$10 -> 6.9832402 | J85: ='Impala Platinum'!D85/'Impala Platinum'!$O$9 -> 6.0233559 | K85: =E85/$O$8 -> 4.9867374 | L85: =F85/$O$7 -> 3.0236394
B86: Доходы будущих периодов | C86: — | D86: — | E86: 144 | F86: 240 | H86: Доходы будущих периодов | K86: =E86/$O$8 -> 7.6392573 | L86: =F86/$O$7 -> 13.194063
B87: Заемные средства | C87: 241 | D87: 250 | E87: 335 | F87: 1429 | H87: Заемные средства | I87: =C87/$O$10 -> 16.829609 | J87: ='Impala Platinum'!D87/'Impala Platinum'!$O$9 -> 15.365704 | K87: =E87/$O$8 -> 17.771883 | L87: =F87/$O$7 -> 78.559648
B88: Прочие финансовые обязательства | C88: 28 | D88: 34 | E88: 263 | F88: 49 | H88: Прочие финансовые обязательства | I88: =C88/$O$10 -> 1.9553073 | J88: ='Impala Platinum'!D88/'Impala Platinum'!$O$9 -> 2.0897357 | K88: =E88/$O$8 -> 13.952255 | L88: =F88/$O$7 -> 2.6937878
B89: Прочие обязательства | C89: 581 | D89: 244 | E89: 553 | F89: 100 | H89: Прочие обязательства | I89: =C89/$O$10 -> 40.572626 | J89: ='Impala Platinum'!D89/'Impala Platinum'!$O$9 -> 14.996927 | K89: =E89/$O$8 -> 29.33687 | L89: =F89/$O$7 -> 5.4975261
B90: ИТОГО КРАТКОСРОЧНЫЕ ОБЯЗАТЕЛЬСТВА | C90: 17793 | D90: 16587 | E90: 17672 | F90: 16844 | H90: ИТОГО КРАТКОСРОЧНЫЕ ОБЯЗАТЕЛЬСТВА | I90: =C90/$O$10 -> 1242.5279 | J90: ='Impala Platinum'!D90/'Impala Platinum'!$O$9 -> 1019.4837 | K90: =E90/$O$8 -> 937.50663 | L90: =F90/$O$7 -> 926.0033
B91: ИТОГО ОБЯЗАТЕЛЬСТВА | C91: 35799 | D91: 36796 | E91: 43351 | F91: 36330 | H91: ИТОГО ОБЯЗАТЕЛЬСТВА | I91: =C91/$O$10 -> 2499.9302 | J91: ='Impala Platinum'!D91/'Impala Platinum'!$O$9 -> 2261.5857 | K91: =E91/$O$8 -> 2299.7878 | L91: =F91/$O$7 -> 1997.2512
B92: ИТОГО КАПИТАЛ И ОБЯЗАТЕЛЬСТВА | C92: 126475 | D92: 156087 | E92: 169386 | F92: 132955 | H92: ИТОГО КАПИТАЛ И ОБЯЗАТЕЛЬСТВА | I92: =C92/$O$10 -> 8832.0531 | J92: ='Impala Platinum'!D92/'Impala Platinum'!$O$9 -> 9593.5464 | K92: =E92/$O$8 -> 8985.9947 | L92: =F92/$O$7 -> 7309.2358

Sheet Параметры ключевых метрик
B2: ОПРЕДЕЛИТЕ ЗДЕСЬ КЛЮЧЕВЫЕ МЕТРИКИ
B3: 1 | C3: Итого выручка | D3: =IF(ISBLANK(C3),"← Выберите значение из раскрывающегося списка",IF(COUNTIF($C$3:C3,C3)>1,"Вы выбрали значение "&C3&" дважды.",""))
B4: 2 | C4: Валовая прибыль | D4: =IF(ISBLANK(C4),"← Выберите значение из раскрывающегося списка",IF(COUNTIF($C$3:C4,C4)>1,"Вы выбрали значение "&C4&" дважды.",""))
B5: 3 | C5: Прибыль от операционной деятельности | D5: =IF(ISBLANK(C5),"← Выберите значение из раскрывающегося списка",IF(COUNTIF($C$3:C5,C5)>1,"Вы выбрали значение "&C5&" дважды.",""))
B6: 4 | C6: Прибыль до налогообложения | D6: =IF(ISBLANK(C6),"← Выберите значение из раскрывающегося списка",IF(COUNTIF($C$3:C6,C6)>1,"Вы выбрали значение "&C6&" дважды.",""))
B7: 5 | C7: Прибыль за год | D7: =IF(ISBLANK(C7),"← Выберите значение из раскрывающегося списка",IF(COUNTIF($C$3:C7,C7)>1,"Вы выбрали значение "&C7&" дважды.",""))

Sheet Расчеты
A1: Этот лист используется для выполнения расчетов финансового отчета и должен оставаться скрытым.
D2: Позиция
B3: Текущий год | C3: =Выбранный_год -> 2024 | D3: =MATCH(C3,Прошедшие_годы,0)+1 -> #N/A
B4: Предыдущий год | C4: =C3-1 -> 2023 | D4: =MATCH(C4,Прошедшие_годы,0)+1 -> #N/A
B6: Позиция | C6: =MATCH(C7,Прошедшие_годы,0)+1 -> #N/A | D6: =MATCH(D7,Прошедшие_годы,0)+1 -> #N/A | E6: =MATCH(E7,Прошедшие_годы,0)+1 -> #N/A | F6: =MATCH(F7,Прошедшие_годы,0)+1 -> #N/A | G6: =MATCH(G7,Прошедшие_годы,0)+1 -> #N/A
B7: Ключевые метрики | C7: =D7-1 -> 2020 | D7: =E7-1 -> 2021 | E7: =F7-1 -> 2022 | F7: =G7-1 -> 2023 | G7: =C3 -> 2024
A8: =MATCH(B8,Норникель!$B$6:$B$18,0) -> 4 | B8: =IF('Параметры ключевых метрик'!C3="","",'Параметры ключевых метрик'!C3) -> Итого выручка | C8: =IFERROR(INDEX(Норникель!$B$4:$G$18,$A8,C$6),NA()) -> #N/A | D8: =IFERROR(INDEX(Норникель!$B$4:$G$18,$A8,D$6),NA()) -> #N/A | E8: =IFERROR(INDEX(Норникель!$B$4:$G$18,$A8,E$6),NA()) -> #N/A | F8: =IFERROR(INDEX(Норникель!$B$4:$G$18,$A8,F$6),NA()) -> #N/A | G8: =IFERROR(INDEX(Норникель!$B$4:$G$18,$A8,G$6),NA()) -> #N/A | H8: =IFERROR(G8/F8-1,"")
A9: =MATCH(B9,Норникель!$B$6:$B$18,0) -> 7 | B9: =IF('Параметры ключевых метрик'!C4="","",'Параметры ключевых метрик'!C4) -> Валовая прибыль | C9: =IFERROR(INDEX(Норникель!$B$4:$G$18,$A9,C$6),NA()) -> #N/A | D9: =IFERROR(INDEX(Норникель!$B$4:$G$18,$A9,D$6),NA()) -> #N/A | E9: =IFERROR(INDEX(Норникель!$B$4:$G$18,$A9,E$6),NA()) -> #N/A | F9: =IFERROR(INDEX(Норникель!$B$4:$G$18,$A9,F$6),NA()) -> #N/A | G9: =IFERROR(INDEX(Норникель!$B$4:$G$18,$A9,G$6),NA()) -> #N/A | H9: =IFERROR(G9/F9-1,"")
A10: =MATCH(B10,Норникель!$B$6:$B$18,0) -> 12 | B10: =IF('Параметры ключевых метрик'!C5="","",'Параметры ключевых метрик'!C5) -> Прибыль от операционной деятельности | C10: =IFERROR(INDEX(Норникель!$B$4:$G$18,$A10,C$6),NA()) -> #N/A | D10: =IFERROR(INDEX(Норникель!$B$4:$G$18,$A10,D$6),NA()) -> #N/A | E10: =IFERROR(INDEX(Норникель!$B$4:$G$18,$A10,E$6),NA()) -> #N/A | F10: =IFERROR(INDEX(Норникель!$B$4:$G$18,$A10,F$6),NA()) -> #N/A | G10: =IFERROR(INDEX(Норникель!$B$4:$G$18,$A10,G$6),NA()) -> #N/A | H10: =IFERROR(G10/F10-1,"")
A11: =MATCH(B11,Норникель!$B$6:$B$18,0) -> #N/A | B11: =IF('Параметры ключевых метрик'!C6="","",'Параметры ключевых метрик'!C6) -> Прибыль до налогообложения | C11: =IFERROR(INDEX(Норникель!$B$4:$G$18,$A11,C$6),NA()) -> #N/A | D11: =IFERROR(INDEX(Норникель!$B$4:$G$18,$A11,D$6),NA()) -> #N/A | E11: =IFERROR(INDEX(Норникель!$B$4:$G$18,$A11,E$6),NA()) -> #N/A | F11: =IFERROR(INDEX(Норникель!$B$4:$G$18,$A11,F$6),NA()) -> #N/A | G11: =IFERROR(INDEX(Норникель!$B$4:$G$18,$A11,G$6),NA()) -> #N/A | H11: =IFERROR(G11/F11-1,"")
A12: =MATCH(B12,Норникель!$B$6:$B$18,0) -> #N/A | B12: =IF('Параметры ключевых метрик'!C7="","",'Параметры ключевых метрик'!C7) -> Прибыль за год | C12: =IFERROR(INDEX(Норникель!$B$4:$G$18,$A12,C$6),NA()) -> #N/A | D12: =IFERROR(INDEX(Норникель!$B$4:$G$18,$A12,D$6),NA()) -> #N/A | E12: =IFERROR(INDEX(Норникель!$B$4:$G$18,$A12,E$6),NA()) -> #N/A | F12: =IFERROR(INDEX(Норникель!$B$4:$G$18,$A12,F$6),NA()) -> #N/A | G12: =IFERROR(INDEX(Норникель!$B$4:$G$18,$A12,G$6),NA()) -> #N/A | H12: =IFERROR(G12/F12-1,"")
B14: Все метрики (можно определить до 25 метрик)
A15: =ROWS($B$15:B15) -> 1 | B15: =IF(Норникель!B6=0,"",Норникель!B6) -> Выручка | C15: =IF(B15="",NA(),IFERROR(INDEX(Норникель!$B$4:$G$23,$A15,C$6),NA())) -> #N/A | D15: =IF(B15="",NA(),IFERROR(INDEX(Норникель!$B$4:$G$23,$A15,D$6),NA())) -> #N/A | E15: =IF(B15="",NA(),IFERROR(INDEX(Норникель!$B$4:$G$23,$A15,E$6),NA())) -> #N/A | F15: =IF(B15="",NA(),IFERROR(INDEX(Норникель!$B$4:$G$23,$A15,F$6),NA())) -> #N/A | G15: =IF(B15="",NA(),IFERROR(INDEX(Норникель!$B$4:$G$23,$A15,G$6),NA())) -> #N/A
A16: =ROWS($B$15:B16) -> 2 | B16: =IF(Норникель!B7=0,"",Норникель!B7) -> Выручка от реализации металлов | C16: =IF(B16="",NA(),IFERROR(INDEX(Норникель!$B$4:$G$23,$A16,C$6),NA())) -> #N/A | D16: =IF(B16="",NA(),IFERROR(INDEX(Норникель!$B$4:$G$23,$A16,D$6),NA())) -> #N/A | E16: =IF(B16="",NA(),IFERROR(INDEX(Норникель!$B$4:$G$23,$A16,E$6),NA())) -> #N/A | F16: =IF(B16="",NA(),IFERROR(INDEX(Норникель!$B$4:$G$23,$A16,F$6),NA())) -> #N/A | G16: =IF(B16="",NA(),IFERROR(INDEX(Норникель!$B$4:$G$23,$A16,G$6),NA())) -> #N/A
A17: =ROWS($B$15:B17) -> 3 | B17: =IF(Норникель!B8=0,"",Норникель!B8) -> Выручка от прочей реализации | C17: =IF(B17="",NA(),IFERROR(INDEX(Норникель!$B$4:$G$23,$A17,C$6),NA())) -> #N/A | D17: =IF(B17="",NA(),IFERROR(INDEX(Норникель!$B$4:$G$23,$A17,D$6),NA())) -> #N/A | E17: =IF(B17="",NA(),IFERROR(INDEX(Норникель!$B$4:$G$23,$A17,E$6),NA())) -> #N/A | F17: =IF(B17="",NA(),IFERROR(INDEX(Норникель!$B$4:$G$23,$A17,F$6),NA())) -> #N/A | G17: =IF(B17="",NA(),IFERROR(INDEX(Норникель!$B$4:$G$23,$A17,G$6),NA())) -> #N/A
A18: =ROWS($B$15:B18) -> 4 | B18: =IF(Норникель!B9=0,"",Норникель!B9) -> Итого выручка | C18: =IF(B18="",NA(),IFERROR(INDEX(Норникель!$B$4:$G$23,$A18,C$6),NA())) -> #N/A | D18: =IF(B18="",NA(),IFERROR(INDEX(Норникель!$B$4:$G$23,$A18,D$6),NA())) -> #N/A | E18: =IF(B18="",NA(),IFERROR(INDEX(Норникель!$B$4:$G$23,$A18,E$6),NA())) -> #N/A | F18: =IF(B18="",NA(),IFERROR(INDEX(Норникель!$B$4:$G$23,$A18,F$6),NA())) -> #N/A | G18: =IF(B18="",NA(),IFERROR(INDEX(Норникель!$B$4:$G$23,$A18,G$6),NA())) -> #N/A
A19: =ROWS($B$15:B19) -> 5 | B19: =IF(Норникель!B10=0,"",Норникель!B10) -> Себестоимость реализованных металлов | C19: =IF(B19="",NA(),IFERROR(INDEX(Норникель!$B$4:$G$23,$A19,C$6),NA())) -> #N/A | D19: =IF(B19="",NA(),IFERROR(INDEX(Норникель!$B$4:$G$23,$A19,D$6),NA())) -> #N/A | E19: =IF(B19="",NA(),IFERROR(INDEX(Норникель!$B$4:$G$23,$A19,E$6),NA())) -> #N/A | F19: =IF(B19="",NA(),IFERROR(INDEX(Норникель!$B$4:$G$23,$A19,F$6),NA())) -> #N/A | G19: =IF(B19="",NA(),IFERROR(INDEX(Норникель!$B$4:$G$23,$A19,G$6),NA())) -> #N/A
A20: =ROWS($B$15:B20) -> 6 | B20: =IF(Норникель!B11=0,"",Норникель!B11) -> Себестоимость прочей реализации | C20: =IF(B20="",NA(),IFERROR(INDEX(Норникель!$B$4:$G$23,$A20,C$6),NA())) -> #N/A | D20: =IF(B20="",NA(),IFERROR(INDEX(Норникель!$B$4:$G$23,$A20,D$6),NA())) -> #N/A | E20: =IF(B20="",NA(),IFERROR(INDEX(Норникель!$B$4:$G$23,$A20,E$6),NA())) -> #N/A | F20: =IF(B20="",NA(),IFERROR(INDEX(Норникель!$B$4:$G$23,$A20,F$6),NA())) -> #N/A | G20: =IF(B20="",NA(),IFERROR(INDEX(Норникель!$B$4:$G$23,$A20,G$6),NA())) -> #N/A
A21: =ROWS($B$15:B21) -> 7 | B21: =IF(Норникель!B12=0,"",Норникель!B12) -> Валовая прибыль | C21: =IF(B21="",NA(),IFERROR(INDEX(Норникель!$B$4:$G$23,$A21,C$6),NA())) -> #N/A | D21: =IF(B21="",NA(),IFERROR(INDEX(Норникель!$B$4:$G$23,$A21,D$6),NA())) -> #N/A | E21: =IF(B21="",NA(),IFERROR(INDEX(Норникель!$B$4:$G$23,$A21,E$6),NA())) -> #N/A | F21: =IF(B21="",NA(),IFERROR(INDEX(Норникель!$B$4:$G$23,$A21,F$6),NA())) -> #N/A | G21: =IF(B21="",NA(),IFERROR(INDEX(Норникель!$B$4:$G$23,$A21,G$6),NA())) -> #N/A
A22: =ROWS($B$15:B22) -> 8 | B22: =IF(Норникель!B13=0,"",Норникель!B13) -> Административные расходы | C22: =IF(B22="",NA(),IFERROR(INDEX(Норникель!$B$4:$G$23,$A22,C$6),NA())) -> #N/A | D22: =IF(B22="",NA(),IFERROR(INDEX(Норникель!$B$4:$G$23,$A22,D$6),NA())) -> #N/A | E22: =IF(B22="",NA(),IFERROR(INDEX(Норникель!$B$4:$G$23,$A22,E$6),NA())) -> #N/A | F22: =IF(B22="",NA(),IFERROR(INDEX(Норникель!$B$4:$G$23,$A22,F$6),NA())) -> #N/A | G22: =IF(B22="",NA(),IFERROR(INDEX(Норникель!$B$4:$G$23,$A22,G$6),NA())) -> #N/A
A23: =ROWS($B$15:B23) -> 9 | B23: =IF(Норникель!B14=0,"",Норникель!B14) -> Коммерческие расходы | C23: =IF(B23="",NA(),IFERROR(INDEX(Норникель!$B$4:$G$23,$A23,C$6),NA())) -> #N/A | D23: =IF(B23="",NA(),IFERROR(INDEX(Норникель!$B$4:$G$23,$A23,D$6),NA())) -> #N/A | E23: =IF(B23="",NA(),IFERROR(INDEX(Норникель!$B$4:$G$23,$A23,E$6),NA())) -> #N/A | F23: =IF(B23="",NA(),IFERROR(INDEX(Норникель!$B$4:$G$23,$A23,F$6),NA())) -> #N/A | G23: =IF(B23="",NA(),IFERROR(INDEX(Норникель!$B$4:$G$23,$A23,G$6),NA())) -> #N/A
A24: =ROWS($B$15:B24) -> 10 | B24: =IF(Норникель!B15=0,"",Норникель!B15) -> Убыток от обесценения нефинансовых активов, нетто | C24: =IF(B24="",NA(),IFERROR(INDEX(Норникель!$B$4:$G$23,$A24,C$6),NA())) -> #N/A | D24: =IF(B24="",NA(),IFERROR(INDEX(Норникель!$B$4:$G$23,$A24,D$6),NA())) -> #N/A | E24: =IF(B24="",NA(),IFERROR(INDEX(Норникель!$B$4:$G$23,$A24,E$6),NA())) -> #N/A | F24: =IF(B24="",NA(),IFERROR(INDEX(Норникель!$B$4:$G$23,$A24,F$6),NA())) -> #N/A | G24: =IF(B24="",NA(),IFERROR(INDEX(Норникель!$B$4:$G$23,$A24,G$6),NA())) -> #N/A
A25: =ROWS($B$15:B25) -> 11 | B25: =IF(Норникель!#REF!=0,"",Норникель!#REF!) -> #REF! | C25: =IF(B25="",NA(),IFERROR(INDEX(Норникель!$B$4:$G$23,$A25,C$6),NA())) -> #REF! | D25: =IF(B25="",NA(),IFERROR(INDEX(Норникель!$B$4:$G$23,$A25,D$6),NA())) -> #REF! | E25: =IF(B25="",NA(),IFERROR(INDEX(Норникель!$B$4:$G$23,$A25,E$6),NA())) -> #REF! | F25: =IF(B25="",NA(),IFERROR(INDEX(Норникель!$B$4:$G$23,$A25,F$6),NA())) -> #REF! | G25: =IF(B25="",NA(),IFERROR(INDEX(Норникель!$B$4:$G$23,$A25,G$6),NA())) -> #REF!
A26: =ROWS($B$15:B26) -> 12 | B26: =IF(Норникель!B16=0,"",Норникель!B16) -> Прочие операционные расходы, нетто | C26: =IF(B26="",NA(),IFERROR(INDEX(Норникель!$B$4:$G$23,$A26,C$6),NA())) -> #N/A | D26: =IF(B26="",NA(),IFERROR(INDEX(Норникель!$B$4:$G$23,$A26,D$6),NA())) -> #N/A | E26: =IF(B26="",NA(),IFERROR(INDEX(Норникель!$B$4:$G$23,$A26,E$6),NA())) -> #N/A | F26: =IF(B26="",NA(),IFERROR(INDEX(Норникель!$B$4:$G$23,$A26,F$6),NA())) -> #N/A | G26: =IF(B26="",NA(),IFERROR(INDEX(Норникель!$B$4:$G$23,$A26,G$6),NA())) -> #N/A
A27: =ROWS($B$15:B27) -> 13 | B27: =IF(Норникель!B17=0,"",Норникель!B17) -> Прибыль от операционной деятельности | C27: =IF(B27="",NA(),IFERROR(INDEX(Норникель!$B$4:$G$23,$A27,C$6),NA())) -> #N/A | D27: =IF(B27="",NA(),IFERROR(INDEX(Норникель!$B$4:$G$23,$A27,D$6),NA())) -> #N/A | E27: =IF(B27="",NA(),IFERROR(INDEX(Норникель!$B$4:$G$23,$A27,E$6),NA())) -> #N/A | F27: =IF(B27="",NA(),IFERROR(INDEX(Норникель!$B$4:$G$23,$A27,F$6),NA())) -> #N/A | G27: =IF(B27="",NA(),IFERROR(INDEX(Норникель!$B$4:$G$23,$A27,G$6),NA())) -> #N/A
A28: =ROWS($B$15:B28) -> 14 | B28: =IF(Норникель!B18=0,"",Норникель!B18) -> (Отрицательные)/положительные курсовые разницы, нетто | C28: =IF(B28="",NA(),IFERROR(INDEX(Норникель!$B$4:$G$23,$A28,C$6),NA())) -> #N/A | D28: =IF(B28="",NA(),IFERROR(INDEX(Норникель!$B$4:$G$23,$A28,D$6),NA())) -> #N/A | E28: =IF(B28="",NA(),IFERROR(INDEX(Норникель!$B$4:$G$23,$A28,E$6),NA())) -> #N/A | F28: =IF(B28="",NA(),IFERROR(INDEX(Норникель!$B$4:$G$23,$A28,F$6),NA())) -> #N/A | G28: =IF(B28="",NA(),IFERROR(INDEX(Норникель!$B$4:$G$23,$A28,G$6),NA())) -> #N/A
A29: =ROWS($B$15:B29) -> 15 | B29: =IF(Норникель!#REF!=0,"",Норникель!#REF!) -> #REF! | C29: =IF(B29="",NA(),IFERROR(INDEX(Норникель!$B$4:$G$23,$A29,C$6),NA())) -> #REF! | D29: =IF(B29="",NA(),IFERROR(INDEX(Норникель!$B$4:$G$23,$A29,D$6),NA())) -> #REF! | E29: =IF(B29="",NA(),IFERROR(INDEX(Норникель!$B$4:$G$23,$A29,E$6),NA())) -> #REF! | F29: =IF(B29="",NA(),IFERROR(INDEX(Норникель!$B$4:$G$23,$A29,F$6),NA())) -> #REF! | G29: =IF(B29="",NA(),IFERROR(INDEX(Норникель!$B$4:$G$23,$A29,G$6),NA())) -> #REF!
A30: =ROWS($B$15:B30) -> 16 | B30: =IF(Норникель!B19=0,"",Норникель!B19) -> Финансовые расходы, нетто | C30: =IF(B30="",NA(),IFERROR(INDEX(Норникель!$B$4:$G$23,$A30,C$6),NA())) -> #N/A | D30: =IF(B30="",NA(),IFERROR(INDEX(Норникель!$B$4:$G$23,$A30,D$6),NA())) -> #N/A | E30: =IF(B30="",NA(),IFERROR(INDEX(Норникель!$B$4:$G$23,$A30,E$6),NA())) -> #N/A | F30: =IF(B30="",NA(),IFERROR(INDEX(Норникель!$B$4:$G$23,$A30,F$6),NA())) -> #N/A | G30: =IF(B30="",NA(),IFERROR(INDEX(Норникель!$B$4:$G$23,$A30,G$6),NA())) -> #N/A
A31: =ROWS($B$15:B31) -> 17 | B31: =IF(Норникель!B20=0,"",Норникель!B20) -> Прибыль/(убыток) от выбытия дочерних организаций и зарубежных совместных операций | C31: =IF(B31="",NA(),IFERROR(INDEX(Норникель!$B$4:$G$23,$A31,C$6),NA())) -> #N/A | D31: =IF(B31="",NA(),IFERROR(INDEX(Норникель!$B$4:$G$23,$A31,D$6),NA())) -> #N/A | E31: =IF(B31="",NA(),IFERROR(INDEX(Норникель!$B$4:$G$23,$A31,E$6),NA())) -> #N/A | F31: =IF(B31="",NA(),IFERROR(INDEX(Норникель!$B$4:$G$23,$A31,F$6),NA())) -> #N/A | G31: =IF(B31="",NA(),IFERROR(INDEX(Норникель!$B$4:$G$23,$A31,G$6),NA())) -> #N/A
A32: =ROWS($B$15:B32) -> 18 | B32: =IF(Норникель!#REF!=0,"",Норникель!#REF!) -> #REF! | C32: =IF(B32="",NA(),IFERROR(INDEX(Норникель!$B$4:$G$23,$A32,C$6),NA())) -> #REF! | D32: =IF(B32="",NA(),IFERROR(INDEX(Норникель!$B$4:$G$23,$A32,D$6),NA())) -> #REF! | E32: =IF(B32="",NA(),IFERROR(INDEX(Норникель!$B$4:$G$23,$A32,E$6),NA())) -> #REF! | F32: =IF(B32="",NA(),IFERROR(INDEX(Норникель!$B$4:$G$23,$A32,F$6),NA())) -> #REF! | G32: =IF(B32="",NA(),IFERROR(INDEX(Норникель!$B$4:$G$23,$A32,G$6),NA())) -> #REF!
A33: =ROWS($B$15:B33) -> 19 | B33: =IF(Норникель!B21=0,"",Норникель!B21) -> Прибыль от инвестиционной деятельности, нетто | C33: =IF(B33="",NA(),IFERROR(INDEX(Норникель!$B$4:$G$23,$A33,C$6),NA())) -> #N/A | D33: =IF(B33="",NA(),IFERROR(INDEX(Норникель!$B$4:$G$23,$A33,D$6),NA())) -> #N/A | E33: =IF(B33="",NA(),IFERROR(INDEX(Норникель!$B$4:$G$23,$A33,E$6),NA())) -> #N/A | F33: =IF(B33="",NA(),IFERROR(INDEX(Норникель!$B$4:$G$23,$A33,F$6),NA())) -> #N/A | G33: =IF(B33="",NA(),IFERROR(INDEX(Норникель!$B$4:$G$23,$A33,G$6),NA())) -> #N/A
A34: =ROWS($B$15:B34) -> 20 | B34: =IF(Норникель!B22=0,"",Норникель!B22) -> Прибыль до налогообложения | C34: =IF(B34="",NA(),IFERROR(INDEX(Норникель!$B$4:$G$23,$A34,C$6),NA())) -> #N/A | D34: =IF(B34="",NA(),IFERROR(INDEX(Норникель!$B$4:$G$23,$A34,D$6),NA())) -> #N/A | E34: =IF(B34="",NA(),IFERROR(INDEX(Норникель!$B$4:$G$23,$A34,E$6),NA())) -> #N/A | F34: =IF(B34="",NA(),IFERROR(INDEX(Норникель!$B$4:$G$23,$A34,F$6),NA())) -> #N/A | G34: =IF(B34="",NA(),IFERROR(INDEX(Норникель!$B$4:$G$23,$A34,G$6),NA())) -> #N/A
A35: =ROWS($B$15:B35) -> 21 | B35: =IF(Норникель!B23=0,"",Норникель!B23) -> Расходы по налогу на прибыль | C35: =IF(B35="",NA(),IFERROR(INDEX(Норникель!$B$4:$G$23,$A35,C$6),NA())) -> #N/A | D35: =IF(B35="",NA(),IFERROR(INDEX(Норникель!$B$4:$G$23,$A35,D$6),NA())) -> #N/A | E35: =IF(B35="",NA(),IFERROR(INDEX(Норникель!$B$4:$G$23,$A35,E$6),NA())) -> #N/A | F35: =IF(B35="",NA(),IFERROR(INDEX(Норникель!$B$4:$G$23,$A35,F$6),NA())) -> #N/A | G35: =IF(B35="",NA(),IFERROR(INDEX(Норникель!$B$4:$G$23,$A35,G$6),NA())) -> #N/A
A36: =ROWS($B$15:B36) -> 22 | B36: =IF(Норникель!B24=0,"",Норникель!B24) -> Прибыль за год | C36: =IF(B36="",NA(),IFERROR(INDEX(Норникель!$B$4:$G$23,$A36,C$6),NA())) -> #N/A | D36: =IF(B36="",NA(),IFERROR(INDEX(Норникель!$B$4:$G$23,$A36,D$6),NA())) -> #N/A | E36: =IF(B36="",NA(),IFERROR(INDEX(Норникель!$B$4:$G$23,$A36,E$6),NA())) -> #N/A | F36: =IF(B36="",NA(),IFERROR(INDEX(Норникель!$B$4:$G$23,$A36,F$6),NA())) -> #N/A | G36: =IF(B36="",NA(),IFERROR(INDEX(Норникель!$B$4:$G$23,$A36,G$6),NA())) -> #N/A
A37: =ROWS($B$15:B37) -> 23 | B37: =IF(Норникель!#REF!=0,"",Норникель!#REF!) -> #REF! | C37: =IF(B37="",NA(),IFERROR(INDEX(Норникель!$B$4:$G$23,$A37,C$6),NA())) -> #REF! | D37: =IF(B37="",NA(),IFERROR(INDEX(Норникель!$B$4:$G$23,$A37,D$6),NA())) -> #REF! | E37: =IF(B37="",NA(),IFERROR(INDEX(Норникель!$B$4:$G$23,$A37,E$6),NA())) -> #REF! | F37: =IF(B37="",NA(),IFERROR(INDEX(Норникель!$B$4:$G$23,$A37,F$6),NA())) -> #REF! | G37: =IF(B37="",NA(),IFERROR(INDEX(Норникель!$B$4:$G$23,$A37,G$6),NA())) -> #REF!
A38: =ROWS($B$15:B38) -> 24 | B38: =IF(Норникель!#REF!=0,"",Норникель!#REF!) -> #REF! | C38: =IF(B38="",NA(),IFERROR(INDEX(Норникель!$B$4:$G$23,$A38,C$6),NA())) -> #REF! | D38: =IF(B38="",NA(),IFERROR(INDEX(Норникель!$B$4:$G$23,$A38,D$6),NA())) -> #REF! | E38: =IF(B38="",NA(),IFERROR(INDEX(Норникель!$B$4:$G$23,$A38,E$6),NA())) -> #REF! | F38: =IF(B38="",NA(),IFERROR(INDEX(Норникель!$B$4:$G$23,$A38,F$6),NA())) -> #REF! | G38: =IF(B38="",NA(),IFERROR(INDEX(Норникель!$B$4:$G$23,$A38,G$6),NA())) -> #REF!
A39: =ROWS($B$15:B39) -> 25 | B39: =IF(Норникель!#REF!=0,"",Норникель!#REF!) -> #REF! | C39: =IF(B39="",NA(),IFERROR(INDEX(Норникель!$B$4:$G$23,$A39,C$6),NA())) -> #REF! | D39: =IF(B39="",NA(),IFERROR(INDEX(Норникель!$B$4:$G$23,$A39,D$6),NA())) -> #REF! | E39: =IF(B39="",NA(),IFERROR(INDEX(Норникель!$B$4:$G$23,$A39,E$6),NA())) -> #REF! | F39: =IF(B39="",NA(),IFERROR(INDEX(Норникель!$B$4:$G$23,$A39,F$6),NA())) -> #REF! | G39: =IF(B39="",NA(),IFERROR(INDEX(Норникель!$B$4:$G$23,$A39,G$6),NA())) -> #REF!

Sheet Построение графиков
B1: 2021 | C1: 2022 | D1: 2023 | E1: 2024
A2: Запасы | B2: 3026 | C2: 4945 | D2: 3817 | E2: 3114
A3: Прочее | B3: 829 | C3: 730 | D3: 622 | E3: 535
A4: Торг. и пр. ДЗ | B4: 468 | C4: 846 | D4: 764 | E4: 1374
A5: ДС и их экв. | B5: 5547 | C5: 1882 | D5: 2139 | E5: 1822
B7: 2021 | C7: 2022 | D7: 2023 | E7: 2024
A8: Норникель | B8: 0.84671533 | C8: 0.44973339 | D8: 0.39916204 | E8: 0.63034296
A9: Vale | B9: 1.1457926 | C9: 0.79504715 | D9: 0.71541081 | E9: 0.67807487
A10: Anglo American | B10: 0.90644259 | C10: 1.0354824 | D10: 0.96359104 | E10: 0.74612536
A11: Impala | B11: 1.9086719 | C11: 2.1873154 | D11: 2.458239 | E11: 1.425374
A12: мин, желаемое значение | B12: 1 | C12: 1 | D12: 1 | E12: 1
B14: 2021 | C14: 2022 | D14: 2023 | E14: 2024 | F14: 2021 | G14: 2022 | H14: 2023 | I14: 2024
A15: Норникель | B15: 17852 | C15: 16876 | D15: 14409 | E15: 12535 | F15: =B15/$B15 -> 1 | G15: =C15/$B15 -> 0.94532825 | H15: =D15/$B15 -> 0.80713646 | I15: =E15/$B15 -> 0.70216222
A16: Vale | B16: 54502 | C16: 43839 | D16: 41784 | E16: 38056 | F16: =B16/$B16 -> 1 | G16: =C16/$B16 -> 0.8043558 | H16: =D16/$B16 -> 0.76665077 | I16: =E16/$B16 -> 0.69824961
A17: Anglo American | B17: 13932.987 | C17: 10781.209 | D17: 7010.861 | E17: 5825.0668 | F17: =B17/$B17 -> 1 | G17: =C17/$B17 -> 0.77379021 | H17: =D17/$B17 -> 0.50318435 | I17: =E17/$B17 -> 0.41807739
A18: Impala | B18: 8413.961 | C18: 7774.77 | D18: 5998.5369 | E18: 4617.7445 | F18: =B18/$B18 -> 1 | G18: =C18/$B18 -> 0.92403209 | H18: =D18/$B18 -> 0.71292663 | I18: =E18/$B18 -> 0.54881934
A36: Коэффициенты рентабельности
A37: PBIT | B37: 9536 | C37: 7581 | D37: 5540 | E37: 3574 | G37: 27693 | H37: 17208 | I37: 14205 | J37: 10788 | L37: 6825.4545 | M37: 4632.8515 | N37: 1182.4986 | O37: 973.7039 | Q37: 3471.1039 | R37: 2712.5493 | S37: 1257.0625 | T37: 292.19669
A38: Активы | B38: 23435 | C38: 25795 | D38: 23580 | E38: 23170 | G38: 89442 | H38: 86894 | I38: 94186 | J38: 80152 | L38: 12580.237 | M38: 10873.632 | N38: 8976.9231 | O38: 9397.6361 | Q38: 8832.0531 | R38: 9593.5464 | S38: 8985.9947 | T38: 7309.2358
A39: Краткосрочные обязательства | B39: 8083 | C39: 7689 | D39: 8831 | E39: 5919 | G39: 15198 | H39: 13891 | I39: 14655 | J39: 1309 | L39: 3943.2961 | M39: 3568.3467 | N39: 2490.1326 | O39: 2479.4393 | Q39: 1242.5279 | R39: 1019.4837 | S39: 937.50663 | T39: 926.0033
A40: Задействованный капитал (CE) | B40: 15352 | C40: 18106 | D40: 14749 | E40: 17251 | G40: 74244 | H40: 73003 | I40: 79531 | J40: 78843 | L40: 8636.9413 | M40: 7305.2858 | N40: 6486.7905 | O40: 6918.1968 | Q40: 7589.5251 | R40: 8574.0627 | S40: 8048.4881 | T40: 6383.2325
A41: Рентабельность задействованного капитала (ROCE) | B41: 0.62115685 | C41: 0.41870098 | D41: 0.37561869 | E41: 0.2071764 | G41: 0.37299984 | H41: 0.23571634 | I41: 0.1786096 | J41: 0.13682889 | L41: 0.79026293 | M41: 0.634178 | N41: 0.18229332 | O41: 0.14074533 | Q41: 0.45735456 | R41: 0.31636686 | S41: 0.15618616 | T41: 0.045775661
A42: Валовая прибыль | B42: 12042 | C42: 9963 | D42: 7377 | E42: 5647 | G42: 32773 | H42: 19811 | I42: 17695 | J42: 13791 | L42: 6825.4545 | M42: 4632.8515 | N42: 1182.4986 | O42: 973.7039 | Q42: 3471.1039 | R42: 2712.5493 | S42: 1257.0625 | T42: 292.19669
A43: Выручка | B43: 17852 | C43: 16876 | D43: 14409 | E43: 12535 | G43: 54502 | H43: 43839 | I43: 41784 | J43: 38056 | L43: 13932.987 | M43: 10781.209 | N43: 7010.861 | O43: 5825.0668 | Q43: 8413.961 | R43: 7774.77 | S43: 5998.5369 | T43: 4617.7445
A44: Маржа валовой прибыли (Gross profit margin) | B44: 0.67454627 | C44: 0.59036502 | D44: 0.51197168 | E44: 0.4504986 | G44: 0.60131738 | H44: 0.45190356 | I44: 0.42348746 | J44: 0.36238701 | L44: 0.48987733 | M44: 0.4297154 | N44: 0.16866667 | O44: 0.16715755 | Q44: 0.412541 | R44: 0.34889126 | S44: 0.20956151 | T44: 0.063276928
A45: Чистая прибыль | B45: 6974 | C45: 5854 | D45: 2870 | E45: 1815 | G45: 24844 | H45: 16810 | I45: 8105 | J45: 6166 | L45: 5131.2338 | M45: 3238.8962 | N45: 756.66854 | O45: 395.13629 | Q45: 3107.4675 | R45: 2177.3325 | S45: 347.6646 | T45: -916.67557
A46: Выручка | B46: 17852 | C46: 16876 | D46: 14409 | E46: 12535 | G46: 54502 | H46: 43839 | I46: 41784 | J46: 38056 | L46: 13932.987 | M46: 10781.209 | N46: 7010.861 | O46: 5825.0668 | Q46: 8413.961 | R46: 7774.77 | S46: 5998.5369 | T46: 4617.7445
A47: Маржа чистой прибыли (Net profit margin) | B47: 0.39065651 | C47: 0.34688315 | D47: 0.19918107 | E47: 0.14479458 | G47: 0.45583648 | H47: 0.38344853 | I47: 0.19397377 | J47: 0.16202439 | L47: 0.36827952 | M47: 0.3004205 | N47: 0.10792805 | O47: 0.067833778 | Q47: 0.36932279 | R47: 0.28005104 | S47: 0.057958234 | T47: -0.19851154
A48: Чистая прибыль | B48: 6974 | C48: 5854 | D48: 2870 | E48: 1815 | G48: 24844 | H48: 16810 | I48: 8105 | J48: 6166 | L48: 5131.2338 | M48: 3238.8962 | N48: 756.66854 | O48: 395.13629 | Q48: 3107.4675 | R48: 2177.3325 | S48: 347.6646 | T48: -916.67557
... A52: Активы | B52: 23435 | C52: 0 | D52: 23580 | E52: 23170 | G52: 89442 | H52: 86894 | I52: 94186 | J52: 80152 | L52: 12580.237 | M52: 10873.632 | N52: 8976.9231 | O52: 9397.6361 | Q52: 8832.0531 | R52: 9593.5464 | S52: 8985.9947 | T52: 7309.2358
A53: Средняя величина активов | C53: 11717.5 | D53: 11790 | E53: 23375 | H53: 88168 | I53: 90540 | J53: 87169 | M53: 11726.935 | N53: 9925.2778 | O53: 9187.2796 | R53: 9212.7997 | S53: 9289.7705 | T53: 8147.6153
A54: Рентабельность собственных активов (ROA) | C54: 0.49959462 | D54: 0.24342663 | E54: 0.077647059 | H54: 0.19065874 | I54: 0.089518445 | J54: 0.070736156 | M54: 0.2761929 | N54: 0.07623651 | O54: 0.043009064 | R54: 0.23633776 | S54: 0.037424455 | T54: -0.11250845
A55: Выручка | B55: 17852 | C55: 16876 | D55: 14409 | E55: 12535 | G55: 54502 | H55: 43839 | I55: 41784 | J55: 38056 | L55: 13932.987 | M55: 10781.209 | N55: 7010.861 | O55: 5825.0668 | Q55: 8413.961 | R55: 7774.77 | S55: 5998.5369 | T55: 4617.7445
A56: Активы | B56: 23435 | C56: 25795 | D56: 23580 | E56: 23170 | G56: 89442 | H56: 86894 | I56: 94186 | J56: 80152 | L56: 12580.237 | M56: 10873.632 | N56: 8976.9231 | O56: 9397.6361 | Q56: 8832.0531 | R56: 9593.5464 | S56: 8985.9947 | T56: 7309.2358
A57: Средняя величина активов | C57: 24615 | D57: 24687.5 | E57: 23375 | H57: 88168 | I57: 90540 | J57: 87169 | M57: 11726.935 | N57: 9925.2778 | O57: 9187.2796 | R57: 9212.7997 | S57: 9289.7705 | T57: 8147.6153
A58: Оборачиваемость активов (asset turnover) | C58: 0.68559821 | D58: 0.5836557 | E58: 0.53625668 | H58: 0.49722121 | I58: 0.46149768 | J58: 0.43657722 | M58: 0.91935437 | N58: 0.70636421 | O58: 0.63403609 | R58: 0.84390959 | S58: 0.64571421 | T58: 0.56676026
A62: Рентабельность задействованного капитала (ROCE)
B63: 2021 | C63: 2022 | D63: 2023 | E63: 2024
A64: Норникель | B64: 0.62115685 | C64: 0.41870098 | D64: 0.37561869 | E64: 0.2071764
A65: Vale | B65: 0.37299984 | C65: 0.23571634 | D65: 0.1786096 | E65: 0.13682889
A66: Anglo American | B66: 0.79026293 | C66: 0.634178 | D66: 0.18229332 | E66: 0.14074533
A67: Impala | B67: 0.45735456 | C67: 0.31636686 | D67: 0.15618616 | E67: 0.045775661
A68: мин, желаемое значение
A70: Маржа валовой прибыли (Gross profit margin)
B71: 2021 | C71: 2022 | D71: 2023 | E71: 2024
A72: Норникель | B72: 0.67454627 | C72: 0.59036502 | D72: 0.51197168 | E72: 0.4504986
A73: Vale | B73: 0.60131738 | C73: 0.45190356 | D73: 0.42348746 | E73: 0.36238701
A74: Anglo American | B74: 0.48987733 | C74: 0.4297154 | D74: 0.16866667 | E74: 0.16715755
A75: Impala | B75: 0.412541 | C75: 0.34889126 | D75: 0.20956151 | E75: 0.063276928
A76: мин, желаемое значение | B76: 0.2 | C76: 0.2 | D76: 0.2 | E76: 0.2
A78: Маржа чистой прибыли (Net profit margin)
B79: 2021 | C79: 2022 | D79: 2023 | E79: 2024
A80: Норникель | B80: 0.39065651 | C80: 0.34688315 | D80: 0.19918107 | E80: 0.14479458
A81: Vale | B81: 0.45583648 | C81: 0.38344853 | D81: 0.19397377 | E81: 0.16202439
A82: Anglo American | B82: 0.36827952 | C82: 0.3004205 | D82: 0.10792805 | E82: 0.067833778
A83: Impala | B83: 0.36932279 | C83: 0.28005104 | D83: 0.057958234 | E83: -0.19851154
A84: мин, желаемое значение | B84: 0.15 | C84: 0.15 | D84: 0.15 | E84: 0.15
A86: Рентабельность собственного капитала (ROE)
B87: 2021 | C87: 2022 | D87: 2023 | E87: 2024
A88: Норникель | B88: 1.4565581 | C88: 0.68331972 | D88: 0.37788018 | E88: 0.2241571
A89: Vale | B89: 0.70367643 | C89: 0.44997056 | D89: 0.19777458 | E89: 0.1785797
A90: Anglo American | B90: 0.71792152 | C90: 0.54347931 | D90: 0.14258212 | E90: 0.070387993
A91: Impala | B91: 2.100096 | C91: 1.5348873 | D91: 0.25382384 | E91: -0.53622102
A92: мин, желаемое значение | B92: 0.12 | C92: 0.12 | D92: 0.12 | E92: 0.12
A94: Рентабельность собственных активов (ROA)
B95: 2022 | C95: 2023 | D95: 2024
A96: Норникель | B96: 0.25 | C96: 0.24342663 | D96: 0.077647059
A97: Vale | B97: 0.49722121 | C97: 0.46149768 | D97: 0.43657722
A98: Anglo American | B98: 0.91935437 | C98: 0.70636421 | D98: 0.63403609
A99: Impala | B99: 0.23633776 | C99: 0.037424455 | D99: -0.11250845
A100: мин, желаемое значение | B100: 0.05 | C100: 0.05 | D100: 0.05
A102: Оборачиваемость активов (asset turnover)
B103: 2022 | C103: 2023 | D103: 2024
A104: Норникель | B104: 0.68559821 | C104: 0.5836557 | D104: 0.53625668
A105: Vale | B105: 0.19065874 | C105: 0.089518445 | D105: 0.070736156
A106: Anglo American | B106: 0.2761929 | C106: 0.07623651 | D106: 0.043009064
A107: Impala | B107: 0.84390959 | C107: 0.64571421 | D107: 0.56676026
A108: мин, желаемое значение
